Workbook

Sheet Year
Z1: =YEAR(TODAY()) -> 2026 | AA1: Create more with themes Go to Format >> Theme
B2: JANUARY | J2: FEBRUARY | R2: MARCH
B3: S | C3: M | D3: T | E3: W | F3: T | G3: F | H3: S | J3: S | K3: M | L3: T | M3: W | N3: T | O3: F | P3: S | R3: S | S3: M | T3: T | U3: W | V3: T | W3: F | X3: S
B4: =IF(WEEKDAY(DATEVALUE($Z$1&$B$2&1))=1,1,"") | C4: =IF(B4<>"",B4+1,IF(WEEKDAY(DATEVALUE($Z$1&$B$2&1))=2,1,"")) | D4: =IF(C4<>"",C4+1,IF(WEEKDAY(DATEVALUE($Z$1&$B$2&1))=3,1,"")) | E4: =IF(D4<>"",D4+1,IF(WEEKDAY(DATEVALUE($Z$1&$B$2&1))=4,1,"")) | F4: =IF(E4<>"",E4+1,IF(WEEKDAY(DATEVALUE($Z$1&$B$2&1))=5,1,"")) -> 1 | G4: =IF(F4<>"",F4+1,IF(WEEKDAY(DATEVALUE($Z$1&$B$2&1))=6,1,"")) -> 2 | H4: =IF(G4<>"",G4+1,IF(WEEKDAY(DATEVALUE($Z$1&$B$2&1))=7,1,"")) -> 3 | J4: =IF(WEEKDAY(DATEVALUE($Z$1&$J$2&1))=1,1,"") -> 1 | K4: =IF(J4<>"",J4+1,IF(WEEKDAY(DATEVALUE($Z$1&$J$2&1))=2,1,"")) -> 2 | L4: =IF(K4<>"",K4+1,IF(WEEKDAY(DATEVALUE($Z$1&$J$2&1))=3,1,"")) -> 3 | M4: =IF(L4<>"",L4+1,IF(WEEKDAY(DATEVALUE($Z$1&$J$2&1))=4,1,"")) -> 4 | N4: =IF(M4<>"",M4+1,IF(WEEKDAY(DATEVALUE($Z$1&$J$2&1))=5,1,"")) -> 5 | O4: =IF(N4<>"",N4+1,IF(WEEKDAY(DATEVALUE($Z$1&$J$2&1))=6,1,"")) -> 6 | P4: =IF(O4<>"",O4+1,IF(WEEKDAY(DATEVALUE($Z$1&$J$2&1))=7,1,"")) -> 7 | R4: =IF(WEEKDAY(DATEVALUE($Z$1&$R$2&1))=1,1,"") -> 1 | S4: =IF(R4<>"",R4+1,IF(WEEKDAY(DATEVALUE($Z$1&$R$2&1))=2,1,"")) -> 2 | T4: =IF(S4<>"",S4+1,IF(WEEKDAY(DATEVALUE($Z$1&$R$2&1))=3,1,"")) -> 3 | U4: =IF(T4<>"",T4+1,IF(WEEKDAY(DATEVALUE($Z$1&$R$2&1))=4,1,"")) -> 4 | V4: =IF(U4<>"",U4+1,IF(WEEKDAY(DATEVALUE($Z$1&$R$2&1))=5,1,"")) -> 5 | W4: =IF(V4<>"",V4+1,IF(WEEKDAY(DATEVALUE($Z$1&$R$2&1))=6,1,"")) -> 6 | X4: =IF(W4<>"",W4+1,IF(WEEKDAY(DATEVALUE($Z$1&$R$2&1))=7,1,"")) -> 7
B5: =IF(OR(H4="",VALUE(H4)>EOMONTH(DATEVALUE($Z$1&$B$2&1),0)-EOMONTH(DATEVALUE($Z$1&$B$2&1),-1)-1),"",H4+1) -> 4 | C5: =IF(OR(B5="",VALUE(B5)>EOMONTH(DATEVALUE($Z$1&$B$2&1),0)-EOMONTH(DATEVALUE($Z$1&$B$2&1),-1)-1),"",B5+1) -> 5 | D5: =IF(OR(C5="",VALUE(C5)>EOMONTH(DATEVALUE($Z$1&$B$2&1),0)-EOMONTH(DATEVALUE($Z$1&$B$2&1),-1)-1),"",C5+1) -> 6 | E5: =IF(OR(D5="",VALUE(D5)>EOMONTH(DATEVALUE($Z$1&$B$2&1),0)-EOMONTH(DATEVALUE($Z$1&$B$2&1),-1)-1),"",D5+1) -> 7 | F5: =IF(OR(E5="",VALUE(E5)>EOMONTH(DATEVALUE($Z$1&$B$2&1),0)-EOMONTH(DATEVALUE($Z$1&$B$2&1),-1)-1),"",E5+1) -> 8 | G5: =IF(OR(F5="",VALUE(F5)>EOMONTH(DATEVALUE($Z$1&$B$2&1),0)-EOMONTH(DATEVALUE($Z$1&$B$2&1),-1)-1),"",F5+1) -> 9 | H5: =IF(OR(G5="",VALUE(G5)>EOMONTH(DATEVALUE($Z$1&$B$2&1),0)-EOMONTH(DATEVALUE($Z$1&$B$2&1),-1)-1),"",G5+1) -> 10 | J5: =IF(OR(P4="",VALUE(P4)>EOMONTH(DATEVALUE($Z$1&$J$2&1),0)-EOMONTH(DATEVALUE($Z$1&$J$2&1),-1)-1),"",P4+1) -> 8 | K5: =IF(OR(J5="",VALUE(J5)>EOMONTH(DATEVALUE($Z$1&$J$2&1),0)-EOMONTH(DATEVALUE($Z$1&$J$2&1),-1)-1),"",J5+1) -> 9 | L5: =IF(OR(K5="",VALUE(K5)>EOMONTH(DATEVALUE($Z$1&$J$2&1),0)-EOMONTH(DATEVALUE($Z$1&$J$2&1),-1)-1),"",K5+1) -> 10 | M5: =IF(OR(L5="",VALUE(L5)>EOMONTH(DATEVALUE($Z$1&$J$2&1),0)-EOMONTH(DATEVALUE($Z$1&$J$2&1),-1)-1),"",L5+1) -> 11 | N5: =IF(OR(M5="",VALUE(M5)>EOMONTH(DATEVALUE($Z$1&$J$2&1),0)-EOMONTH(DATEVALUE($Z$1&$J$2&1),-1)-1),"",M5+1) -> 12 | O5: =IF(OR(N5="",VALUE(N5)>EOMONTH(DATEVALUE($Z$1&$J$2&1),0)-EOMONTH(DATEVALUE($Z$1&$J$2&1),-1)-1),"",N5+1) -> 13 | P5: =IF(OR(O5="",VALUE(O5)>EOMONTH(DATEVALUE($Z$1&$J$2&1),0)-EOMONTH(DATEVALUE($Z$1&$J$2&1),-1)-1),"",O5+1) -> 14 | R5: =IF(OR(X4="",VALUE(X4)>EOMONTH(DATEVALUE($Z$1&$R$2&1),0)-EOMONTH(DATEVALUE($Z$1&$R$2&1),-1)-1),"",X4+1) -> 8 | S5: =IF(OR(R5="",VALUE(R5)>EOMONTH(DATEVALUE($Z$1&$R$2&1),0)-EOMONTH(DATEVALUE($Z$1&$R$2&1),-1)-1),"",R5+1) -> 9 | T5: =IF(OR(S5="",VALUE(S5)>EOMONTH(DATEVALUE($Z$1&$R$2&1),0)-EOMONTH(DATEVALUE($Z$1&$R$2&1),-1)-1),"",S5+1) -> 10 | U5: =IF(OR(T5="",VALUE(T5)>EOMONTH(DATEVALUE($Z$1&$R$2&1),0)-EOMONTH(DATEVALUE($Z$1&$R$2&1),-1)-1),"",T5+1) -> 11 | V5: =IF(OR(U5="",VALUE(U5)>EOMONTH(DATEVALUE($Z$1&$R$2&1),0)-EOMONTH(DATEVALUE($Z$1&$R$2&1),-1)-1),"",U5+1) -> 12 | W5: =IF(OR(V5="",VALUE(V5)>EOMONTH(DATEVALUE($Z$1&$R$2&1),0)-EOMONTH(DATEVALUE($Z$1&$R$2&1),-1)-1),"",V5+1) -> 13 | X5: =IF(OR(W5="",VALUE(W5)>EOMONTH(DATEVALUE($Z$1&$R$2&1),0)-EOMONTH(DATEVALUE($Z$1&$R$2&1),-1)-1),"",W5+1) -> 14
B6: =IF(OR(H5="",VALUE(H5)>EOMONTH(DATEVALUE($Z$1&$B$2&1),0)-EOMONTH(DATEVALUE($Z$1&$B$2&1),-1)-1),"",H5+1) -> 11 | C6: =IF(OR(B6="",VALUE(B6)>EOMONTH(DATEVALUE($Z$1&$B$2&1),0)-EOMONTH(DATEVALUE($Z$1&$B$2&1),-1)-1),"",B6+1) -> 12 | D6: =IF(OR(C6="",VALUE(C6)>EOMONTH(DATEVALUE($Z$1&$B$2&1),0)-EOMONTH(DATEVALUE($Z$1&$B$2&1),-1)-1),"",C6+1) -> 13 | E6: =IF(OR(D6="",VALUE(D6)>EOMONTH(DATEVALUE($Z$1&$B$2&1),0)-EOMONTH(DATEVALUE($Z$1&$B$2&1),-1)-1),"",D6+1) -> 14 | F6: =IF(OR(E6="",VALUE(E6)>EOMONTH(DATEVALUE($Z$1&$B$2&1),0)-EOMONTH(DATEVALUE($Z$1&$B$2&1),-1)-1),"",E6+1) -> 15 | G6: =IF(OR(F6="",VALUE(F6)>EOMONTH(DATEVALUE($Z$1&$B$2&1),0)-EOMONTH(DATEVALUE($Z$1&$B$2&1),-1)-1),"",F6+1) -> 16 | H6: =IF(OR(G6="",VALUE(G6)>EOMONTH(DATEVALUE($Z$1&$B$2&1),0)-EOMONTH(DATEVALUE($Z$1&$B$2&1),-1)-1),"",G6+1) -> 17 | J6: =IF(OR(P5="",VALUE(P5)>EOMONTH(DATEVALUE($Z$1&$J$2&1),0)-EOMONTH(DATEVALUE($Z$1&$J$2&1),-1)-1),"",P5+1) -> 15 | K6: =IF(OR(J6="",VALUE(J6)>EOMONTH(DATEVALUE($Z$1&$J$2&1),0)-EOMONTH(DATEVALUE($Z$1&$J$2&1),-1)-1),"",J6+1) -> 16 | L6: =IF(OR(K6="",VALUE(K6)>EOMONTH(DATEVALUE($Z$1&$J$2&1),0)-EOMONTH(DATEVALUE($Z$1&$J$2&1),-1)-1),"",K6+1) -> 17 | M6: =IF(OR(L6="",VALUE(L6)>EOMONTH(DATEVALUE($Z$1&$J$2&1),0)-EOMONTH(DATEVALUE($Z$1&$J$2&1),-1)-1),"",L6+1) -> 18 | N6: =IF(OR(M6="",VALUE(M6)>EOMONTH(DATEVALUE($Z$1&$J$2&1),0)-EOMONTH(DATEVALUE($Z$1&$J$2&1),-1)-1),"",M6+1) -> 19 | O6: =IF(OR(N6="",VALUE(N6)>EOMONTH(DATEVALUE($Z$1&$J$2&1),0)-EOMONTH(DATEVALUE($Z$1&$J$2&1),-1)-1),"",N6+1) -> 20 | P6: =IF(OR(O6="",VALUE(O6)>EOMONTH(DATEVALUE($Z$1&$J$2&1),0)-EOMONTH(DATEVALUE($Z$1&$J$2&1),-1)-1),"",O6+1) -> 21 | R6: =IF(OR(X5="",VALUE(X5)>EOMONTH(DATEVALUE($Z$1&$R$2&1),0)-EOMONTH(DATEVALUE($Z$1&$R$2&1),-1)-1),"",X5+1) -> 15 | S6: =IF(OR(R6="",VALUE(R6)>EOMONTH(DATEVALUE($Z$1&$R$2&1),0)-EOMONTH(DATEVALUE($Z$1&$R$2&1),-1)-1),"",R6+1) -> 16 | T6: =IF(OR(S6="",VALUE(S6)>EOMONTH(DATEVALUE($Z$1&$R$2&1),0)-EOMONTH(DATEVALUE($Z$1&$R$2&1),-1)-1),"",S6+1) -> 17 | U6: =IF(OR(T6="",VALUE(T6)>EOMONTH(DATEVALUE($Z$1&$R$2&1),0)-EOMONTH(DATEVALUE($Z$1&$R$2&1),-1)-1),"",T6+1) -> 18 | V6: =IF(OR(U6="",VALUE(U6)>EOMONTH(DATEVALUE($Z$1&$R$2&1),0)-EOMONTH(DATEVALUE($Z$1&$R$2&1),-1)-1),"",U6+1) -> 19 | W6: =IF(OR(V6="",VALUE(V6)>EOMONTH(DATEVALUE($Z$1&$R$2&1),0)-EOMONTH(DATEVALUE($Z$1&$R$2&1),-1)-1),"",V6+1) -> 20 | X6: =IF(OR(W6="",VALUE(W6)>EOMONTH(DATEVALUE($Z$1&$R$2&1),0)-EOMONTH(DATEVALUE($Z$1&$R$2&1),-1)-1),"",W6+1) -> 21
B7: =IF(OR(H6="",VALUE(H6)>EOMONTH(DATEVALUE($Z$1&$B$2&1),0)-EOMONTH(DATEVALUE($Z$1&$B$2&1),-1)-1),"",H6+1) -> 18 | C7: =IF(OR(B7="",VALUE(B7)>EOMONTH(DATEVALUE($Z$1&$B$2&1),0)-EOMONTH(DATEVALUE($Z$1&$B$2&1),-1)-1),"",B7+1) -> 19 | D7: =IF(OR(C7="",VALUE(C7)>EOMONTH(DATEVALUE($Z$1&$B$2&1),0)-EOMONTH(DATEVALUE($Z$1&$B$2&1),-1)-1),"",C7+1) -> 20 | E7: =IF(OR(D7="",VALUE(D7)>EOMONTH(DATEVALUE($Z$1&$B$2&1),0)-EOMONTH(DATEVALUE($Z$1&$B$2&1),-1)-1),"",D7+1) -> 21 | F7: =IF(OR(E7="",VALUE(E7)>EOMONTH(DATEVALUE($Z$1&$B$2&1),0)-EOMONTH(DATEVALUE($Z$1&$B$2&1),-1)-1),"",E7+1) -> 22 | G7: =IF(OR(F7="",VALUE(F7)>EOMONTH(DATEVALUE($Z$1&$B$2&1),0)-EOMONTH(DATEVALUE($Z$1&$B$2&1),-1)-1),"",F7+1) -> 23 | H7: =IF(OR(G7="",VALUE(G7)>EOMONTH(DATEVALUE($Z$1&$B$2&1),0)-EOMONTH(DATEVALUE($Z$1&$B$2&1),-1)-1),"",G7+1) -> 24 | J7: =IF(OR(P6="",VALUE(P6)>EOMONTH(DATEVALUE($Z$1&$J$2&1),0)-EOMONTH(DATEVALUE($Z$1&$J$2&1),-1)-1),"",P6+1) -> 22 | K7: =IF(OR(J7="",VALUE(J7)>EOMONTH(DATEVALUE($Z$1&$J$2&1),0)-EOMONTH(DATEVALUE($Z$1&$J$2&1),-1)-1),"",J7+1) -> 23 | L7: =IF(OR(K7="",VALUE(K7)>EOMONTH(DATEVALUE($Z$1&$J$2&1),0)-EOMONTH(DATEVALUE($Z$1&$J$2&1),-1)-1),"",K7+1) -> 24 | M7: =IF(OR(L7="",VALUE(L7)>EOMONTH(DATEVALUE($Z$1&$J$2&1),0)-EOMONTH(DATEVALUE($Z$1&$J$2&1),-1)-1),"",L7+1) -> 25 | N7: =IF(OR(M7="",VALUE(M7)>EOMONTH(DATEVALUE($Z$1&$J$2&1),0)-EOMONTH(DATEVALUE($Z$1&$J$2&1),-1)-1),"",M7+1) -> 26 | O7: =IF(OR(N7="",VALUE(N7)>EOMONTH(DATEVALUE($Z$1&$J$2&1),0)-EOMONTH(DATEVALUE($Z$1&$J$2&1),-1)-1),"",N7+1) -> 27 | P7: =IF(OR(O7="",VALUE(O7)>EOMONTH(DATEVALUE($Z$1&$J$2&1),0)-EOMONTH(DATEVALUE($Z$1&$J$2&1),-1)-1),"",O7+1) -> 28 | R7: =IF(OR(X6="",VALUE(X6)>EOMONTH(DATEVALUE($Z$1&$R$2&1),0)-EOMONTH(DATEVALUE($Z$1&$R$2&1),-1)-1),"",X6+1) -> 22 | S7: =IF(OR(R7="",VALUE(R7)>EOMONTH(DATEVALUE($Z$1&$R$2&1),0)-EOMONTH(DATEVALUE($Z$1&$R$2&1),-1)-1),"",R7+1) -> 23 | T7: =IF(OR(S7="",VALUE(S7)>EOMONTH(DATEVALUE($Z$1&$R$2&1),0)-EOMONTH(DATEVALUE($Z$1&$R$2&1),-1)-1),"",S7+1) -> 24 | U7: =IF(OR(T7="",VALUE(T7)>EOMONTH(DATEVALUE($Z$1&$R$2&1),0)-EOMONTH(DATEVALUE($Z$1&$R$2&1),-1)-1),"",T7+1) -> 25 | V7: =IF(OR(U7="",VALUE(U7)>EOMONTH(DATEVALUE($Z$1&$R$2&1),0)-EOMONTH(DATEVALUE($Z$1&$R$2&1),-1)-1),"",U7+1) -> 26 | W7: =IF(OR(V7="",VALUE(V7)>EOMONTH(DATEVALUE($Z$1&$R$2&1),0)-EOMONTH(DATEVALUE($Z$1&$R$2&1),-1)-1),"",V7+1) -> 27 | X7: =IF(OR(W7="",VALUE(W7)>EOMONTH(DATEVALUE($Z$1&$R$2&1),0)-EOMONTH(DATEVALUE($Z$1&$R$2&1),-1)-1),"",W7+1) -> 28
B8: =IF(OR(H7="",VALUE(H7)>EOMONTH(DATEVALUE($Z$1&$B$2&1),0)-EOMONTH(DATEVALUE($Z$1&$B$2&1),-1)-1),"",H7+1) -> 25 | C8: =IF(OR(B8="",VALUE(B8)>EOMONTH(DATEVALUE($Z$1&$B$2&1),0)-EOMONTH(DATEVALUE($Z$1&$B$2&1),-1)-1),"",B8+1) -> 26 | D8: =IF(OR(C8="",VALUE(C8)>EOMONTH(DATEVALUE($Z$1&$B$2&1),0)-EOMONTH(DATEVALUE($Z$1&$B$2&1),-1)-1),"",C8+1) -> 27 | E8: =IF(OR(D8="",VALUE(D8)>EOMONTH(DATEVALUE($Z$1&$B$2&1),0)-EOMONTH(DATEVALUE($Z$1&$B$2&1),-1)-1),"",D8+1) -> 28 | F8: =IF(OR(E8="",VALUE(E8)>EOMONTH(DATEVALUE($Z$1&$B$2&1),0)-EOMONTH(DATEVALUE($Z$1&$B$2&1),-1)-1),"",E8+1) -> 29 | G8: =IF(OR(F8="",VALUE(F8)>EOMONTH(DATEVALUE($Z$1&$B$2&1),0)-EOMONTH(DATEVALUE($Z$1&$B$2&1),-1)-1),"",F8+1) -> 30 | H8: =IF(OR(G8="",VALUE(G8)>EOMONTH(DATEVALUE($Z$1&$B$2&1),0)-EOMONTH(DATEVALUE($Z$1&$B$2&1),-1)-1),"",G8+1) -> 31 | J8: =IF(OR(P7="",VALUE(P7)>EOMONTH(DATEVALUE($Z$1&$J$2&1),0)-EOMONTH(DATEVALUE($Z$1&$J$2&1),-1)-1),"",P7+1) | K8: =IF(OR(J8="",VALUE(J8)>EOMONTH(DATEVALUE($Z$1&$J$2&1),0)-EOMONTH(DATEVALUE($Z$1&$J$2&1),-1)-1),"",J8+1) | L8: =IF(OR(K8="",VALUE(K8)>EOMONTH(DATEVALUE($Z$1&$J$2&1),0)-EOMONTH(DATEVALUE($Z$1&$J$2&1),-1)-1),"",K8+1) | M8: =IF(OR(L8="",VALUE(L8)>EOMONTH(DATEVALUE($Z$1&$J$2&1),0)-EOMONTH(DATEVALUE($Z$1&$J$2&1),-1)-1),"",L8+1) | N8: =IF(OR(M8="",VALUE(M8)>EOMONTH(DATEVALUE($Z$1&$J$2&1),0)-EOMONTH(DATEVALUE($Z$1&$J$2&1),-1)-1),"",M8+1) | O8: =IF(OR(N8="",VALUE(N8)>EOMONTH(DATEVALUE($Z$1&$J$2&1),0)-EOMONTH(DATEVALUE($Z$1&$J$2&1),-1)-1),"",N8+1) | P8: =IF(OR(O8="",VALUE(O8)>EOMONTH(DATEVALUE($Z$1&$J$2&1),0)-EOMONTH(DATEVALUE($Z$1&$J$2&1),-1)-1),"",O8+1) | R8: =IF(OR(X7="",VALUE(X7)>EOMONTH(DATEVALUE($Z$1&$R$2&1),0)-EOMONTH(DATEVALUE($Z$1&$R$2&1),-1)-1),"",X7+1) -> 29 | S8: =IF(OR(R8="",VALUE(R8)>EOMONTH(DATEVALUE($Z$1&$R$2&1),0)-EOMONTH(DATEVALUE($Z$1&$R$2&1),-1)-1),"",R8+1) -> 30 | T8: =IF(OR(S8="",VALUE(S8)>EOMONTH(DATEVALUE($Z$1&$R$2&1),0)-EOMONTH(DATEVALUE($Z$1&$R$2&1),-1)-1),"",S8+1) -> 31 | U8: =IF(OR(T8="",VALUE(T8)>EOMONTH(DATEVALUE($Z$1&$R$2&1),0)-EOMONTH(DATEVALUE($Z$1&$R$2&1),-1)-1),"",T8+1) | V8: =IF(OR(U8="",VALUE(U8)>EOMONTH(DATEVALUE($Z$1&$R$2&1),0)-EOMONTH(DATEVALUE($Z$1&$R$2&1),-1)-1),"",U8+1) | W8: =IF(OR(V8="",VALUE(V8)>EOMONTH(DATEVALUE($Z$1&$R$2&1),0)-EOMONTH(DATEVALUE($Z$1&$R$2&1),-1)-1),"",V8+1) | X8: =IF(OR(W8="",VALUE(W8)>EOMONTH(DATEVALUE($Z$1&$R$2&1),0)-EOMONTH(DATEVALUE($Z$1&$R$2&1),-1)-1),"",W8+1)
B9: =IF(OR(H8="",VALUE(H8)>EOMONTH(DATEVALUE($Z$1&$B$2&1),0)-EOMONTH(DATEVALUE($Z$1&$B$2&1),-1)-1),"",H8+1) | C9: =IF(OR(B9="",VALUE(B9)>EOMONTH(DATEVALUE($Z$1&$B$2&1),0)-EOMONTH(DATEVALUE($Z$1&$B$2&1),-1)-1),"",B9+1) | D9: =IF(OR(C9="",VALUE(C9)>EOMONTH(DATEVALUE($Z$1&$B$2&1),0)-EOMONTH(DATEVALUE($Z$1&$B$2&1),-1)-1),"",C9+1) | E9: =IF(OR(D9="",VALUE(D9)>EOMONTH(DATEVALUE($Z$1&$B$2&1),0)-EOMONTH(DATEVALUE($Z$1&$B$2&1),-1)-1),"",D9+1) | F9: =IF(OR(E9="",VALUE(E9)>EOMONTH(DATEVALUE($Z$1&$B$2&1),0)-EOMONTH(DATEVALUE($Z$1&$B$2&1),-1)-1),"",E9+1) | G9: =IF(OR(F9="",VALUE(F9)>EOMONTH(DATEVALUE($Z$1&$B$2&1),0)-EOMONTH(DATEVALUE($Z$1&$B$2&1),-1)-1),"",F9+1) | H9: =IF(OR(G9="",VALUE(G9)>EOMONTH(DATEVALUE($Z$1&$B$2&1),0)-EOMONTH(DATEVALUE($Z$1&$B$2&1),-1)-1),"",G9+1) | J9: =IF(OR(P8="",VALUE(P8)>EOMONTH(DATEVALUE($Z$1&$J$2&1),0)-EOMONTH(DATEVALUE($Z$1&$J$2&1),-1)-1),"",P8+1) | K9: =IF(OR(J9="",VALUE(J9)>EOMONTH(DATEVALUE($Z$1&$J$2&1),0)-EOMONTH(DATEVALUE($Z$1&$J$2&1),-1)-1),"",J9+1) | L9: =IF(OR(K9="",VALUE(K9)>EOMONTH(DATEVALUE($Z$1&$J$2&1),0)-EOMONTH(DATEVALUE($Z$1&$J$2&1),-1)-1),"",K9+1) | M9: =IF(OR(L9="",VALUE(L9)>EOMONTH(DATEVALUE($Z$1&$J$2&1),0)-EOMONTH(DATEVALUE($Z$1&$J$2&1),-1)-1),"",L9+1) | N9: =IF(OR(M9="",VALUE(M9)>EOMONTH(DATEVALUE($Z$1&$J$2&1),0)-EOMONTH(DATEVALUE($Z$1&$J$2&1),-1)-1),"",M9+1) | O9: =IF(OR(N9="",VALUE(N9)>EOMONTH(DATEVALUE($Z$1&$J$2&1),0)-EOMONTH(DATEVALUE($Z$1&$J$2&1),-1)-1),"",N9+1) | P9: =IF(OR(O9="",VALUE(O9)>EOMONTH(DATEVALUE($Z$1&$J$2&1),0)-EOMONTH(DATEVALUE($Z$1&$J$2&1),-1)-1),"",O9+1) | R9: =IF(OR(X8="",VALUE(X8)>EOMONTH(DATEVALUE($Z$1&$R$2&1),0)-EOMONTH(DATEVALUE($Z$1&$R$2&1),-1)-1),"",X8+1) | S9: =IF(OR(R9="",VALUE(R9)>EOMONTH(DATEVALUE($Z$1&$R$2&1),0)-EOMONTH(DATEVALUE($Z$1&$R$2&1),-1)-1),"",R9+1) | T9: =IF(OR(S9="",VALUE(S9)>EOMONTH(DATEVALUE($Z$1&$R$2&1),0)-EOMONTH(DATEVALUE($Z$1&$R$2&1),-1)-1),"",S9+1) | U9: =IF(OR(T9="",VALUE(T9)>EOMONTH(DATEVALUE($Z$1&$R$2&1),0)-EOMONTH(DATEVALUE($Z$1&$R$2&1),-1)-1),"",T9+1) | V9: =IF(OR(U9="",VALUE(U9)>EOMONTH(DATEVALUE($Z$1&$R$2&1),0)-EOMONTH(DATEVALUE($Z$1&$R$2&1),-1)-1),"",U9+1) | W9: =IF(OR(V9="",VALUE(V9)>EOMONTH(DATEVALUE($Z$1&$R$2&1),0)-EOMONTH(DATEVALUE($Z$1&$R$2&1),-1)-1),"",V9+1) | X9: =IF(OR(W9="",VALUE(W9)>EOMONTH(DATEVALUE($Z$1&$R$2&1),0)-EOMONTH(DATEVALUE($Z$1&$R$2&1),-1)-1),"",W9+1)
B11: APRIL | J11: MAY | R11: JUNE
B12: S | C12: M | D12: T | E12: W | F12: T | G12: F | H12: S | J12: S | K12: M | L12: T | M12: W | N12: T | O12: F | P12: S | R12: S | S12: M | T12: T | U12: W | V12: T | W12: F | X12: S
B13: =IF(WEEKDAY(DATEVALUE($Z$1&$B$11&1))=1,1,"") | C13: =IF(B13<>"",B13+1,IF(WEEKDAY(DATEVALUE($Z$1&$B$11&1))=2,1,"")) | D13: =IF(C13<>"",C13+1,IF(WEEKDAY(DATEVALUE($Z$1&$B$11&1))=3,1,"")) | E13: =IF(D13<>"",D13+1,IF(WEEKDAY(DATEVALUE($Z$1&$B$11&1))=4,1,"")) -> 1 | F13: =IF(E13<>"",E13+1,IF(WEEKDAY(DATEVALUE($Z$1&$B$11&1))=5,1,"")) -> 2 | G13: =IF(F13<>"",F13+1,IF(WEEKDAY(DATEVALUE($Z$1&$B$11&1))=6,1,"")) -> 3 | H13: =IF(G13<>"",G13+1,IF(WEEKDAY(DATEVALUE($Z$1&$B$11&1))=7,1,"")) -> 4 | J13: =IF(WEEKDAY(DATEVALUE($Z$1&$J$11&1))=1,1,"") | K13: =IF(J13<>"",J13+1,IF(WEEKDAY(DATEVALUE($Z$1&$J$11&1))=2,1,"")) | L13: =IF(K13<>"",K13+1,IF(WEEKDAY(DATEVALUE($Z$1&$J$11&1))=3,1,"")) | M13: =IF(L13<>"",L13+1,IF(WEEKDAY(DATEVALUE($Z$1&$J$11&1))=4,1,"")) | N13: =IF(M13<>"",M13+1,IF(WEEKDAY(DATEVALUE($Z$1&$J$11&1))=5,1,"")) | O13: =IF(N13<>"",N13+1,IF(WEEKDAY(DATEVALUE($Z$1&$J$11&1))=6,1,"")) -> 1 | P13: =IF(O13<>"",O13+1,IF(WEEKDAY(DATEVALUE($Z$1&$J$11&1))=7,1,"")) -> 2 | R13: =IF(WEEKDAY(DATEVALUE($Z$1&$R$11&1))=1,1,"") | S13: =IF(R13<>"",R13+1,IF(WEEKDAY(DATEVALUE($Z$1&$R$11&1))=2,1,"")) -> 1 | T13: =IF(S13<>"",S13+1,IF(WEEKDAY(DATEVALUE($Z$1&$R$11&1))=3,1,"")) -> 2 | U13: =IF(T13<>"",T13+1,IF(WEEKDAY(DATEVALUE($Z$1&$R$11&1))=4,1,"")) -> 3 | V13: =IF(U13<>"",U13+1,IF(WEEKDAY(DATEVALUE($Z$1&$R$11&1))=5,1,"")) -> 4 | W13: =IF(V13<>"",V13+1,IF(WEEKDAY(DATEVALUE($Z$1&$R$11&1))=6,1,"")) -> 5 | X13: =IF(W13<>"",W13+1,IF(WEEKDAY(DATEVALUE($Z$1&$R$11&1))=7,1,"")) -> 6
B14: =IF(OR(H13="",VALUE(H13)>EOMONTH(DATEVALUE($Z$1&$B$11&1),0)-EOMONTH(DATEVALUE($Z$1&$B$11&1),-1)-1),"",H13+1) -> 5 | C14: =IF(OR(B14="",VALUE(B14)>EOMONTH(DATEVALUE($Z$1&$B$11&1),0)-EOMONTH(DATEVALUE($Z$1&$B$11&1),-1)-1),"",B14+1) -> 6 | D14: =IF(OR(C14="",VALUE(C14)>EOMONTH(DATEVALUE($Z$1&$B$11&1),0)-EOMONTH(DATEVALUE($Z$1&$B$11&1),-1)-1),"",C14+1) -> 7 | E14: =IF(OR(D14="",VALUE(D14)>EOMONTH(DATEVALUE($Z$1&$B$11&1),0)-EOMONTH(DATEVALUE($Z$1&$B$11&1),-1)-1),"",D14+1) -> 8 | F14: =IF(OR(E14="",VALUE(E14)>EOMONTH(DATEVALUE($Z$1&$B$11&1),0)-EOMONTH(DATEVALUE($Z$1&$B$11&1),-1)-1),"",E14+1) -> 9 | G14: =IF(OR(F14="",VALUE(F14)>EOMONTH(DATEVALUE($Z$1&$B$11&1),0)-EOMONTH(DATEVALUE($Z$1&$B$11&1),-1)-1),"",F14+1) -> 10 | H14: =IF(OR(G14="",VALUE(G14)>EOMONTH(DATEVALUE($Z$1&$B$11&1),0)-EOMONTH(DATEVALUE($Z$1&$B$11&1),-1)-1),"",G14+1) -> 11 | J14: =IF(OR(P13="",VALUE(P13)>EOMONTH(DATEVALUE($Z$1&$J$11&1),0)-EOMONTH(DATEVALUE($Z$1&$J$11&1),-1)-1),"",P13+1) -> 3 | K14: =IF(OR(J14="",VALUE(J14)>EOMONTH(DATEVALUE($Z$1&$J$11&1),0)-EOMONTH(DATEVALUE($Z$1&$J$11&1),-1)-1),"",J14+1) -> 4 | L14: =IF(OR(K14="",VALUE(K14)>EOMONTH(DATEVALUE($Z$1&$J$11&1),0)-EOMONTH(DATEVALUE($Z$1&$J$11&1),-1)-1),"",K14+1) -> 5 | M14: =IF(OR(L14="",VALUE(L14)>EOMONTH(DATEVALUE($Z$1&$J$11&1),0)-EOMONTH(DATEVALUE($Z$1&$J$11&1),-1)-1),"",L14+1) -> 6 | N14: =IF(OR(M14="",VALUE(M14)>EOMONTH(DATEVALUE($Z$1&$J$11&1),0)-EOMONTH(DATEVALUE($Z$1&$J$11&1),-1)-1),"",M14+1) -> 7 | O14: =IF(OR(N14="",VALUE(N14)>EOMONTH(DATEVALUE($Z$1&$J$11&1),0)-EOMONTH(DATEVALUE($Z$1&$J$11&1),-1)-1),"",N14+1) -> 8 | P14: =IF(OR(O14="",VALUE(O14)>EOMONTH(DATEVALUE($Z$1&$J$11&1),0)-EOMONTH(DATEVALUE($Z$1&$J$11&1),-1)-1),"",O14+1) -> 9 | R14: =IF(OR(X13="",VALUE(X13)>EOMONTH(DATEVALUE($Z$1&$R$11&1),0)-EOMONTH(DATEVALUE($Z$1&$R$11&1),-1)-1),"",X13+1) -> 7 | S14: =IF(OR(R14="",VALUE(R14)>EOMONTH(DATEVALUE($Z$1&$R$11&1),0)-EOMONTH(DATEVALUE($Z$1&$R$11&1),-1)-1),"",R14+1) -> 8 | T14: =IF(OR(S14="",VALUE(S14)>EOMONTH(DATEVALUE($Z$1&$R$11&1),0)-EOMONTH(DATEVALUE($Z$1&$R$11&1),-1)-1),"",S14+1) -> 9 | U14: =IF(OR(T14="",VALUE(T14)>EOMONTH(DATEVALUE($Z$1&$R$11&1),0)-EOMONTH(DATEVALUE($Z$1&$R$11&1),-1)-1),"",T14+1) -> 10 | V14: =IF(OR(U14="",VALUE(U14)>EOMONTH(DATEVALUE($Z$1&$R$11&1),0)-EOMONTH(DATEVALUE($Z$1&$R$11&1),-1)-1),"",U14+1) -> 11 | W14: =IF(OR(V14="",VALUE(V14)>EOMONTH(DATEVALUE($Z$1&$R$11&1),0)-EOMONTH(DATEVALUE($Z$1&$R$11&1),-1)-1),"",V14+1) -> 12 | X14: =IF(OR(W14="",VALUE(W14)>EOMONTH(DATEVALUE($Z$1&$R$11&1),0)-EOMONTH(DATEVALUE($Z$1&$R$11&1),-1)-1),"",W14+1) -> 13
B15: =IF(OR(H14="",VALUE(H14)>EOMONTH(DATEVALUE($Z$1&$B$11&1),0)-EOMONTH(DATEVALUE($Z$1&$B$11&1),-1)-1),"",H14+1) -> 12 | C15: =IF(OR(B15="",VALUE(B15)>EOMONTH(DATEVALUE($Z$1&$B$11&1),0)-EOMONTH(DATEVALUE($Z$1&$B$11&1),-1)-1),"",B15+1) -> 13 | D15: =IF(OR(C15="",VALUE(C15)>EOMONTH(DATEVALUE($Z$1&$B$11&1),0)-EOMONTH(DATEVALUE($Z$1&$B$11&1),-1)-1),"",C15+1) -> 14 | E15: =IF(OR(D15="",VALUE(D15)>EOMONTH(DATEVALUE($Z$1&$B$11&1),0)-EOMONTH(DATEVALUE($Z$1&$B$11&1),-1)-1),"",D15+1) -> 15 | F15: =IF(OR(E15="",VALUE(E15)>EOMONTH(DATEVALUE($Z$1&$B$11&1),0)-EOMONTH(DATEVALUE($Z$1&$B$11&1),-1)-1),"",E15+1) -> 16 | G15: =IF(OR(F15="",VALUE(F15)>EOMONTH(DATEVALUE($Z$1&$B$11&1),0)-EOMONTH(DATEVALUE($Z$1&$B$11&1),-1)-1),"",F15+1) -> 17 | H15: =IF(OR(G15="",VALUE(G15)>EOMONTH(DATEVALUE($Z$1&$B$11&1),0)-EOMONTH(DATEVALUE($Z$1&$B$11&1),-1)-1),"",G15+1) -> 18 | J15: =IF(OR(P14="",VALUE(P14)>EOMONTH(DATEVALUE($Z$1&$J$11&1),0)-EOMONTH(DATEVALUE($Z$1&$J$11&1),-1)-1),"",P14+1) -> 10 | K15: =IF(OR(J15="",VALUE(J15)>EOMONTH(DATEVALUE($Z$1&$J$11&1),0)-EOMONTH(DATEVALUE($Z$1&$J$11&1),-1)-1),"",J15+1) -> 11 | L15: =IF(OR(K15="",VALUE(K15)>EOMONTH(DATEVALUE($Z$1&$J$11&1),0)-EOMONTH(DATEVALUE($Z$1&$J$11&1),-1)-1),"",K15+1) -> 12 | M15: =IF(OR(L15="",VALUE(L15)>EOMONTH(DATEVALUE($Z$1&$J$11&1),0)-EOMONTH(DATEVALUE($Z$1&$J$11&1),-1)-1),"",L15+1) -> 13 | N15: =IF(OR(M15="",VALUE(M15)>EOMONTH(DATEVALUE($Z$1&$J$11&1),0)-EOMONTH(DATEVALUE($Z$1&$J$11&1),-1)-1),"",M15+1) -> 14 | O15: =IF(OR(N15="",VALUE(N15)>EOMONTH(DATEVALUE($Z$1&$J$11&1),0)-EOMONTH(DATEVALUE($Z$1&$J$11&1),-1)-1),"",N15+1) -> 15 | P15: =IF(OR(O15="",VALUE(O15)>EOMONTH(DATEVALUE($Z$1&$J$11&1),0)-EOMONTH(DATEVALUE($Z$1&$J$11&1),-1)-1),"",O15+1) -> 16 | R15: =IF(OR(X14="",VALUE(X14)>EOMONTH(DATEVALUE($Z$1&$R$11&1),0)-EOMONTH(DATEVALUE($Z$1&$R$11&1),-1)-1),"",X14+1) -> 14 | S15: =IF(OR(R15="",VALUE(R15)>EOMONTH(DATEVALUE($Z$1&$R$11&1),0)-EOMONTH(DATEVALUE($Z$1&$R$11&1),-1)-1),"",R15+1) -> 15 | T15: =IF(OR(S15="",VALUE(S15)>EOMONTH(DATEVALUE($Z$1&$R$11&1),0)-EOMONTH(DATEVALUE($Z$1&$R$11&1),-1)-1),"",S15+1) -> 16 | U15: =IF(OR(T15="",VALUE(T15)>EOMONTH(DATEVALUE($Z$1&$R$11&1),0)-EOMONTH(DATEVALUE($Z$1&$R$11&1),-1)-1),"",T15+1) -> 17 | V15: =IF(OR(U15="",VALUE(U15)>EOMONTH(DATEVALUE($Z$1&$R$11&1),0)-EOMONTH(DATEVALUE($Z$1&$R$11&1),-1)-1),"",U15+1) -> 18 | W15: =IF(OR(V15="",VALUE(V15)>EOMONTH(DATEVALUE($Z$1&$R$11&1),0)-EOMONTH(DATEVALUE($Z$1&$R$11&1),-1)-1),"",V15+1) -> 19 | X15: =IF(OR(W15="",VALUE(W15)>EOMONTH(DATEVALUE($Z$1&$R$11&1),0)-EOMONTH(DATEVALUE($Z$1&$R$11&1),-1)-1),"",W15+1) -> 20
B16: =IF(OR(H15="",VALUE(H15)>EOMONTH(DATEVALUE($Z$1&$B$11&1),0)-EOMONTH(DATEVALUE($Z$1&$B$11&1),-1)-1),"",H15+1) -> 19 | C16: =IF(OR(B16="",VALUE(B16)>EOMONTH(DATEVALUE($Z$1&$B$11&1),0)-EOMONTH(DATEVALUE($Z$1&$B$11&1),-1)-1),"",B16+1) -> 20 | D16: =IF(OR(C16="",VALUE(C16)>EOMONTH(DATEVALUE($Z$1&$B$11&1),0)-EOMONTH(DATEVALUE($Z$1&$B$11&1),-1)-1),"",C16+1) -> 21 | E16: =IF(OR(D16="",VALUE(D16)>EOMONTH(DATEVALUE($Z$1&$B$11&1),0)-EOMONTH(DATEVALUE($Z$1&$B$11&1),-1)-1),"",D16+1) -> 22 | F16: =IF(OR(E16="",VALUE(E16)>EOMONTH(DATEVALUE($Z$1&$B$11&1),0)-EOMONTH(DATEVALUE($Z$1&$B$11&1),-1)-1),"",E16+1) -> 23 | G16: =IF(OR(F16="",VALUE(F16)>EOMONTH(DATEVALUE($Z$1&$B$11&1),0)-EOMONTH(DATEVALUE($Z$1&$B$11&1),-1)-1),"",F16+1) -> 24 | H16: =IF(OR(G16="",VALUE(G16)>EOMONTH(DATEVALUE($Z$1&$B$11&1),0)-EOMONTH(DATEVALUE($Z$1&$B$11&1),-1)-1),"",G16+1) -> 25 | J16: =IF(OR(P15="",VALUE(P15)>EOMONTH(DATEVALUE($Z$1&$J$11&1),0)-EOMONTH(DATEVALUE($Z$1&$J$11&1),-1)-1),"",P15+1) -> 17 | K16: =IF(OR(J16="",VALUE(J16)>EOMONTH(DATEVALUE($Z$1&$J$11&1),0)-EOMONTH(DATEVALUE($Z$1&$J$11&1),-1)-1),"",J16+1) -> 18 | L16: =IF(OR(K16="",VALUE(K16)>EOMONTH(DATEVALUE($Z$1&$J$11&1),0)-EOMONTH(DATEVALUE($Z$1&$J$11&1),-1)-1),"",K16+1) -> 19 | M16: =IF(OR(L16="",VALUE(L16)>EOMONTH(DATEVALUE($Z$1&$J$11&1),0)-EOMONTH(DATEVALUE($Z$1&$J$11&1),-1)-1),"",L16+1) -> 20 | N16: =IF(OR(M16="",VALUE(M16)>EOMONTH(DATEVALUE($Z$1&$J$11&1),0)-EOMONTH(DATEVALUE($Z$1&$J$11&1),-1)-1),"",M16+1) -> 21 | O16: =IF(OR(N16="",VALUE(N16)>EOMONTH(DATEVALUE($Z$1&$J$11&1),0)-EOMONTH(DATEVALUE($Z$1&$J$11&1),-1)-1),"",N16+1) -> 22 | P16: =IF(OR(O16="",VALUE(O16)>EOMONTH(DATEVALUE($Z$1&$J$11&1),0)-EOMONTH(DATEVALUE($Z$1&$J$11&1),-1)-1),"",O16+1) -> 23 | R16: =IF(OR(X15="",VALUE(X15)>EOMONTH(DATEVALUE($Z$1&$R$11&1),0)-EOMONTH(DATEVALUE($Z$1&$R$11&1),-1)-1),"",X15+1) -> 21 | S16: =IF(OR(R16="",VALUE(R16)>EOMONTH(DATEVALUE($Z$1&$R$11&1),0)-EOMONTH(DATEVALUE($Z$1&$R$11&1),-1)-1),"",R16+1) -> 22 | T16: =IF(OR(S16="",VALUE(S16)>EOMONTH(DATEVALUE($Z$1&$R$11&1),0)-EOMONTH(DATEVALUE($Z$1&$R$11&1),-1)-1),"",S16+1) -> 23 | U16: =IF(OR(T16="",VALUE(T16)>EOMONTH(DATEVALUE($Z$1&$R$11&1),0)-EOMONTH(DATEVALUE($Z$1&$R$11&1),-1)-1),"",T16+1) -> 24 | V16: =IF(OR(U16="",VALUE(U16)>EOMONTH(DATEVALUE($Z$1&$R$11&1),0)-EOMONTH(DATEVALUE($Z$1&$R$11&1),-1)-1),"",U16+1) -> 25 | W16: =IF(OR(V16="",VALUE(V16)>EOMONTH(DATEVALUE($Z$1&$R$11&1),0)-EOMONTH(DATEVALUE($Z$1&$R$11&1),-1)-1),"",V16+1) -> 26 | X16: =IF(OR(W16="",VALUE(W16)>EOMONTH(DATEVALUE($Z$1&$R$11&1),0)-EOMONTH(DATEVALUE($Z$1&$R$11&1),-1)-1),"",W16+1) -> 27
B17: =IF(OR(H16="",VALUE(H16)>EOMONTH(DATEVALUE($Z$1&$B$11&1),0)-EOMONTH(DATEVALUE($Z$1&$B$11&1),-1)-1),"",H16+1) -> 26 | C17: =IF(OR(B17="",VALUE(B17)>EOMONTH(DATEVALUE($Z$1&$B$11&1),0)-EOMONTH(DATEVALUE($Z$1&$B$11&1),-1)-1),"",B17+1) -> 27 | D17: =IF(OR(C17="",VALUE(C17)>EOMONTH(DATEVALUE($Z$1&$B$11&1),0)-EOMONTH(DATEVALUE($Z$1&$B$11&1),-1)-1),"",C17+1) -> 28 | E17: =IF(OR(D17="",VALUE(D17)>EOMONTH(DATEVALUE($Z$1&$B$11&1),0)-EOMONTH(DATEVALUE($Z$1&$B$11&1),-1)-1),"",D17+1) -> 29 | F17: =IF(OR(E17="",VALUE(E17)>EOMONTH(DATEVALUE($Z$1&$B$11&1),0)-EOMONTH(DATEVALUE($Z$1&$B$11&1),-1)-1),"",E17+1) -> 30 | G17: =IF(OR(F17="",VALUE(F17)>EOMONTH(DATEVALUE($Z$1&$B$11&1),0)-EOMONTH(DATEVALUE($Z$1&$B$11&1),-1)-1),"",F17+1) | H17: =IF(OR(G17="",VALUE(G17)>EOMONTH(DATEVALUE($Z$1&$B$11&1),0)-EOMONTH(DATEVALUE($Z$1&$B$11&1),-1)-1),"",G17+1) | J17: =IF(OR(P16="",VALUE(P16)>EOMONTH(DATEVALUE($Z$1&$J$11&1),0)-EOMONTH(DATEVALUE($Z$1&$J$11&1),-1)-1),"",P16+1) -> 24 | K17: =IF(OR(J17="",VALUE(J17)>EOMONTH(DATEVALUE($Z$1&$J$11&1),0)-EOMONTH(DATEVALUE($Z$1&$J$11&1),-1)-1),"",J17+1) -> 25 | L17: =IF(OR(K17="",VALUE(K17)>EOMONTH(DATEVALUE($Z$1&$J$11&1),0)-EOMONTH(DATEVALUE($Z$1&$J$11&1),-1)-1),"",K17+1) -> 26 | M17: =IF(OR(L17="",VALUE(L17)>EOMONTH(DATEVALUE($Z$1&$J$11&1),0)-EOMONTH(DATEVALUE($Z$1&$J$11&1),-1)-1),"",L17+1) -> 27 | N17: =IF(OR(M17="",VALUE(M17)>EOMONTH(DATEVALUE($Z$1&$J$11&1),0)-EOMONTH(DATEVALUE($Z$1&$J$11&1),-1)-1),"",M17+1) -> 28 | O17: =IF(OR(N17="",VALUE(N17)>EOMONTH(DATEVALUE($Z$1&$J$11&1),0)-EOMONTH(DATEVALUE($Z$1&$J$11&1),-1)-1),"",N17+1) -> 29 | P17: =IF(OR(O17="",VALUE(O17)>EOMONTH(DATEVALUE($Z$1&$J$11&1),0)-EOMONTH(DATEVALUE($Z$1&$J$11&1),-1)-1),"",O17+1) -> 30 | R17: =IF(OR(X16="",VALUE(X16)>EOMONTH(DATEVALUE($Z$1&$R$11&1),0)-EOMONTH(DATEVALUE($Z$1&$R$11&1),-1)-1),"",X16+1) -> 28 | S17: =IF(OR(R17="",VALUE(R17)>EOMONTH(DATEVALUE($Z$1&$R$11&1),0)-EOMONTH(DATEVALUE($Z$1&$R$11&1),-1)-1),"",R17+1) -> 29 | T17: =IF(OR(S17="",VALUE(S17)>EOMONTH(DATEVALUE($Z$1&$R$11&1),0)-EOMONTH(DATEVALUE($Z$1&$R$11&1),-1)-1),"",S17+1) -> 30 | U17: =IF(OR(T17="",VALUE(T17)>EOMONTH(DATEVALUE($Z$1&$R$11&1),0)-EOMONTH(DATEVALUE($Z$1&$R$11&1),-1)-1),"",T17+1) | V17: =IF(OR(U17="",VALUE(U17)>EOMONTH(DATEVALUE($Z$1&$R$11&1),0)-EOMONTH(DATEVALUE($Z$1&$R$11&1),-1)-1),"",U17+1) | W17: =IF(OR(V17="",VALUE(V17)>EOMONTH(DATEVALUE($Z$1&$R$11&1),0)-EOMONTH(DATEVALUE($Z$1&$R$11&1),-1)-1),"",V17+1) | X17: =IF(OR(W17="",VALUE(W17)>EOMONTH(DATEVALUE($Z$1&$R$11&1),0)-EOMONTH(DATEVALUE($Z$1&$R$11&1),-1)-1),"",W17+1)
B18: =IF(OR(H17="",VALUE(H17)>EOMONTH(DATEVALUE($Z$1&$B$11&1),0)-EOMONTH(DATEVALUE($Z$1&$B$11&1),-1)-1),"",H17+1) | C18: =IF(OR(B18="",VALUE(B18)>EOMONTH(DATEVALUE($Z$1&$B$11&1),0)-EOMONTH(DATEVALUE($Z$1&$B$11&1),-1)-1),"",B18+1) | D18: =IF(OR(C18="",VALUE(C18)>EOMONTH(DATEVALUE($Z$1&$B$11&1),0)-EOMONTH(DATEVALUE($Z$1&$B$11&1),-1)-1),"",C18+1) | E18: =IF(OR(D18="",VALUE(D18)>EOMONTH(DATEVALUE($Z$1&$B$11&1),0)-EOMONTH(DATEVALUE($Z$1&$B$11&1),-1)-1),"",D18+1) | F18: =IF(OR(E18="",VALUE(E18)>EOMONTH(DATEVALUE($Z$1&$B$11&1),0)-EOMONTH(DATEVALUE($Z$1&$B$11&1),-1)-1),"",E18+1) | G18: =IF(OR(F18="",VALUE(F18)>EOMONTH(DATEVALUE($Z$1&$B$11&1),0)-EOMONTH(DATEVALUE($Z$1&$B$11&1),-1)-1),"",F18+1) | H18: =IF(OR(G18="",VALUE(G18)>EOMONTH(DATEVALUE($Z$1&$B$11&1),0)-EOMONTH(DATEVALUE($Z$1&$B$11&1),-1)-1),"",G18+1) | J18: =IF(OR(P17="",VALUE(P17)>EOMONTH(DATEVALUE($Z$1&$J$11&1),0)-EOMONTH(DATEVALUE($Z$1&$J$11&1),-1)-1),"",P17+1) -> 31 | K18: =IF(OR(J18="",VALUE(J18)>EOMONTH(DATEVALUE($Z$1&$J$11&1),0)-EOMONTH(DATEVALUE($Z$1&$J$11&1),-1)-1),"",J18+1) | L18: =IF(OR(K18="",VALUE(K18)>EOMONTH(DATEVALUE($Z$1&$J$11&1),0)-EOMONTH(DATEVALUE($Z$1&$J$11&1),-1)-1),"",K18+1) | M18: =IF(OR(L18="",VALUE(L18)>EOMONTH(DATEVALUE($Z$1&$J$11&1),0)-EOMONTH(DATEVALUE($Z$1&$J$11&1),-1)-1),"",L18+1) | N18: =IF(OR(M18="",VALUE(M18)>EOMONTH(DATEVALUE($Z$1&$J$11&1),0)-EOMONTH(DATEVALUE($Z$1&$J$11&1),-1)-1),"",M18+1) | O18: =IF(OR(N18="",VALUE(N18)>EOMONTH(DATEVALUE($Z$1&$J$11&1),0)-EOMONTH(DATEVALUE($Z$1&$J$11&1),-1)-1),"",N18+1) | P18: =IF(OR(O18="",VALUE(O18)>EOMONTH(DATEVALUE($Z$1&$J$11&1),0)-EOMONTH(DATEVALUE($Z$1&$J$11&1),-1)-1),"",O18+1) | R18: =IF(OR(X17="",VALUE(X17)>EOMONTH(DATEVALUE($Z$1&$R$11&1),0)-EOMONTH(DATEVALUE($Z$1&$R$11&1),-1)-1),"",X17+1) | S18: =IF(OR(R18="",VALUE(R18)>EOMONTH(DATEVALUE($Z$1&$R$11&1),0)-EOMONTH(DATEVALUE($Z$1&$R$11&1),-1)-1),"",R18+1) | T18: =IF(OR(S18="",VALUE(S18)>EOMONTH(DATEVALUE($Z$1&$R$11&1),0)-EOMONTH(DATEVALUE($Z$1&$R$11&1),-1)-1),"",S18+1) | U18: =IF(OR(T18="",VALUE(T18)>EOMONTH(DATEVALUE($Z$1&$R$11&1),0)-EOMONTH(DATEVALUE($Z$1&$R$11&1),-1)-1),"",T18+1) | V18: =IF(OR(U18="",VALUE(U18)>EOMONTH(DATEVALUE($Z$1&$R$11&1),0)-EOMONTH(DATEVALUE($Z$1&$R$11&1),-1)-1),"",U18+1) | W18: =IF(OR(V18="",VALUE(V18)>EOMONTH(DATEVALUE($Z$1&$R$11&1),0)-EOMONTH(DATEVALUE($Z$1&$R$11&1),-1)-1),"",V18+1) | X18: =IF(OR(W18="",VALUE(W18)>EOMONTH(DATEVALUE($Z$1&$R$11&1),0)-EOMONTH(DATEVALUE($Z$1&$R$11&1),-1)-1),"",W18+1)
B20: JULY | J20: AUGUST | R20: SEPTEMBER
B21: S | C21: M | D21: T | E21: W | F21: T | G21: F | H21: S | J21: S | K21: M | L21: T | M21: W | N21: T | O21: F | P21: S | R21: S | S21: M | T21: T | U21: W | V21: T | W21: F | X21: S
B22: =IF(WEEKDAY(DATEVALUE($Z$1&$B$20&1))=1,1,"") | C22: =IF(B22<>"",B22+1,IF(WEEKDAY(DATEVALUE($Z$1&$B$20&1))=2,1,"")) | D22: =IF(C22<>"",C22+1,IF(WEEKDAY(DATEVALUE($Z$1&$B$20&1))=3,1,"")) | E22: =IF(D22<>"",D22+1,IF(WEEKDAY(DATEVALUE($Z$1&$B$20&1))=4,1,"")) -> 1 | F22: =IF(E22<>"",E22+1,IF(WEEKDAY(DATEVALUE($Z$1&$B$20&1))=5,1,"")) -> 2 | G22: =IF(F22<>"",F22+1,IF(WEEKDAY(DATEVALUE($Z$1&$B$20&1))=6,1,"")) -> 3 | H22: =IF(G22<>"",G22+1,IF(WEEKDAY(DATEVALUE($Z$1&$B$20&1))=7,1,"")) -> 4 | J22: =IF(WEEKDAY(DATEVALUE($Z$1&$J$20&1))=1,1,"") | K22: =IF(J22<>"",J22+1,IF(WEEKDAY(DATEVALUE($Z$1&$J$20&1))=2,1,"")) | L22: =IF(K22<>"",K22+1,IF(WEEKDAY(DATEVALUE($Z$1&$J$20&1))=3,1,"")) | M22: =IF(L22<>"",L22+1,IF(WEEKDAY(DATEVALUE($Z$1&$J$20&1))=4,1,"")) | N22: =IF(M22<>"",M22+1,IF(WEEKDAY(DATEVALUE($Z$1&$J$20&1))=5,1,"")) | O22: =IF(N22<>"",N22+1,IF(WEEKDAY(DATEVALUE($Z$1&$J$20&1))=6,1,"")) | P22: =IF(O22<>"",O22+1,IF(WEEKDAY(DATEVALUE($Z$1&$J$20&1))=7,1,"")) -> 1 | R22: =IF(WEEKDAY(DATEVALUE($Z$1&$R$20&1))=1,1,"") | S22: =IF(R22<>"",R22+1,IF(WEEKDAY(DATEVALUE($Z$1&$R$20&1))=2,1,"")) | T22: =IF(S22<>"",S22+1,IF(WEEKDAY(DATEVALUE($Z$1&$R$20&1))=3,1,"")) -> 1 | U22: =IF(T22<>"",T22+1,IF(WEEKDAY(DATEVALUE($Z$1&$R$20&1))=4,1,"")) -> 2 | V22: =IF(U22<>"",U22+1,IF(WEEKDAY(DATEVALUE($Z$1&$R$20&1))=5,1,"")) -> 3 | W22: =IF(V22<>"",V22+1,IF(WEEKDAY(DATEVALUE($Z$1&$R$20&1))=6,1,"")) -> 4 | X22: =IF(W22<>"",W22+1,IF(WEEKDAY(DATEVALUE($Z$1&$R$20&1))=7,1,"")) -> 5
B23: =IF(OR(H22="",VALUE(H22)>EOMONTH(DATEVALUE($Z$1&$B$20&1),0)-EOMONTH(DATEVALUE($Z$1&$B$20&1),-1)-1),"",H22+1) -> 5 | C23: =IF(OR(B23="",VALUE(B23)>EOMONTH(DATEVALUE($Z$1&$B$20&1),0)-EOMONTH(DATEVALUE($Z$1&$B$20&1),-1)-1),"",B23+1) -> 6 | D23: =IF(OR(C23="",VALUE(C23)>EOMONTH(DATEVALUE($Z$1&$B$20&1),0)-EOMONTH(DATEVALUE($Z$1&$B$20&1),-1)-1),"",C23+1) -> 7 | E23: =IF(OR(D23="",VALUE(D23)>EOMONTH(DATEVALUE($Z$1&$B$20&1),0)-EOMONTH(DATEVALUE($Z$1&$B$20&1),-1)-1),"",D23+1) -> 8 | F23: =IF(OR(E23="",VALUE(E23)>EOMONTH(DATEVALUE($Z$1&$B$20&1),0)-EOMONTH(DATEVALUE($Z$1&$B$20&1),-1)-1),"",E23+1) -> 9 | G23: =IF(OR(F23="",VALUE(F23)>EOMONTH(DATEVALUE($Z$1&$B$20&1),0)-EOMONTH(DATEVALUE($Z$1&$B$20&1),-1)-1),"",F23+1) -> 10 | H23: =IF(OR(G23="",VALUE(G23)>EOMONTH(DATEVALUE($Z$1&$B$20&1),0)-EOMONTH(DATEVALUE($Z$1&$B$20&1),-1)-1),"",G23+1) -> 11 | J23: =IF(OR(P22="",VALUE(P22)>EOMONTH(DATEVALUE($Z$1&$J$20&1),0)-EOMONTH(DATEVALUE($Z$1&$J$20&1),-1)-1),"",P22+1) -> 2 | K23: =IF(OR(J23="",VALUE(J23)>EOMONTH(DATEVALUE($Z$1&$J$20&1),0)-EOMONTH(DATEVALUE($Z$1&$J$20&1),-1)-1),"",J23+1) -> 3 | L23: =IF(OR(K23="",VALUE(K23)>EOMONTH(DATEVALUE($Z$1&$J$20&1),0)-EOMONTH(DATEVALUE($Z$1&$J$20&1),-1)-1),"",K23+1) -> 4 | M23: =IF(OR(L23="",VALUE(L23)>EOMONTH(DATEVALUE($Z$1&$J$20&1),0)-EOMONTH(DATEVALUE($Z$1&$J$20&1),-1)-1),"",L23+1) -> 5 | N23: =IF(OR(M23="",VALUE(M23)>EOMONTH(DATEVALUE($Z$1&$J$20&1),0)-EOMONTH(DATEVALUE($Z$1&$J$20&1),-1)-1),"",M23+1) -> 6 | O23: =IF(OR(N23="",VALUE(N23)>EOMONTH(DATEVALUE($Z$1&$J$20&1),0)-EOMONTH(DATEVALUE($Z$1&$J$20&1),-1)-1),"",N23+1) -> 7 | P23: =IF(OR(O23="",VALUE(O23)>EOMONTH(DATEVALUE($Z$1&$J$20&1),0)-EOMONTH(DATEVALUE($Z$1&$J$20&1),-1)-1),"",O23+1) -> 8 | R23: =IF(OR(X22="",VALUE(X22)>EOMONTH(DATEVALUE($Z$1&$R$20&1),0)-EOMONTH(DATEVALUE($Z$1&$R$20&1),-1)-1),"",X22+1) -> 6 | S23: =IF(OR(R23="",VALUE(R23)>EOMONTH(DATEVALUE($Z$1&$R$20&1),0)-EOMONTH(DATEVALUE($Z$1&$R$20&1),-1)-1),"",R23+1) -> 7 | T23: =IF(OR(S23="",VALUE(S23)>EOMONTH(DATEVALUE($Z$1&$R$20&1),0)-EOMONTH(DATEVALUE($Z$1&$R$20&1),-1)-1),"",S23+1) -> 8 | U23: =IF(OR(T23="",VALUE(T23)>EOMONTH(DATEVALUE($Z$1&$R$20&1),0)-EOMONTH(DATEVALUE($Z$1&$R$20&1),-1)-1),"",T23+1) -> 9 | V23: =IF(OR(U23="",VALUE(U23)>EOMONTH(DATEVALUE($Z$1&$R$20&1),0)-EOMONTH(DATEVALUE($Z$1&$R$20&1),-1)-1),"",U23+1) -> 10 | W23: =IF(OR(V23="",VALUE(V23)>EOMONTH(DATEVALUE($Z$1&$R$20&1),0)-EOMONTH(DATEVALUE($Z$1&$R$20&1),-1)-1),"",V23+1) -> 11 | X23: =IF(OR(W23="",VALUE(W23)>EOMONTH(DATEVALUE($Z$1&$R$20&1),0)-EOMONTH(DATEVALUE($Z$1&$R$20&1),-1)-1),"",W23+1) -> 12
B24: =IF(OR(H23="",VALUE(H23)>EOMONTH(DATEVALUE($Z$1&$B$20&1),0)-EOMONTH(DATEVALUE($Z$1&$B$20&1),-1)-1),"",H23+1) -> 12 | C24: =IF(OR(B24="",VALUE(B24)>EOMONTH(DATEVALUE($Z$1&$B$20&1),0)-EOMONTH(DATEVALUE($Z$1&$B$20&1),-1)-1),"",B24+1) -> 13 | D24: =IF(OR(C24="",VALUE(C24)>EOMONTH(DATEVALUE($Z$1&$B$20&1),0)-EOMONTH(DATEVALUE($Z$1&$B$20&1),-1)-1),"",C24+1) -> 14 | E24: =IF(OR(D24="",VALUE(D24)>EOMONTH(DATEVALUE($Z$1&$B$20&1),0)-EOMONTH(DATEVALUE($Z$1&$B$20&1),-1)-1),"",D24+1) -> 15 | F24: =IF(OR(E24="",VALUE(E24)>EOMONTH(DATEVALUE($Z$1&$B$20&1),0)-EOMONTH(DATEVALUE($Z$1&$B$20&1),-1)-1),"",E24+1) -> 16 | G24: =IF(OR(F24="",VALUE(F24)>EOMONTH(DATEVALUE($Z$1&$B$20&1),0)-EOMONTH(DATEVALUE($Z$1&$B$20&1),-1)-1),"",F24+1) -> 17 | H24: =IF(OR(G24="",VALUE(G24)>EOMONTH(DATEVALUE($Z$1&$B$20&1),0)-EOMONTH(DATEVALUE($Z$1&$B$20&1),-1)-1),"",G24+1) -> 18 | J24: =IF(OR(P23="",VALUE(P23)>EOMONTH(DATEVALUE($Z$1&$J$20&1),0)-EOMONTH(DATEVALUE($Z$1&$J$20&1),-1)-1),"",P23+1) -> 9 | K24: =IF(OR(J24="",VALUE(J24)>EOMONTH(DATEVALUE($Z$1&$J$20&1),0)-EOMONTH(DATEVALUE($Z$1&$J$20&1),-1)-1),"",J24+1) -> 10 | L24: =IF(OR(K24="",VALUE(K24)>EOMONTH(DATEVALUE($Z$1&$J$20&1),0)-EOMONTH(DATEVALUE($Z$1&$J$20&1),-1)-1),"",K24+1) -> 11 | M24: =IF(OR(L24="",VALUE(L24)>EOMONTH(DATEVALUE($Z$1&$J$20&1),0)-EOMONTH(DATEVALUE($Z$1&$J$20&1),-1)-1),"",L24+1) -> 12 | N24: =IF(OR(M24="",VALUE(M24)>EOMONTH(DATEVALUE($Z$1&$J$20&1),0)-EOMONTH(DATEVALUE($Z$1&$J$20&1),-1)-1),"",M24+1) -> 13 | O24: =IF(OR(N24="",VALUE(N24)>EOMONTH(DATEVALUE($Z$1&$J$20&1),0)-EOMONTH(DATEVALUE($Z$1&$J$20&1),-1)-1),"",N24+1) -> 14 | P24: =IF(OR(O24="",VALUE(O24)>EOMONTH(DATEVALUE($Z$1&$J$20&1),0)-EOMONTH(DATEVALUE($Z$1&$J$20&1),-1)-1),"",O24+1) -> 15 | R24: =IF(OR(X23="",VALUE(X23)>EOMONTH(DATEVALUE($Z$1&$R$20&1),0)-EOMONTH(DATEVALUE($Z$1&$R$20&1),-1)-1),"",X23+1) -> 13 | S24: =IF(OR(R24="",VALUE(R24)>EOMONTH(DATEVALUE($Z$1&$R$20&1),0)-EOMONTH(DATEVALUE($Z$1&$R$20&1),-1)-1),"",R24+1) -> 14 | T24: =IF(OR(S24="",VALUE(S24)>EOMONTH(DATEVALUE($Z$1&$R$20&1),0)-EOMONTH(DATEVALUE($Z$1&$R$20&1),-1)-1),"",S24+1) -> 15 | U24: =IF(OR(T24="",VALUE(T24)>EOMONTH(DATEVALUE($Z$1&$R$20&1),0)-EOMONTH(DATEVALUE($Z$1&$R$20&1),-1)-1),"",T24+1) -> 16 | V24: =IF(OR(U24="",VALUE(U24)>EOMONTH(DATEVALUE($Z$1&$R$20&1),0)-EOMONTH(DATEVALUE($Z$1&$R$20&1),-1)-1),"",U24+1) -> 17 | W24: =IF(OR(V24="",VALUE(V24)>EOMONTH(DATEVALUE($Z$1&$R$20&1),0)-EOMONTH(DATEVALUE($Z$1&$R$20&1),-1)-1),"",V24+1) -> 18 | X24: =IF(OR(W24="",VALUE(W24)>EOMONTH(DATEVALUE($Z$1&$R$20&1),0)-EOMONTH(DATEVALUE($Z$1&$R$20&1),-1)-1),"",W24+1) -> 19
B25: =IF(OR(H24="",VALUE(H24)>EOMONTH(DATEVALUE($Z$1&$B$20&1),0)-EOMONTH(DATEVALUE($Z$1&$B$20&1),-1)-1),"",H24+1) -> 19 | C25: =IF(OR(B25="",VALUE(B25)>EOMONTH(DATEVALUE($Z$1&$B$20&1),0)-EOMONTH(DATEVALUE($Z$1&$B$20&1),-1)-1),"",B25+1) -> 20 | D25: =IF(OR(C25="",VALUE(C25)>EOMONTH(DATEVALUE($Z$1&$B$20&1),0)-EOMONTH(DATEVALUE($Z$1&$B$20&1),-1)-1),"",C25+1) -> 21 | E25: =IF(OR(D25="",VALUE(D25)>EOMONTH(DATEVALUE($Z$1&$B$20&1),0)-EOMONTH(DATEVALUE($Z$1&$B$20&1),-1)-1),"",D25+1) -> 22 | F25: =IF(OR(E25="",VALUE(E25)>EOMONTH(DATEVALUE($Z$1&$B$20&1),0)-EOMONTH(DATEVALUE($Z$1&$B$20&1),-1)-1),"",E25+1) -> 23 | G25: =IF(OR(F25="",VALUE(F25)>EOMONTH(DATEVALUE($Z$1&$B$20&1),0)-EOMONTH(DATEVALUE($Z$1&$B$20&1),-1)-1),"",F25+1) -> 24 | H25: =IF(OR(G25="",VALUE(G25)>EOMONTH(DATEVALUE($Z$1&$B$20&1),0)-EOMONTH(DATEVALUE($Z$1&$B$20&1),-1)-1),"",G25+1) -> 25 | J25: =IF(OR(P24="",VALUE(P24)>EOMONTH(DATEVALUE($Z$1&$J$20&1),0)-EOMONTH(DATEVALUE($Z$1&$J$20&1),-1)-1),"",P24+1) -> 16 | K25: =IF(OR(J25="",VALUE(J25)>EOMONTH(DATEVALUE($Z$1&$J$20&1),0)-EOMONTH(DATEVALUE($Z$1&$J$20&1),-1)-1),"",J25+1) -> 17 | L25: =IF(OR(K25="",VALUE(K25)>EOMONTH(DATEVALUE($Z$1&$J$20&1),0)-EOMONTH(DATEVALUE($Z$1&$J$20&1),-1)-1),"",K25+1) -> 18 | M25: =IF(OR(L25="",VALUE(L25)>EOMONTH(DATEVALUE($Z$1&$J$20&1),0)-EOMONTH(DATEVALUE($Z$1&$J$20&1),-1)-1),"",L25+1) -> 19 | N25: =IF(OR(M25="",VALUE(M25)>EOMONTH(DATEVALUE($Z$1&$J$20&1),0)-EOMONTH(DATEVALUE($Z$1&$J$20&1),-1)-1),"",M25+1) -> 20 | O25: =IF(OR(N25="",VALUE(N25)>EOMONTH(DATEVALUE($Z$1&$J$20&1),0)-EOMONTH(DATEVALUE($Z$1&$J$20&1),-1)-1),"",N25+1) -> 21 | P25: =IF(OR(O25="",VALUE(O25)>EOMONTH(DATEVALUE($Z$1&$J$20&1),0)-EOMONTH(DATEVALUE($Z$1&$J$20&1),-1)-1),"",O25+1) -> 22 | R25: =IF(OR(X24="",VALUE(X24)>EOMONTH(DATEVALUE($Z$1&$R$20&1),0)-EOMONTH(DATEVALUE($Z$1&$R$20&1),-1)-1),"",X24+1) -> 20 | S25: =IF(OR(R25="",VALUE(R25)>EOMONTH(DATEVALUE($Z$1&$R$20&1),0)-EOMONTH(DATEVALUE($Z$1&$R$20&1),-1)-1),"",R25+1) -> 21 | T25: =IF(OR(S25="",VALUE(S25)>EOMONTH(DATEVALUE($Z$1&$R$20&1),0)-EOMONTH(DATEVALUE($Z$1&$R$20&1),-1)-1),"",S25+1) -> 22 | U25: =IF(OR(T25="",VALUE(T25)>EOMONTH(DATEVALUE($Z$1&$R$20&1),0)-EOMONTH(DATEVALUE($Z$1&$R$20&1),-1)-1),"",T25+1) -> 23 | V25: =IF(OR(U25="",VALUE(U25)>EOMONTH(DATEVALUE($Z$1&$R$20&1),0)-EOMONTH(DATEVALUE($Z$1&$R$20&1),-1)-1),"",U25+1) -> 24 | W25: =IF(OR(V25="",VALUE(V25)>EOMONTH(DATEVALUE($Z$1&$R$20&1),0)-EOMONTH(DATEVALUE($Z$1&$R$20&1),-1)-1),"",V25+1) -> 25 | X25: =IF(OR(W25="",VALUE(W25)>EOMONTH(DATEVALUE($Z$1&$R$20&1),0)-EOMONTH(DATEVALUE($Z$1&$R$20&1),-1)-1),"",W25+1) -> 26
B26: =IF(OR(H25="",VALUE(H25)>EOMONTH(DATEVALUE($Z$1&$B$20&1),0)-EOMONTH(DATEVALUE($Z$1&$B$20&1),-1)-1),"",H25+1) -> 26 | C26: =IF(OR(B26="",VALUE(B26)>EOMONTH(DATEVALUE($Z$1&$B$20&1),0)-EOMONTH(DATEVALUE($Z$1&$B$20&1),-1)-1),"",B26+1) -> 27 | D26: =IF(OR(C26="",VALUE(C26)>EOMONTH(DATEVALUE($Z$1&$B$20&1),0)-EOMONTH(DATEVALUE($Z$1&$B$20&1),-1)-1),"",C26+1) -> 28 | E26: =IF(OR(D26="",VALUE(D26)>EOMONTH(DATEVALUE($Z$1&$B$20&1),0)-EOMONTH(DATEVALUE($Z$1&$B$20&1),-1)-1),"",D26+1) -> 29 | F26: =IF(OR(E26="",VALUE(E26)>EOMONTH(DATEVALUE($Z$1&$B$20&1),0)-EOMONTH(DATEVALUE($Z$1&$B$20&1),-1)-1),"",E26+1) -> 30 | G26: =IF(OR(F26="",VALUE(F26)>EOMONTH(DATEVALUE($Z$1&$B$20&1),0)-EOMONTH(DATEVALUE($Z$1&$B$20&1),-1)-1),"",F26+1) -> 31 | H26: =IF(OR(G26="",VALUE(G26)>EOMONTH(DATEVALUE($Z$1&$B$20&1),0)-EOMONTH(DATEVALUE($Z$1&$B$20&1),-1)-1),"",G26+1) | J26: =IF(OR(P25="",VALUE(P25)>EOMONTH(DATEVALUE($Z$1&$J$20&1),0)-EOMONTH(DATEVALUE($Z$1&$J$20&1),-1)-1),"",P25+1) -> 23 | K26: =IF(OR(J26="",VALUE(J26)>EOMONTH(DATEVALUE($Z$1&$J$20&1),0)-EOMONTH(DATEVALUE($Z$1&$J$20&1),-1)-1),"",J26+1) -> 24 | L26: =IF(OR(K26="",VALUE(K26)>EOMONTH(DATEVALUE($Z$1&$J$20&1),0)-EOMONTH(DATEVALUE($Z$1&$J$20&1),-1)-1),"",K26+1) -> 25 | M26: =IF(OR(L26="",VALUE(L26)>EOMONTH(DATEVALUE($Z$1&$J$20&1),0)-EOMONTH(DATEVALUE($Z$1&$J$20&1),-1)-1),"",L26+1) -> 26 | N26: =IF(OR(M26="",VALUE(M26)>EOMONTH(DATEVALUE($Z$1&$J$20&1),0)-EOMONTH(DATEVALUE($Z$1&$J$20&1),-1)-1),"",M26+1) -> 27 | O26: =IF(OR(N26="",VALUE(N26)>EOMONTH(DATEVALUE($Z$1&$J$20&1),0)-EOMONTH(DATEVALUE($Z$1&$J$20&1),-1)-1),"",N26+1) -> 28 | P26: =IF(OR(O26="",VALUE(O26)>EOMONTH(DATEVALUE($Z$1&$J$20&1),0)-EOMONTH(DATEVALUE($Z$1&$J$20&1),-1)-1),"",O26+1) -> 29 | R26: =IF(OR(X25="",VALUE(X25)>EOMONTH(DATEVALUE($Z$1&$R$20&1),0)-EOMONTH(DATEVALUE($Z$1&$R$20&1),-1)-1),"",X25+1) -> 27 | S26: =IF(OR(R26="",VALUE(R26)>EOMONTH(DATEVALUE($Z$1&$R$20&1),0)-EOMONTH(DATEVALUE($Z$1&$R$20&1),-1)-1),"",R26+1) -> 28 | T26: =IF(OR(S26="",VALUE(S26)>EOMONTH(DATEVALUE($Z$1&$R$20&1),0)-EOMONTH(DATEVALUE($Z$1&$R$20&1),-1)-1),"",S26+1) -> 29 | U26: =IF(OR(T26="",VALUE(T26)>EOMONTH(DATEVALUE($Z$1&$R$20&1),0)-EOMONTH(DATEVALUE($Z$1&$R$20&1),-1)-1),"",T26+1) -> 30 | V26: =IF(OR(U26="",VALUE(U26)>EOMONTH(DATEVALUE($Z$1&$R$20&1),0)-EOMONTH(DATEVALUE($Z$1&$R$20&1),-1)-1),"",U26+1) | W26: =IF(OR(V26="",VALUE(V26)>EOMONTH(DATEVALUE($Z$1&$R$20&1),0)-EOMONTH(DATEVALUE($Z$1&$R$20&1),-1)-1),"",V26+1) | X26: =IF(OR(W26="",VALUE(W26)>EOMONTH(DATEVALUE($Z$1&$R$20&1),0)-EOMONTH(DATEVALUE($Z$1&$R$20&1),-1)-1),"",W26+1)
B27: =IF(OR(H26="",VALUE(H26)>EOMONTH(DATEVALUE($Z$1&$B$20&1),0)-EOMONTH(DATEVALUE($Z$1&$B$20&1),-1)-1),"",H26+1) | C27: =IF(OR(B27="",VALUE(B27)>EOMONTH(DATEVALUE($Z$1&$B$20&1),0)-EOMONTH(DATEVALUE($Z$1&$B$20&1),-1)-1),"",B27+1) | D27: =IF(OR(C27="",VALUE(C27)>EOMONTH(DATEVALUE($Z$1&$B$20&1),0)-EOMONTH(DATEVALUE($Z$1&$B$20&1),-1)-1),"",C27+1) | E27: =IF(OR(D27="",VALUE(D27)>EOMONTH(DATEVALUE($Z$1&$B$20&1),0)-EOMONTH(DATEVALUE($Z$1&$B$20&1),-1)-1),"",D27+1) | F27: =IF(OR(E27="",VALUE(E27)>EOMONTH(DATEVALUE($Z$1&$B$20&1),0)-EOMONTH(DATEVALUE($Z$1&$B$20&1),-1)-1),"",E27+1) | G27: =IF(OR(F27="",VALUE(F27)>EOMONTH(DATEVALUE($Z$1&$B$20&1),0)-EOMONTH(DATEVALUE($Z$1&$B$20&1),-1)-1),"",F27+1) | H27: =IF(OR(G27="",VALUE(G27)>EOMONTH(DATEVALUE($Z$1&$B$20&1),0)-EOMONTH(DATEVALUE($Z$1&$B$20&1),-1)-1),"",G27+1) | J27: =IF(OR(P26="",VALUE(P26)>EOMONTH(DATEVALUE($Z$1&$J$20&1),0)-EOMONTH(DATEVALUE($Z$1&$J$20&1),-1)-1),"",P26+1) -> 30 | K27: =IF(OR(J27="",VALUE(J27)>EOMONTH(DATEVALUE($Z$1&$J$20&1),0)-EOMONTH(DATEVALUE($Z$1&$J$20&1),-1)-1),"",J27+1) -> 31 | L27: =IF(OR(K27="",VALUE(K27)>EOMONTH(DATEVALUE($Z$1&$J$20&1),0)-EOMONTH(DATEVALUE($Z$1&$J$20&1),-1)-1),"",K27+1) | M27: =IF(OR(L27="",VALUE(L27)>EOMONTH(DATEVALUE($Z$1&$J$20&1),0)-EOMONTH(DATEVALUE($Z$1&$J$20&1),-1)-1),"",L27+1) | N27: =IF(OR(M27="",VALUE(M27)>EOMONTH(DATEVALUE($Z$1&$J$20&1),0)-EOMONTH(DATEVALUE($Z$1&$J$20&1),-1)-1),"",M27+1) | O27: =IF(OR(N27="",VALUE(N27)>EOMONTH(DATEVALUE($Z$1&$J$20&1),0)-EOMONTH(DATEVALUE($Z$1&$J$20&1),-1)-1),"",N27+1) | P27: =IF(OR(O27="",VALUE(O27)>EOMONTH(DATEVALUE($Z$1&$J$20&1),0)-EOMONTH(DATEVALUE($Z$1&$J$20&1),-1)-1),"",O27+1) | R27: =IF(OR(X26="",VALUE(X26)>EOMONTH(DATEVALUE($Z$1&$R$20&1),0)-EOMONTH(DATEVALUE($Z$1&$R$20&1),-1)-1),"",X26+1) | S27: =IF(OR(R27="",VALUE(R27)>EOMONTH(DATEVALUE($Z$1&$R$20&1),0)-EOMONTH(DATEVALUE($Z$1&$R$20&1),-1)-1),"",R27+1) | T27: =IF(OR(S27="",VALUE(S27)>EOMONTH(DATEVALUE($Z$1&$R$20&1),0)-EOMONTH(DATEVALUE($Z$1&$R$20&1),-1)-1),"",S27+1) | U27: =IF(OR(T27="",VALUE(T27)>EOMONTH(DATEVALUE($Z$1&$R$20&1),0)-EOMONTH(DATEVALUE($Z$1&$R$20&1),-1)-1),"",T27+1) | V27: =IF(OR(U27="",VALUE(U27)>EOMONTH(DATEVALUE($Z$1&$R$20&1),0)-EOMONTH(DATEVALUE($Z$1&$R$20&1),-1)-1),"",U27+1) | W27: =IF(OR(V27="",VALUE(V27)>EOMONTH(DATEVALUE($Z$1&$R$20&1),0)-EOMONTH(DATEVALUE($Z$1&$R$20&1),-1)-1),"",V27+1) | X27: =IF(OR(W27="",VALUE(W27)>EOMONTH(DATEVALUE($Z$1&$R$20&1),0)-EOMONTH(DATEVALUE($Z$1&$R$20&1),-1)-1),"",W27+1)
B29: OCTOBER | J29: NOVEMBER | R29: DECEMBER
B30: S | C30: M | D30: T | E30: W | F30: T | G30: F | H30: S | J30: S | K30: M | L30: T | M30: W | N30: T | O30: F | P30: S | R30: S | S30: M | T30: T | U30: W | V30: T | W30: F | X30: S
B31: =IF(WEEKDAY(DATEVALUE($Z$1&$B$29&1))=1,1,"") | C31: =IF(B31<>"",B31+1,IF(WEEKDAY(DATEVALUE($Z$1&$B$29&1))=2,1,"")) | D31: =IF(C31<>"",C31+1,IF(WEEKDAY(DATEVALUE($Z$1&$B$29&1))=3,1,"")) | E31: =IF(D31<>"",D31+1,IF(WEEKDAY(DATEVALUE($Z$1&$B$29&1))=4,1,"")) | F31: =IF(E31<>"",E31+1,IF(WEEKDAY(DATEVALUE($Z$1&$B$29&1))=5,1,"")) -> 1 | G31: =IF(F31<>"",F31+1,IF(WEEKDAY(DATEVALUE($Z$1&$B$29&1))=6,1,"")) -> 2 | H31: =IF(G31<>"",G31+1,IF(WEEKDAY(DATEVALUE($Z$1&$B$29&1))=7,1,"")) -> 3 | J31: =IF(WEEKDAY(DATEVALUE($Z$1&$J$29&1))=1,1,"") -> 1 | K31: =IF(J31<>"",J31+1,IF(WEEKDAY(DATEVALUE($Z$1&$J$29&1))=2,1,"")) -> 2 | L31: =IF(K31<>"",K31+1,IF(WEEKDAY(DATEVALUE($Z$1&$J$29&1))=3,1,"")) -> 3 | M31: =IF(L31<>"",L31+1,IF(WEEKDAY(DATEVALUE($Z$1&$J$29&1))=4,1,"")) -> 4 | N31: =IF(M31<>"",M31+1,IF(WEEKDAY(DATEVALUE($Z$1&$J$29&1))=5,1,"")) -> 5 | O31: =IF(N31<>"",N31+1,IF(WEEKDAY(DATEVALUE($Z$1&$J$29&1))=6,1,"")) -> 6 | P31: =IF(O31<>"",O31+1,IF(WEEKDAY(DATEVALUE($Z$1&$J$29&1))=7,1,"")) -> 7 | R31: =IF(WEEKDAY(DATEVALUE($Z$1&$R$29&1))=1,1,"") | S31: =IF(R31<>"",R31+1,IF(WEEKDAY(DATEVALUE($Z$1&$R$29&1))=2,1,"")) | T31: =IF(S31<>"",S31+1,IF(WEEKDAY(DATEVALUE($Z$1&$R$29&1))=3,1,"")) -> 1 | U31: =IF(T31<>"",T31+1,IF(WEEKDAY(DATEVALUE($Z$1&$R$29&1))=4,1,"")) -> 2 | V31: =IF(U31<>"",U31+1,IF(WEEKDAY(DATEVALUE($Z$1&$R$29&1))=5,1,"")) -> 3 | W31: =IF(V31<>"",V31+1,IF(WEEKDAY(DATEVALUE($Z$1&$R$29&1))=6,1,"")) -> 4 | X31: =IF(W31<>"",W31+1,IF(WEEKDAY(DATEVALUE($Z$1&$R$29&1))=7,1,"")) -> 5
B32: =IF(OR(H31="",VALUE(H31)>EOMONTH(DATEVALUE($Z$1&$B$29&1),0)-EOMONTH(DATEVALUE($Z$1&$B$29&1),-1)-1),"",H31+1) -> 4 | C32: =IF(OR(B32="",VALUE(B32)>EOMONTH(DATEVALUE($Z$1&$B$29&1),0)-EOMONTH(DATEVALUE($Z$1&$B$29&1),-1)-1),"",B32+1) -> 5 | D32: =IF(OR(C32="",VALUE(C32)>EOMONTH(DATEVALUE($Z$1&$B$29&1),0)-EOMONTH(DATEVALUE($Z$1&$B$29&1),-1)-1),"",C32+1) -> 6 | E32: =IF(OR(D32="",VALUE(D32)>EOMONTH(DATEVALUE($Z$1&$B$29&1),0)-EOMONTH(DATEVALUE($Z$1&$B$29&1),-1)-1),"",D32+1) -> 7 | F32: =IF(OR(E32="",VALUE(E32)>EOMONTH(DATEVALUE($Z$1&$B$29&1),0)-EOMONTH(DATEVALUE($Z$1&$B$29&1),-1)-1),"",E32+1) -> 8 | G32: =IF(OR(F32="",VALUE(F32)>EOMONTH(DATEVALUE($Z$1&$B$29&1),0)-EOMONTH(DATEVALUE($Z$1&$B$29&1),-1)-1),"",F32+1) -> 9 | H32: =IF(OR(G32="",VALUE(G32)>EOMONTH(DATEVALUE($Z$1&$B$29&1),0)-EOMONTH(DATEVALUE($Z$1&$B$29&1),-1)-1),"",G32+1) -> 10 | J32: =IF(OR(P31="",VALUE(P31)>EOMONTH(DATEVALUE($Z$1&$J$29&1),0)-EOMONTH(DATEVALUE($Z$1&$J$29&1),-1)-1),"",P31+1) -> 8 | K32: =IF(OR(J32="",VALUE(J32)>EOMONTH(DATEVALUE($Z$1&$J$29&1),0)-EOMONTH(DATEVALUE($Z$1&$J$29&1),-1)-1),"",J32+1) -> 9 | L32: =IF(OR(K32="",VALUE(K32)>EOMONTH(DATEVALUE($Z$1&$J$29&1),0)-EOMONTH(DATEVALUE($Z$1&$J$29&1),-1)-1),"",K32+1) -> 10 | M32: =IF(OR(L32="",VALUE(L32)>EOMONTH(DATEVALUE($Z$1&$J$29&1),0)-EOMONTH(DATEVALUE($Z$1&$J$29&1),-1)-1),"",L32+1) -> 11 | N32: =IF(OR(M32="",VALUE(M32)>EOMONTH(DATEVALUE($Z$1&$J$29&1),0)-EOMONTH(DATEVALUE($Z$1&$J$29&1),-1)-1),"",M32+1) -> 12 | O32: =IF(OR(N32="",VALUE(N32)>EOMONTH(DATEVALUE($Z$1&$J$29&1),0)-EOMONTH(DATEVALUE($Z$1&$J$29&1),-1)-1),"",N32+1) -> 13 | P32: =IF(OR(O32="",VALUE(O32)>EOMONTH(DATEVALUE($Z$1&$J$29&1),0)-EOMONTH(DATEVALUE($Z$1&$J$29&1),-1)-1),"",O32+1) -> 14 | R32: =IF(OR(X31="",VALUE(X31)>EOMONTH(DATEVALUE($Z$1&$R$29&1),0)-EOMONTH(DATEVALUE($Z$1&$R$29&1),-1)-1),"",X31+1) -> 6 | S32: =IF(OR(R32="",VALUE(R32)>EOMONTH(DATEVALUE($Z$1&$R$29&1),0)-EOMONTH(DATEVALUE($Z$1&$R$29&1),-1)-1),"",R32+1) -> 7 | T32: =IF(OR(S32="",VALUE(S32)>EOMONTH(DATEVALUE($Z$1&$R$29&1),0)-EOMONTH(DATEVALUE($Z$1&$R$29&1),-1)-1),"",S32+1) -> 8 | U32: =IF(OR(T32="",VALUE(T32)>EOMONTH(DATEVALUE($Z$1&$R$29&1),0)-EOMONTH(DATEVALUE($Z$1&$R$29&1),-1)-1),"",T32+1) -> 9 | V32: =IF(OR(U32="",VALUE(U32)>EOMONTH(DATEVALUE($Z$1&$R$29&1),0)-EOMONTH(DATEVALUE($Z$1&$R$29&1),-1)-1),"",U32+1) -> 10 | W32: =IF(OR(V32="",VALUE(V32)>EOMONTH(DATEVALUE($Z$1&$R$29&1),0)-EOMONTH(DATEVALUE($Z$1&$R$29&1),-1)-1),"",V32+1) -> 11 | X32: =IF(OR(W32="",VALUE(W32)>EOMONTH(DATEVALUE($Z$1&$R$29&1),0)-EOMONTH(DATEVALUE($Z$1&$R$29&1),-1)-1),"",W32+1) -> 12
B33: =IF(OR(H32="",VALUE(H32)>EOMONTH(DATEVALUE($Z$1&$B$29&1),0)-EOMONTH(DATEVALUE($Z$1&$B$29&1),-1)-1),"",H32+1) -> 11 | C33: =IF(OR(B33="",VALUE(B33)>EOMONTH(DATEVALUE($Z$1&$B$29&1),0)-EOMONTH(DATEVALUE($Z$1&$B$29&1),-1)-1),"",B33+1) -> 12 | D33: =IF(OR(C33="",VALUE(C33)>EOMONTH(DATEVALUE($Z$1&$B$29&1),0)-EOMONTH(DATEVALUE($Z$1&$B$29&1),-1)-1),"",C33+1) -> 13 | E33: =IF(OR(D33="",VALUE(D33)>EOMONTH(DATEVALUE($Z$1&$B$29&1),0)-EOMONTH(DATEVALUE($Z$1&$B$29&1),-1)-1),"",D33+1) -> 14 | F33: =IF(OR(E33="",VALUE(E33)>EOMONTH(DATEVALUE($Z$1&$B$29&1),0)-EOMONTH(DATEVALUE($Z$1&$B$29&1),-1)-1),"",E33+1) -> 15 | G33: =IF(OR(F33="",VALUE(F33)>EOMONTH(DATEVALUE($Z$1&$B$29&1),0)-EOMONTH(DATEVALUE($Z$1&$B$29&1),-1)-1),"",F33+1) -> 16 | H33: =IF(OR(G33="",VALUE(G33)>EOMONTH(DATEVALUE($Z$1&$B$29&1),0)-EOMONTH(DATEVALUE($Z$1&$B$29&1),-1)-1),"",G33+1) -> 17 | J33: =IF(OR(P32="",VALUE(P32)>EOMONTH(DATEVALUE($Z$1&$J$29&1),0)-EOMONTH(DATEVALUE($Z$1&$J$29&1),-1)-1),"",P32+1) -> 15 | K33: =IF(OR(J33="",VALUE(J33)>EOMONTH(DATEVALUE($Z$1&$J$29&1),0)-EOMONTH(DATEVALUE($Z$1&$J$29&1),-1)-1),"",J33+1) -> 16 | L33: =IF(OR(K33="",VALUE(K33)>EOMONTH(DATEVALUE($Z$1&$J$29&1),0)-EOMONTH(DATEVALUE($Z$1&$J$29&1),-1)-1),"",K33+1) -> 17 | M33: =IF(OR(L33="",VALUE(L33)>EOMONTH(DATEVALUE($Z$1&$J$29&1),0)-EOMONTH(DATEVALUE($Z$1&$J$29&1),-1)-1),"",L33+1) -> 18 | N33: =IF(OR(M33="",VALUE(M33)>EOMONTH(DATEVALUE($Z$1&$J$29&1),0)-EOMONTH(DATEVALUE($Z$1&$J$29&1),-1)-1),"",M33+1) -> 19 | O33: =IF(OR(N33="",VALUE(N33)>EOMONTH(DATEVALUE($Z$1&$J$29&1),0)-EOMONTH(DATEVALUE($Z$1&$J$29&1),-1)-1),"",N33+1) -> 20 | P33: =IF(OR(O33="",VALUE(O33)>EOMONTH(DATEVALUE($Z$1&$J$29&1),0)-EOMONTH(DATEVALUE($Z$1&$J$29&1),-1)-1),"",O33+1) -> 21 | R33: =IF(OR(X32="",VALUE(X32)>EOMONTH(DATEVALUE($Z$1&$R$29&1),0)-EOMONTH(DATEVALUE($Z$1&$R$29&1),-1)-1),"",X32+1) -> 13 | S33: =IF(OR(R33="",VALUE(R33)>EOMONTH(DATEVALUE($Z$1&$R$29&1),0)-EOMONTH(DATEVALUE($Z$1&$R$29&1),-1)-1),"",R33+1) -> 14 | T33: =IF(OR(S33="",VALUE(S33)>EOMONTH(DATEVALUE($Z$1&$R$29&1),0)-EOMONTH(DATEVALUE($Z$1&$R$29&1),-1)-1),"",S33+1) -> 15 | U33: =IF(OR(T33="",VALUE(T33)>EOMONTH(DATEVALUE($Z$1&$R$29&1),0)-EOMONTH(DATEVALUE($Z$1&$R$29&1),-1)-1),"",T33+1) -> 16 | V33: =IF(OR(U33="",VALUE(U33)>EOMONTH(DATEVALUE($Z$1&$R$29&1),0)-EOMONTH(DATEVALUE($Z$1&$R$29&1),-1)-1),"",U33+1) -> 17 | W33: =IF(OR(V33="",VALUE(V33)>EOMONTH(DATEVALUE($Z$1&$R$29&1),0)-EOMONTH(DATEVALUE($Z$1&$R$29&1),-1)-1),"",V33+1) -> 18 | X33: =IF(OR(W33="",VALUE(W33)>EOMONTH(DATEVALUE($Z$1&$R$29&1),0)-EOMONTH(DATEVALUE($Z$1&$R$29&1),-1)-1),"",W33+1) -> 19
B34: =IF(OR(H33="",VALUE(H33)>EOMONTH(DATEVALUE($Z$1&$B$29&1),0)-EOMONTH(DATEVALUE($Z$1&$B$29&1),-1)-1),"",H33+1) -> 18 | C34: =IF(OR(B34="",VALUE(B34)>EOMONTH(DATEVALUE($Z$1&$B$29&1),0)-EOMONTH(DATEVALUE($Z$1&$B$29&1),-1)-1),"",B34+1) -> 19 | D34: =IF(OR(C34="",VALUE(C34)>EOMONTH(DATEVALUE($Z$1&$B$29&1),0)-EOMONTH(DATEVALUE($Z$1&$B$29&1),-1)-1),"",C34+1) -> 20 | E34: =IF(OR(D34="",VALUE(D34)>EOMONTH(DATEVALUE($Z$1&$B$29&1),0)-EOMONTH(DATEVALUE($Z$1&$B$29&1),-1)-1),"",D34+1) -> 21 | F34: =IF(OR(E34="",VALUE(E34)>EOMONTH(DATEVALUE($Z$1&$B$29&1),0)-EOMONTH(DATEVALUE($Z$1&$B$29&1),-1)-1),"",E34+1) -> 22 | G34: =IF(OR(F34="",VALUE(F34)>EOMONTH(DATEVALUE($Z$1&$B$29&1),0)-EOMONTH(DATEVALUE($Z$1&$B$29&1),-1)-1),"",F34+1) -> 23 | H34: =IF(OR(G34="",VALUE(G34)>EOMONTH(DATEVALUE($Z$1&$B$29&1),0)-EOMONTH(DATEVALUE($Z$1&$B$29&1),-1)-1),"",G34+1) -> 24 | J34: =IF(OR(P33="",VALUE(P33)>EOMONTH(DATEVALUE($Z$1&$J$29&1),0)-EOMONTH(DATEVALUE($Z$1&$J$29&1),-1)-1),"",P33+1) -> 22 | K34: =IF(OR(J34="",VALUE(J34)>EOMONTH(DATEVALUE($Z$1&$J$29&1),0)-EOMONTH(DATEVALUE($Z$1&$J$29&1),-1)-1),"",J34+1) -> 23 | L34: =IF(OR(K34="",VALUE(K34)>EOMONTH(DATEVALUE($Z$1&$J$29&1),0)-EOMONTH(DATEVALUE($Z$1&$J$29&1),-1)-1),"",K34+1) -> 24 | M34: =IF(OR(L34="",VALUE(L34)>EOMONTH(DATEVALUE($Z$1&$J$29&1),0)-EOMONTH(DATEVALUE($Z$1&$J$29&1),-1)-1),"",L34+1) -> 25 | N34: =IF(OR(M34="",VALUE(M34)>EOMONTH(DATEVALUE($Z$1&$J$29&1),0)-EOMONTH(DATEVALUE($Z$1&$J$29&1),-1)-1),"",M34+1) -> 26 | O34: =IF(OR(N34="",VALUE(N34)>EOMONTH(DATEVALUE($Z$1&$J$29&1),0)-EOMONTH(DATEVALUE($Z$1&$J$29&1),-1)-1),"",N34+1) -> 27 | P34: =IF(OR(O34="",VALUE(O34)>EOMONTH(DATEVALUE($Z$1&$J$29&1),0)-EOMONTH(DATEVALUE($Z$1&$J$29&1),-1)-1),"",O34+1) -> 28 | R34: =IF(OR(X33="",VALUE(X33)>EOMONTH(DATEVALUE($Z$1&$R$29&1),0)-EOMONTH(DATEVALUE($Z$1&$R$29&1),-1)-1),"",X33+1) -> 20 | S34: =IF(OR(R34="",VALUE(R34)>EOMONTH(DATEVALUE($Z$1&$R$29&1),0)-EOMONTH(DATEVALUE($Z$1&$R$29&1),-1)-1),"",R34+1) -> 21 | T34: =IF(OR(S34="",VALUE(S34)>EOMONTH(DATEVALUE($Z$1&$R$29&1),0)-EOMONTH(DATEVALUE($Z$1&$R$29&1),-1)-1),"",S34+1) -> 22 | U34: =IF(OR(T34="",VALUE(T34)>EOMONTH(DATEVALUE($Z$1&$R$29&1),0)-EOMONTH(DATEVALUE($Z$1&$R$29&1),-1)-1),"",T34+1) -> 23 | V34: =IF(OR(U34="",VALUE(U34)>EOMONTH(DATEVALUE($Z$1&$R$29&1),0)-EOMONTH(DATEVALUE($Z$1&$R$29&1),-1)-1),"",U34+1) -> 24 | W34: =IF(OR(V34="",VALUE(V34)>EOMONTH(DATEVALUE($Z$1&$R$29&1),0)-EOMONTH(DATEVALUE($Z$1&$R$29&1),-1)-1),"",V34+1) -> 25 | X34: =IF(OR(W34="",VALUE(W34)>EOMONTH(DATEVALUE($Z$1&$R$29&1),0)-EOMONTH(DATEVALUE($Z$1&$R$29&1),-1)-1),"",W34+1) -> 26
B35: =IF(OR(H34="",VALUE(H34)>EOMONTH(DATEVALUE($Z$1&$B$29&1),0)-EOMONTH(DATEVALUE($Z$1&$B$29&1),-1)-1),"",H34+1) -> 25 | C35: =IF(OR(B35="",VALUE(B35)>EOMONTH(DATEVALUE($Z$1&$B$29&1),0)-EOMONTH(DATEVALUE($Z$1&$B$29&1),-1)-1),"",B35+1) -> 26 | D35: =IF(OR(C35="",VALUE(C35)>EOMONTH(DATEVALUE($Z$1&$B$29&1),0)-EOMONTH(DATEVALUE($Z$1&$B$29&1),-1)-1),"",C35+1) -> 27 | E35: =IF(OR(D35="",VALUE(D35)>EOMONTH(DATEVALUE($Z$1&$B$29&1),0)-EOMONTH(DATEVALUE($Z$1&$B$29&1),-1)-1),"",D35+1) -> 28 | F35: =IF(OR(E35="",VALUE(E35)>EOMONTH(DATEVALUE($Z$1&$B$29&1),0)-EOMONTH(DATEVALUE($Z$1&$B$29&1),-1)-1),"",E35+1) -> 29 | G35: =IF(OR(F35="",VALUE(F35)>EOMONTH(DATEVALUE($Z$1&$B$29&1),0)-EOMONTH(DATEVALUE($Z$1&$B$29&1),-1)-1),"",F35+1) -> 30 | H35: =IF(OR(G35="",VALUE(G35)>EOMONTH(DATEVALUE($Z$1&$B$29&1),0)-EOMONTH(DATEVALUE($Z$1&$B$29&1),-1)-1),"",G35+1) -> 31 | J35: =IF(OR(P34="",VALUE(P34)>EOMONTH(DATEVALUE($Z$1&$J$29&1),0)-EOMONTH(DATEVALUE($Z$1&$J$29&1),-1)-1),"",P34+1) -> 29 | K35: =IF(OR(J35="",VALUE(J35)>EOMONTH(DATEVALUE($Z$1&$J$29&1),0)-EOMONTH(DATEVALUE($Z$1&$J$29&1),-1)-1),"",J35+1) -> 30 | L35: =IF(OR(K35="",VALUE(K35)>EOMONTH(DATEVALUE($Z$1&$J$29&1),0)-EOMONTH(DATEVALUE($Z$1&$J$29&1),-1)-1),"",K35+1) | M35: =IF(OR(L35="",VALUE(L35)>EOMONTH(DATEVALUE($Z$1&$J$29&1),0)-EOMONTH(DATEVALUE($Z$1&$J$29&1),-1)-1),"",L35+1) | N35: =IF(OR(M35="",VALUE(M35)>EOMONTH(DATEVALUE($Z$1&$J$29&1),0)-EOMONTH(DATEVALUE($Z$1&$J$29&1),-1)-1),"",M35+1) | O35: =IF(OR(N35="",VALUE(N35)>EOMONTH(DATEVALUE($Z$1&$J$29&1),0)-EOMONTH(DATEVALUE($Z$1&$J$29&1),-1)-1),"",N35+1) | P35: =IF(OR(O35="",VALUE(O35)>EOMONTH(DATEVALUE($Z$1&$J$29&1),0)-EOMONTH(DATEVALUE($Z$1&$J$29&1),-1)-1),"",O35+1) | R35: =IF(OR(X34="",VALUE(X34)>EOMONTH(DATEVALUE($Z$1&$R$29&1),0)-EOMONTH(DATEVALUE($Z$1&$R$29&1),-1)-1),"",X34+1) -> 27 | S35: =IF(OR(R35="",VALUE(R35)>EOMONTH(DATEVALUE($Z$1&$R$29&1),0)-EOMONTH(DATEVALUE($Z$1&$R$29&1),-1)-1),"",R35+1) -> 28 | T35: =IF(OR(S35="",VALUE(S35)>EOMONTH(DATEVALUE($Z$1&$R$29&1),0)-EOMONTH(DATEVALUE($Z$1&$R$29&1),-1)-1),"",S35+1) -> 29 | U35: =IF(OR(T35="",VALUE(T35)>EOMONTH(DATEVALUE($Z$1&$R$29&1),0)-EOMONTH(DATEVALUE($Z$1&$R$29&1),-1)-1),"",T35+1) -> 30 | V35: =IF(OR(U35="",VALUE(U35)>EOMONTH(DATEVALUE($Z$1&$R$29&1),0)-EOMONTH(DATEVALUE($Z$1&$R$29&1),-1)-1),"",U35+1) -> 31 | W35: =IF(OR(V35="",VALUE(V35)>EOMONTH(DATEVALUE($Z$1&$R$29&1),0)-EOMONTH(DATEVALUE($Z$1&$R$29&1),-1)-1),"",V35+1) | X35: =IF(OR(W35="",VALUE(W35)>EOMONTH(DATEVALUE($Z$1&$R$29&1),0)-EOMONTH(DATEVALUE($Z$1&$R$29&1),-1)-1),"",W35+1)
B36: =IF(OR(H35="",VALUE(H35)>EOMONTH(DATEVALUE($Z$1&$B$29&1),0)-EOMONTH(DATEVALUE($Z$1&$B$29&1),-1)-1),"",H35+1) | C36: =IF(OR(B36="",VALUE(B36)>EOMONTH(DATEVALUE($Z$1&$B$29&1),0)-EOMONTH(DATEVALUE($Z$1&$B$29&1),-1)-1),"",B36+1) | D36: =IF(OR(C36="",VALUE(C36)>EOMONTH(DATEVALUE($Z$1&$B$29&1),0)-EOMONTH(DATEVALUE($Z$1&$B$29&1),-1)-1),"",C36+1) | E36: =IF(OR(D36="",VALUE(D36)>EOMONTH(DATEVALUE($Z$1&$B$29&1),0)-EOMONTH(DATEVALUE($Z$1&$B$29&1),-1)-1),"",D36+1) | F36: =IF(OR(E36="",VALUE(E36)>EOMONTH(DATEVALUE($Z$1&$B$29&1),0)-EOMONTH(DATEVALUE($Z$1&$B$29&1),-1)-1),"",E36+1) | G36: =IF(OR(F36="",VALUE(F36)>EOMONTH(DATEVALUE($Z$1&$B$29&1),0)-EOMONTH(DATEVALUE($Z$1&$B$29&1),-1)-1),"",F36+1) | H36: =IF(OR(G36="",VALUE(G36)>EOMONTH(DATEVALUE($Z$1&$B$29&1),0)-EOMONTH(DATEVALUE($Z$1&$B$29&1),-1)-1),"",G36+1) | J36: =IF(OR(P35="",VALUE(P35)>EOMONTH(DATEVALUE($Z$1&$J$29&1),0)-EOMONTH(DATEVALUE($Z$1&$J$29&1),-1)-1),"",P35+1) | K36: =IF(OR(J36="",VALUE(J36)>EOMONTH(DATEVALUE($Z$1&$J$29&1),0)-EOMONTH(DATEVALUE($Z$1&$J$29&1),-1)-1),"",J36+1) | L36: =IF(OR(K36="",VALUE(K36)>EOMONTH(DATEVALUE($Z$1&$J$29&1),0)-EOMONTH(DATEVALUE($Z$1&$J$29&1),-1)-1),"",K36+1) | M36: =IF(OR(L36="",VALUE(L36)>EOMONTH(DATEVALUE($Z$1&$J$29&1),0)-EOMONTH(DATEVALUE($Z$1&$J$29&1),-1)-1),"",L36+1) | N36: =IF(OR(M36="",VALUE(M36)>EOMONTH(DATEVALUE($Z$1&$J$29&1),0)-EOMONTH(DATEVALUE($Z$1&$J$29&1),-1)-1),"",M36+1) | O36: =IF(OR(N36="",VALUE(N36)>EOMONTH(DATEVALUE($Z$1&$J$29&1),0)-EOMONTH(DATEVALUE($Z$1&$J$29&1),-1)-1),"",N36+1) | P36: =IF(OR(O36="",VALUE(O36)>EOMONTH(DATEVALUE($Z$1&$J$29&1),0)-EOMONTH(DATEVALUE($Z$1&$J$29&1),-1)-1),"",O36+1) | R36: =IF(OR(X35="",VALUE(X35)>EOMONTH(DATEVALUE($Z$1&$R$29&1),0)-EOMONTH(DATEVALUE($Z$1&$R$29&1),-1)-1),"",X35+1) | S36: =IF(OR(R36="",VALUE(R36)>EOMONTH(DATEVALUE($Z$1&$R$29&1),0)-EOMONTH(DATEVALUE($Z$1&$R$29&1),-1)-1),"",R36+1) | T36: =IF(OR(S36="",VALUE(S36)>EOMONTH(DATEVALUE($Z$1&$R$29&1),0)-EOMONTH(DATEVALUE($Z$1&$R$29&1),-1)-1),"",S36+1) | U36: =IF(OR(T36="",VALUE(T36)>EOMONTH(DATEVALUE($Z$1&$R$29&1),0)-EOMONTH(DATEVALUE($Z$1&$R$29&1),-1)-1),"",T36+1) | V36: =IF(OR(U36="",VALUE(U36)>EOMONTH(DATEVALUE($Z$1&$R$29&1),0)-EOMONTH(DATEVALUE($Z$1&$R$29&1),-1)-1),"",U36+1) | W36: =IF(OR(V36="",VALUE(V36)>EOMONTH(DATEVALUE($Z$1&$R$29&1),0)-EOMONTH(DATEVALUE($Z$1&$R$29&1),-1)-1),"",V36+1) | X36: =IF(OR(W36="",VALUE(W36)>EOMONTH(DATEVALUE($Z$1&$R$29&1),0)-EOMONTH(DATEVALUE($Z$1&$R$29&1),-1)-1),"",W36+1)

Sheet Customize your calendar
B1: Go to Format >> Theme
B2: Bring your personal style into your annual planning
B3: This calendar will automatically update based on the year. You can also manually change the year in the first sheet. Explore 16 different themes to personalize your calendar - Simply go to the "Format" menu and select "Theme" - Browse and select from one of the preset Themes in the side panel - Use the themes as-is or you can add your own style by clicking "Customize"
B6: Streamline
B9: Retro
B12: Coral
B14: TIP: Insert images into cells by using: Insert >> Image >> Image in cell

Sheet Instructions
A1: # | B1: TTP TRACKER: INSTRUCTIONS | D1: Promo Name: | E1: ='Promo Info'!C1 -> #REF!
A2: ### | B2: WHAT IS THIS THING?
A3: - | B3: TTP Tracker is a tool for planning monthly resources for your desired STT boost goal. | D3: Length: | E3: ='Promo Info'!F2 -> #REF! | F3: =TEXT('Promo Info'!C2,"mm/dd") -> #REF! | G3: =TEXT('Promo Info'!C3,"mm/dd") -> #REF!
A4: ### | B4: GETTING STARTED:
A5: - | B5: Results are ESTIMATED! | D5: UC | E5: ='Promo Info'!L5 -> #REF!
A6: - | B6: On a web browser, Click File > Make a Copy. Or on the Google Sheets app ... > Share & Export > Make a Copy | E6: 250
A7: - | B7: Fill out any Light Green cells. Results are displayed in Blue cells.
A8: ### | B8: MORE COMING SOON...
A9: -
A12: -
A15: ###
A16: -
A17: -

Sheet Boostimator 26
B1: BOOSTIMATOR 26 | E1: FINAL OVR: | F1: =sum(K40:Q40,L45:P45,K52:R52,L57:Q57,M64:P64,R33) -> 3605.7495 | G1: TTP NEEDED: | H1: =sum(O61,P49,P37)-sum(O28,P16,P4) -> 130500 | I1: by phredd & jawabomb
B2: MY GOAL | E2: TARGET OVR: | F2: 3600
B3: MY CURRENT LINEUP | E3: CURRENT OVR: | F3: =SUM(B7:H7,C12:G12,B19:I19,C24:H24,D31:G31) -> 3470.3 | K3: QB | L3: HB/FB | M3: TE | N3: WR | O3: C/OG/OT | P3: COST
B4: OFFENSE | C4: RANK: | D4: 21 | K4: =vlookup($D$4,'Boost Data'!$A$1:$F$52,2,0) -> 9 | L4: =vlookup($D$4,'Boost Data'!$A$1:$F$52,3,0) -> 9 | M4: =vlookup($D$4,'Boost Data'!$A$1:$F$52,4,0) -> 9 | N4: =vlookup($D$4,'Boost Data'!$A$1:$F$52,5,0) -> 9 | O4: =vlookup($D$4,'Boost Data'!$A$1:$F$52,6,0) -> 9 | P4: =VLOOKUP(D4,'Boost Data'!$A$1:$G$52,7,0) -> 16660
K5: =hlookup(K6,$K3:$O4,2,0)/100 -> 0.09 | L5: =hlookup(L6,$K3:$O4,2,0)/100 -> 0.09 | M5: =hlookup(M6,$K3:$O4,2,0)/100 -> 0.09 | N5: =hlookup(N6,$K3:$O4,2,0)/100 -> 0.09 | O5: =hlookup(O6,$K3:$O4,2,0)/100 -> 0.09 | P5: =hlookup(P6,$K3:$O4,2,0)/100 -> 0.09 | Q5: =hlookup(Q6,$K3:$O4,2,0)/100 -> 0.09
B6: WR1 | C6: LEFT OT | D6: LEFT OG | E6: C | F6: RIGHT OG | G6: RIGHT OT | H6: WR2 | K6: WR | L6: C/OG/OT | M6: C/OG/OT | N6: C/OG/OT | O6: C/OG/OT | P6: C/OG/OT | Q6: WR
B7: 141 | C7: 99 | D7: 106 | E7: 106 | F7: 127 | G7: 140 | H7: 121 | K7: =(B7-K8-K9)/(1+K5) -> 124.77064 | L7: =(C7-L8-L9)/(1+L5) -> 90.825688 | M7: =(D7-M8-M9)/(1+M5) -> 97.247706 | N7: =(E7-N8-N9)/(1+N5) -> 97.247706 | O7: =(F7-O8-O9)/(1+O5) -> 116.51376 | P7: =(G7-P8-P9)/(1+P5) -> 123.85321 | Q7: =(H7-Q8-Q9)/(1+Q5) -> 111.00917
B8: Mythic +1 | G8: Mythic +1 | K8: =if(ISBLANK(B8)=FALSE,$P$28,0) -> 5 | L8: =if(ISBLANK(C8)=FALSE,$P$28,0) -> 0 | M8: =if(ISBLANK(D8)=FALSE,$P$28,0) -> 0 | N8: =if(ISBLANK(E8)=FALSE,$P$28,0) -> 0 | O8: =if(ISBLANK(F8)=FALSE,$P$28,0) -> 0 | P8: =if(ISBLANK(G8)=FALSE,$P$28,0) -> 5 | Q8: =if(ISBLANK(H8)=FALSE,$P$28,0) -> 0
K9: =if(B9="2 from Dual",2,0)+if(B9="1 from Dual",1,0) -> 0 | L9: =if(C9="2 from Dual",2,0)+if(C9="1 from Dual",1,0) -> 0 | M9: =if(D9="2 from Dual",2,0)+if(D9="1 from Dual",1,0) -> 0 | N9: =if(E9="2 from Dual",2,0)+if(E9="1 from Dual",1,0) -> 0 | O9: =if(F9="2 from Dual",2,0)+if(F9="1 from Dual",1,0) -> 0 | P9: =if(G9="2 from Dual",2,0)+if(G9="1 from Dual",1,0) -> 0 | Q9: =if(H9="2 from Dual",2,0)+if(H9="1 from Dual",1,0) -> 0
L10: =hlookup(L11,$K$3:$O$4,2,0)/100 -> 0.09 | M10: =hlookup(M11,$K$3:$O$4,2,0)/100 -> 0.09 | N10: =hlookup(N11,$K$3:$O$4,2,0)/100 -> 0.09 | O10: =hlookup(O11,$K$3:$O$4,2,0)/100 -> 0.09 | P10: =hlookup(P11,$K$3:$O$4,2,0)/100 -> 0.09
C11: WR | D11: HB | E11: QB | F11: HB/FB | G11: TE | L11: =C11 -> WR | M11: HB/FB | N11: QB | O11: HB/FB | P11: TE
C12: 120 | D12: 119 | E12: 118 | F12: 119 | G12: 129 | L12: =(C12-L13-L14)/(1+L10) -> 110.09174 | M12: =(D12-M13-M14)/(1+M10) -> 109.17431 | N12: =(E12-N13-N14)/(1+N10) -> 108.25688 | O12: =(F12-O13-O14)/(1+O10) -> 109.17431 | P12: =(G12-P13-P14)/(1+P10) -> 118.34862
L13: =if(ISBLANK(C13)=FALSE,$P$28,0) -> 0 | M13: =if(ISBLANK(D13)=FALSE,$P$28,0) -> 0 | N13: =if(ISBLANK(E13)=FALSE,$P$28,0) -> 0 | O13: =if(ISBLANK(F13)=FALSE,$P$28,0) -> 0 | P13: =if(ISBLANK(G13)=FALSE,$P$28,0) -> 0
L14: =if(C14="2 from Dual",2,0)+if(C14="1 from Dual",1,0) -> 0 | M14: =if(D14="2 from Dual",2,0)+if(D14="1 from Dual",1,0) -> 0 | N14: =if(E14="2 from Dual",2,0)+if(E14="1 from Dual",1,0) -> 0 | O14: =if(F14="2 from Dual",2,0)+if(F14="1 from Dual",1,0) -> 0 | P14: =if(G14="2 from Dual",2,0)+if(G14="1 from Dual",1,0) -> 0
K15: LB/MLB | L15: CB | M15: S | N15: DT | O15: DE | P15: COST
B16: DEFENSE | C16: RANK: | D16: 21 | K16: =vlookup($D$16,'Boost Data'!$J$1:$O$52,2,0) -> 9 | L16: =vlookup($D$16,'Boost Data'!$J$1:$O$52,2,0) -> 9 | M16: =vlookup($D$16,'Boost Data'!$J$1:$O$52,2,0) -> 9 | N16: =vlookup($D$16,'Boost Data'!$J$1:$O$52,2,0) -> 9 | O16: =vlookup($D$16,'Boost Data'!$J$1:$O$52,2,0) -> 9 | P16: =VLOOKUP(D16,'Boost Data'!$J$1:$P$52,7,0) -> 17550
K17: =hlookup(K18,$K$15:$O$16,2,0)/100 -> 0.09 | L17: =hlookup(L18,$K$15:$O$16,2,0)/100 -> 0.09 | M17: =hlookup(M18,$K$15:$O$16,2,0)/100 -> 0.09 | N17: =hlookup(N18,$K$15:$O$16,2,0)/100 -> 0.09 | O17: =hlookup(O18,$K$15:$O$16,2,0)/100 -> 0.09 | P17: =hlookup(P18,$K$15:$O$16,2,0)/100 -> 0.09 | Q17: =hlookup(Q18,$K$15:$O$16,2,0)/100 -> 0.09 | R17: =hlookup(R18,$K$15:$O$16,2,0)/100 -> 0.09
B18: CB1 | C18: SS | D18: LEFT LB | E18: MLB | F18: MLB | G18: RIGHT LB | H18: FS | I18: CB2 | K18: CB | L18: S | M18: LB/MLB | N18: LB/MLB | O18: LB/MLB | P18: LB/MLB | Q18: S | R18: CB
B19: 116 | C19: 138 | D19: 103 | E19: 116 | F19: 103 | G19: 103 | H19: 116 | I19: 116 | K19: =(B19-K20-K21)/(1+K17) -> 106.42202 | L19: =(C19-L20-L21)/(1+L17) -> 122.01835 | M19: =(D19-M20-M21)/(1+M17) -> 94.495413 | N19: =(E19-N20-N21)/(1+N17) -> 106.42202 | O19: =(F19-O20-O21)/(1+O17) -> 94.495413 | P19: =(G19-P20-P21)/(1+P17) -> 94.495413 | Q19: =(H19-Q20-Q21)/(1+Q17) -> 106.42202 | R19: =(I19-R20-R21)/(1+R17) -> 106.42202
C20: Mythic +1 | K20: =if(ISBLANK(B20)=FALSE,$P$28,0) -> 0 | L20: =if(ISBLANK(C20)=FALSE,$P$28,0) -> 5 | M20: =if(ISBLANK(D20)=FALSE,$P$28,0) -> 0 | N20: =if(ISBLANK(E20)=FALSE,$P$28,0) -> 0 | O20: =if(ISBLANK(F20)=FALSE,$P$28,0) -> 0 | P20: =if(ISBLANK(G20)=FALSE,$P$28,0) -> 0 | Q20: =if(ISBLANK(H20)=FALSE,$P$28,0) -> 0 | R20: =if(ISBLANK(I20)=FALSE,$P$28,0) -> 0
K21: =if(B21="2 from Dual",2,0)+if(B21="1 from Dual",1,0) -> 0 | L21: =if(C21="2 from Dual",2,0)+if(C21="1 from Dual",1,0) -> 0 | M21: =if(D21="2 from Dual",2,0)+if(D21="1 from Dual",1,0) -> 0 | N21: =if(E21="2 from Dual",2,0)+if(E21="1 from Dual",1,0) -> 0 | O21: =if(F21="2 from Dual",2,0)+if(F21="1 from Dual",1,0) -> 0 | P21: =if(G21="2 from Dual",2,0)+if(G21="1 from Dual",1,0) -> 0 | Q21: =if(H21="2 from Dual",2,0)+if(H21="1 from Dual",1,0) -> 0 | R21: =if(I21="2 from Dual",2,0)+if(I21="1 from Dual",1,0) -> 0
L22: =hlookup(L23,$K$15:$O$16,2,0)/100 -> 0.09 | M22: =hlookup(M23,$K$15:$O$16,2,0)/100 -> 0.09 | N22: =hlookup(N23,$K$15:$O$16,2,0)/100 -> 0.09 | O22: =hlookup(O23,$K$15:$O$16,2,0)/100 -> 0.09 | P22: =hlookup(P23,$K$15:$O$16,2,0)/100 -> 0.09 | Q22: =hlookup(Q23,$K$15:$O$16,2,0)/100 -> 0.09
C23: CB | D23: DE | E23: DT | F23: DT | G23: DE | H23: CB | L23: =C23 -> CB | M23: =D23 -> DE | N23: =E23 -> DT | O23: =F23 -> DT | P23: =G23 -> DE | Q23: =H23 -> CB
C24: 102 | D24: 115 | E24: 136 | F24: 115 | G24: 102 | H24: 102 | L24: =(C24-L25-L26)/(1+L22) -> 93.577982 | M24: =(D24-M25-M26)/(1+M22) -> 105.50459 | N24: =(E24-N25-N26)/(1+N22) -> 120.18349 | O24: =(F24-O25-O26)/(1+O22) -> 105.50459 | P24: =(G24-P25-P26)/(1+P22) -> 93.577982 | Q24: =(H24-Q25-Q26)/(1+Q22) -> 93.577982
E25: Mythic +1 | L25: =if(ISBLANK(C25)=FALSE,$P$28,0) -> 0 | M25: =if(ISBLANK(D25)=FALSE,$P$28,0) -> 0 | N25: =if(ISBLANK(E25)=FALSE,$P$28,0) -> 5 | O25: =if(ISBLANK(F25)=FALSE,$P$28,0) -> 0 | P25: =if(ISBLANK(G25)=FALSE,$P$28,0) -> 0 | Q25: =if(ISBLANK(H25)=FALSE,$P$28,0) -> 0
L26: =if(C26="2 from Dual",2,0)+if(C26="1 from Dual",1,0) -> 0 | M26: =if(D26="2 from Dual",2,0)+if(D26="1 from Dual",1,0) -> 0 | N26: =if(E26="2 from Dual",2,0)+if(E26="1 from Dual",1,0) -> 0 | O26: =if(F26="2 from Dual",2,0)+if(F26="1 from Dual",1,0) -> 0 | P26: =if(G26="2 from Dual",2,0)+if(G26="1 from Dual",1,0) -> 0 | Q26: =if(H26="2 from Dual",2,0)+if(H26="1 from Dual",1,0) -> 0
K27: K | L27: KR | M27: P | N27: PR | O27: COST | P27: Mythic Boosts | Q27: Dual Mythic | R27: Dual Iconic
B28: SPECIAL | C28: RANK: | D28: 31 | K28: =vlookup($D$28,'Boost Data'!$S$1:$W$52,2,0) -> 13 | L28: =vlookup($D$28,'Boost Data'!$S$1:$W$52,2,0) -> 13 | M28: =vlookup($D$28,'Boost Data'!$S$1:$W$52,2,0) -> 13 | N28: =vlookup($D$28,'Boost Data'!$S$1:$W$52,2,0) -> 13 | O28: =VLOOKUP(D28,'Boost Data'!$S$1:$X$52,6,0) -> 15820 | P28: =Countif($B$3:$I$33, "Mythic +1") -> 5
M29: =hlookup(M30,$K$27:$N$28,2,0)/100 -> 0.13 | N29: =hlookup(N30,$K$27:$N$28,2,0)/100 -> 0.13 | O29: =hlookup(O30,$K$27:$N$28,2,0)/100 -> 0.13 | P29: =hlookup(P30,$K$27:$N$28,2,0)/100 -> 0.13
D30: K | E30: KR | F30: P | G30: PR | M30: =D30 -> K | N30: =E30 -> KR | O30: =F30 -> P | P30: =G30 -> PR
D31: 102.4 | E31: 136 | F31: 102.2 | G31: 101.7 | M31: =(D31-M32-M33)/(1+M29) -> 90.619469 | N31: =(E31-N32-N33)/(1+N29) -> 115.9292 | O31: =(F31-O32-O33)/(1+O29) -> 90.442478 | P31: =(G31-P32-P33)/(1+P29) -> 90
E32: Mythic +1 | M32: =if(ISBLANK(D32)=FALSE,$P$28,0) -> 0 | N32: =if(ISBLANK(E32)=FALSE,$P$28,0) -> 5 | O32: =if(ISBLANK(F32)=FALSE,$P$28,0) -> 0 | P32: =if(ISBLANK(G32)=FALSE,$P$28,0) -> 0 | R32: Extra
M33: =if(D33="2 from Dual",2,0)+if(D33="1 from Dual",1,0) -> 0 | N33: =if(E33="2 from Dual",2,0)+if(E33="1 from Dual",1,0) -> 0 | O33: =if(F33="2 from Dual",2,0)+if(F33="1 from Dual",1,0) -> 0 | P33: =if(G33="2 from Dual",2,0)+if(G33="1 from Dual",1,0) -> 0 | R33: =I2*P28 -> 0
B35: RANK UP | K35: 2 | L35: 3 | M35: 4 | N35: 5 | O35: 6
B36: OFFENSE | H36: TARGET RANK | K36: QB | L36: HB/FB | M36: TE | N36: WR | O36: C/OG/OT | P36: COST
B37: QB | C37: HB/FB | D37: TE | E37: WR | F37: C/OG/OT | H37: 40 | K37: =vlookup($H$37,'Boost Data'!$A$1:$F$52,K$35,0) -> 16 | L37: =vlookup($H$37,'Boost Data'!$A$1:$F$52,L35,0) -> 16 | M37: =vlookup($H$37,'Boost Data'!$A$1:$F$52,M35,0) -> 16 | N37: =vlookup($H$37,'Boost Data'!$A$1:$F$52,N35,0) -> 16 | O37: =vlookup($H$37,'Boost Data'!$A$1:$F$52,O35,0) -> 16 | P37: =VLOOKUP(H37,'Boost Data'!$A$1:$G$52,7,0) -> 117960
B38: =K4&"% ⏩ "&K37&"%" -> 9% ⏩ 16% | C38: =L4&"% ⏩ "&L37&"%" -> 9% ⏩ 16% | D38: =M4&"% ⏩ "&M37&"%" -> 9% ⏩ 16% | E38: =N4&"% ⏩ "&N37&"%" -> 9% ⏩ 16% | F38: =O4&"% ⏩ "&O37&"%" -> 9% ⏩ 16% | K38: =hlookup(K39,$K36:$O37,2,0) -> 16 | L38: =hlookup(L39,$K$36:$O$37,2,0) -> 16 | M38: =hlookup(M39,$K36:$O37,2,0) -> 16 | N38: =hlookup(N39,$K36:$O37,2,0) -> 16 | O38: =hlookup(O39,$K36:$O37,2,0) -> 16 | P38: =hlookup(P39,$K36:$O37,2,0) -> 16 | Q38: =hlookup(Q39,$K36:$O37,2,0) -> 16
K39: =K6 -> WR | L39: =L6 -> C/OG/OT | M39: =M6 -> C/OG/OT | N39: =N6 -> C/OG/OT | O39: =O6 -> C/OG/OT | P39: =P6 -> C/OG/OT | Q39: =Q6 -> WR
B40: DEFENSE | H40: TARGET RANK | K40: =K7+(K7*(K38/100))+K41+K42 -> 149.73395 | L40: =L7+(L7*(L38/100))+L41+L42 -> 105.3578 | M40: =M7+(M7*(M38/100))+M41+M42 -> 112.80734 | N40: =N7+(N7*(N38/100))+N41+N42 -> 112.80734 | O40: =O7+(O7*(O38/100))+O41+O42 -> 135.15596 | P40: =P7+(P7*(P38/100))+P41+P42 -> 148.66972 | Q40: =Q7+(Q7*(Q38/100))+Q41+Q42 -> 128.77064
B41: LB/MLB | C41: CB | D41: S | E41: DT | F41: DE | H41: 30 | K41: =if(isblank(B8),0,$P$61) -> 5 | L41: =if(isblank(C8),0,$P$61) -> 0 | M41: =if(isblank(D8),0,$P$61) -> 0 | N41: =if(isblank(E8),0,$P$61) -> 0 | O41: =if(isblank(F8),0,$P$61) -> 0 | P41: =if(isblank(G8),0,$P$61) -> 5 | Q41: =if(isblank(H8),0,$P$61) -> 0
B42: =K16&"% ⏩ "&K49&"%" -> 9% ⏩ 12% | C42: =L16&"% ⏩ "&L49&"%" -> 9% ⏩ 12% | D42: =M16&"% ⏩ "&M49&"%" -> 9% ⏩ 12% | E42: =N16&"% ⏩ "&N49&"%" -> 9% ⏩ 12% | F42: =O16&"% ⏩ "&O49&"%" -> 9% ⏩ 12% | K42: =K9 -> 0 | L42: =L9 -> 0 | M42: =M9 -> 0 | N42: =N9 -> 0 | O42: =O9 -> 0 | P42: =P9 -> 0 | Q42: =Q9 -> 0
L43: =hlookup(L44,$K$36:$O$37,2,0) -> 16 | M43: =hlookup(M44,$K$36:$O$37,2,0) -> 16 | N43: =hlookup(N44,$K$36:$O$37,2,0) -> 16 | O43: =hlookup(O44,$K$36:$O$37,2,0) -> 16 | P43: =hlookup(P44,$K$36:$O$37,2,0) -> 16
B44: SPECIAL | H44: TARGET RANK | L44: =L11 -> WR | M44: =M11 -> HB/FB | N44: =N11 -> QB | O44: =O11 -> HB/FB | P44: =P11 -> TE
B45: K | C45: KR | D45: P | E45: PR | H45: 31 | L45: =L12+(L12*(L43/100))+L46+L47 -> 127.70642 | M45: =M12+(M12*(M43/100))+M46+M47 -> 126.6422 | N45: =N12+(N12*(N43/100))+N46+N47 -> 125.57798 | O45: =O12+(O12*(O43/100))+O46+O47 -> 126.6422 | P45: =P12+(P12*(P43/100))+P46+P47 -> 137.2844
B46: =K28&"% ⏩ "&K61&"%" -> 13% ⏩ 13% | C46: =L28&"% ⏩ "&L61&"%" -> 13% ⏩ 13% | D46: =M28&"% ⏩ "&M61&"%" -> 13% ⏩ 13% | E46: =N28&"% ⏩ "&N61&"%" -> 13% ⏩ 13% | L46: =if(isblank(C13),0,$P$61) -> 0 | M46: =if(isblank(D13),0,$P$61) -> 0 | N46: =if(isblank(E13),0,$P$61) -> 0 | O46: =if(isblank(F13),0,$P$61) -> 0 | P46: =if(isblank(G13),0,$P$61) -> 0
L47: =L14 -> 0 | M47: =M14 -> 0 | N47: =N14 -> 0 | O47: =O14 -> 0 | P47: =P14 -> 0
K48: LB/MLB | L48: CB | M48: S | N48: DT | O48: DE | P48: COST
K49: =vlookup($H$41,'Boost Data'!$J$1:$O$52,K35,0) -> 12 | L49: =vlookup($H$41,'Boost Data'!$J$1:$O$52,L35,0) -> 12 | M49: =vlookup($H$41,'Boost Data'!$J$1:$O$52,M35,0) -> 12 | N49: =vlookup($H$41,'Boost Data'!$J$1:$O$52,N35,0) -> 12 | O49: =vlookup($H$41,'Boost Data'!$J$1:$O$52,O35,0) -> 12 | P49: =VLOOKUP(H41,'Boost Data'!$J$1:$P$52,7,0) -> 46750
K50: =hlookup(K51,$K48:$O49,2,0) -> 12 | L50: =hlookup(L51,$K$48:$O$49,2,0) -> 12 | M50: =hlookup(M51,$K48:$O49,2,0) -> 12 | N50: =hlookup(N51,$K48:$O49,2,0) -> 12 | O50: =hlookup(O51,$K48:$O49,2,0) -> 12 | P50: =hlookup(P51,$K48:$O49,2,0) -> 12 | Q50: =hlookup(Q51,$K48:$O49,2,0) -> 12 | R50: =hlookup(R51,$K48:$O49,2,0) -> 12
K51: =K18 -> CB | L51: =L18 -> S | M51: =M18 -> LB/MLB | N51: =N18 -> LB/MLB | O51: =O18 -> LB/MLB | P51: =P18 -> LB/MLB | Q51: =Q18 -> S | R51: =R18 -> CB
K52: =K19+(K19*(K50/100))+K53+K54 -> 119.19266 | L52: =L19+(L19*(L50/100))+L53+L54 -> 141.66055 | M52: =M19+(M19*(M50/100))+M53+M54 -> 105.83486 | N52: =N19+(N19*(N50/100))+N53+N54 -> 119.19266 | O52: =O19+(O19*(O50/100))+O53+O54 -> 105.83486 | P52: =P19+(P19*(P50/100))+P53+P54 -> 105.83486 | Q52: =Q19+(Q19*(Q50/100))+Q53+Q54 -> 119.19266 | R52: =R19+(R19*(R50/100))+R53+R54 -> 119.19266
K53: =if(isblank(B20),0,$P$61) -> 0 | L53: =if(isblank(C20),0,$P$61) -> 5 | M53: =if(isblank(D20),0,$P$61) -> 0 | N53: =if(isblank(E20),0,$P$61) -> 0 | O53: =if(isblank(F20),0,$P$61) -> 0 | P53: =if(isblank(G20),0,$P$61) -> 0 | Q53: =if(isblank(H20),0,$P$61) -> 0 | R53: =if(isblank(I20),0,$P$61) -> 0
K54: =K21 -> 0 | L54: =L21 -> 0 | M54: =M21 -> 0 | N54: =N21 -> 0 | O54: =O21 -> 0 | P54: =P21 -> 0 | Q54: =Q21 -> 0 | R54: =R21 -> 0
L55: =hlookup(L56,$K$48:$O$49,2,0) -> 12 | M55: =hlookup(M56,$K$48:$O$49,2,0) -> 12 | N55: =hlookup(N56,$K$48:$O$49,2,0) -> 12 | O55: =hlookup(O56,$K$48:$O$49,2,0) -> 12 | P55: =hlookup(P56,$K$48:$O$49,2,0) -> 12 | Q55: =hlookup(Q56,$K$48:$O$49,2,0) -> 12
L56: =L23 -> CB | M56: =M23 -> DE | N56: =N23 -> DT | O56: =O23 -> DT | P56: =P23 -> DE | Q56: =Q23 -> CB
L57: =L24+(L24*(L55/100))+L58+L59 -> 104.80734 | M57: =M24+(M24*(M55/100))+M58+M59 -> 118.16514 | N57: =N24+(N24*(N55/100))+N58+N59 -> 139.6055 | O57: =O24+(O24*(O55/100))+O58+O59 -> 118.16514 | P57: =P24+(P24*(P55/100))+P58+P59 -> 104.80734 | Q57: =Q24+(Q24*(Q55/100))+Q58+Q59 -> 104.80734
L58: =if(isblank(C25),0,$P$61) -> 0 | M58: =if(isblank(D25),0,$P$61) -> 0 | N58: =if(isblank(E25),0,$P$61) -> 5 | O58: =if(isblank(F25),0,$P$61) -> 0 | P58: =if(isblank(G25),0,$P$61) -> 0 | Q58: =if(isblank(H25),0,$P$61) -> 0
L59: =L26 -> 0 | M59: =M26 -> 0 | N59: =N26 -> 0 | O59: =O26 -> 0 | P59: =P26 -> 0 | Q59: =Q26 -> 0
K60: K | L60: KR | M60: P | N60: PR | O60: COST | P60: Mythic Boosts | Q60: Dual Mythic | R60: Dual Iconic
K61: =vlookup($H$45,'Boost Data'!$S$1:$W$52,K35,0) -> 13 | L61: =vlookup($H$45,'Boost Data'!$S$1:$W$52,L35,0) -> 13 | M61: =vlookup($H$45,'Boost Data'!$S$1:$W$52,M35,0) -> 13 | N61: =vlookup($H$45,'Boost Data'!$S$1:$W$52,N35,0) -> 13 | O61: =VLOOKUP(H45,'Boost Data'!$S$1:$X$52,6,0) -> 15820 | P61: =Countif($B$3:$I$33, "Mythic +1") -> 5 | Q61: =Countif($B$3:$I$33, "Dual +2")*2 -> 0 | R61: =Countif($B$3:$I$33, "Dual +1") -> 0
M62: =hlookup(M63,$K$60:$N$61,2,0) -> 13 | N62: =hlookup(N63,$K$60:$N$61,2,0) -> 13 | O62: =hlookup(O63,$K$60:$N$61,2,0) -> 13 | P62: =hlookup(P63,$K$60:$N$61,2,0) -> 13
M63: =M30 -> K | N63: =N30 -> KR | O63: =O30 -> P | P63: =P30 -> PR
M64: =M31+(M31*(M62/100))+M65+M66 -> 102.4 | N64: =N31+(N31*(N62/100))+N65+N66 -> 136 | O64: =O31+(O31*(O62/100))+O65+O66 -> 102.2 | P64: =P31+(P31*(P62/100))+P65+P66 -> 101.7
M65: =if(isblank(D32),0,$P$61) -> 0 | N65: =if(isblank(E32),0,$P$61) -> 5 | O65: =if(isblank(F32),0,$P$61) -> 0 | P65: =if(isblank(G32),0,$P$61) -> 0
M66: =M33 -> 0 | N66: =N33 -> 0 | O66: =O33 -> 0 | P66: =P33 -> 0

Sheet Projection 1
B1: BOOSTIMATOR 26 | E1: FINAL OVR: | F1: =sum(K40:Q40,L45:P45,K52:R52,L57:Q57,M64:P64,R33) -> 3608.2492 | G1: TTP NEEDED: | H1: =sum(O61,P49,P37)-sum(O28,P16,P4) -> 26130 | I1: by phredd & jawabomb
B2: MY GOAL | E2: TARGET OVR: | F2: 3600 | I2: 2
B3: MY CURRENT LINEUP | E3: CURRENT OVR: | F3: =SUM(B7:H7,C12:G12,B19:I19,C24:H24,D31:G31) -> 3576.6 | K3: QB | L3: HB/FB | M3: TE | N3: WR | O3: C/OG/OT | P3: COST
B4: OFFENSE | C4: RANK: | D4: 38 | K4: =vlookup($D$4,'Boost Data'!$A$1:$F$52,2,0) -> 15 | L4: =vlookup($D$4,'Boost Data'!$A$1:$F$52,3,0) -> 15 | M4: =vlookup($D$4,'Boost Data'!$A$1:$F$52,4,0) -> 16 | N4: =vlookup($D$4,'Boost Data'!$A$1:$F$52,5,0) -> 16 | O4: =vlookup($D$4,'Boost Data'!$A$1:$F$52,6,0) -> 16 | P4: =VLOOKUP(D4,'Boost Data'!$A$1:$G$52,7,0) -> 96660
K5: =hlookup(K6,$K3:$O4,2,0)/100 -> 0.16 | L5: =hlookup(L6,$K3:$O4,2,0)/100 -> 0.16 | M5: =hlookup(M6,$K3:$O4,2,0)/100 -> 0.16 | N5: =hlookup(N6,$K3:$O4,2,0)/100 -> 0.16 | O5: =hlookup(O6,$K3:$O4,2,0)/100 -> 0.16 | P5: =hlookup(P6,$K3:$O4,2,0)/100 -> 0.16 | Q5: =hlookup(Q6,$K3:$O4,2,0)/100 -> 0.16
B6: WR1 | C6: LEFT OT | D6: LEFT OG | E6: C | F6: RIGHT OG | G6: RIGHT OT | H6: WR2 | K6: WR | L6: C/OG/OT | M6: C/OG/OT | N6: C/OG/OT | O6: C/OG/OT | P6: C/OG/OT | Q6: WR
B7: 141 | C7: 120 | D7: 106 | E7: 106 | F7: 140 | G7: 140 | H7: 121 | K7: =(B7-K8-K9)/(1+K5) -> 115.51724 | L7: =(C7-L8-L9)/(1+L5) -> 103.44828 | M7: =(D7-M8-M9)/(1+M5) -> 91.37931 | N7: =(E7-N8-N9)/(1+N5) -> 91.37931 | O7: =(F7-O8-O9)/(1+O5) -> 114.65517 | P7: =(G7-P8-P9)/(1+P5) -> 114.65517 | Q7: =(H7-Q8-Q9)/(1+Q5) -> 104.31034
B8: Mythic +1 | F8: Mythic +1 | G8: Mythic +1 | K8: =if(ISBLANK(B8)=FALSE,$P$28,0) -> 7 | L8: =if(ISBLANK(C8)=FALSE,$P$28,0) -> 0 | M8: =if(ISBLANK(D8)=FALSE,$P$28,0) -> 0 | N8: =if(ISBLANK(E8)=FALSE,$P$28,0) -> 0 | O8: =if(ISBLANK(F8)=FALSE,$P$28,0) -> 7 | P8: =if(ISBLANK(G8)=FALSE,$P$28,0) -> 7 | Q8: =if(ISBLANK(H8)=FALSE,$P$28,0) -> 0
K9: =if(B9="2 from Dual",2,0)+if(B9="1 from Dual",1,0) -> 0 | L9: =if(C9="2 from Dual",2,0)+if(C9="1 from Dual",1,0) -> 0 | M9: =if(D9="2 from Dual",2,0)+if(D9="1 from Dual",1,0) -> 0 | N9: =if(E9="2 from Dual",2,0)+if(E9="1 from Dual",1,0) -> 0 | O9: =if(F9="2 from Dual",2,0)+if(F9="1 from Dual",1,0) -> 0 | P9: =if(G9="2 from Dual",2,0)+if(G9="1 from Dual",1,0) -> 0 | Q9: =if(H9="2 from Dual",2,0)+if(H9="1 from Dual",1,0) -> 0
L10: =hlookup(L11,$K$3:$O$4,2,0)/100 -> 0.16 | M10: =hlookup(M11,$K$3:$O$4,2,0)/100 -> 0.15 | N10: =hlookup(N11,$K$3:$O$4,2,0)/100 -> 0.15 | O10: =hlookup(O11,$K$3:$O$4,2,0)/100 -> 0.15 | P10: =hlookup(P11,$K$3:$O$4,2,0)/100 -> 0.16
C11: WR | D11: HB | E11: QB | F11: HB/FB | G11: TE | L11: =C11 -> WR | M11: HB/FB | N11: QB | O11: HB/FB | P11: TE
C12: 120 | D12: 119 | E12: 118 | F12: 119 | G12: 140 | L12: =(C12-L13-L14)/(1+L10) -> 103.44828 | M12: =(D12-M13-M14)/(1+M10) -> 103.47826 | N12: =(E12-N13-N14)/(1+N10) -> 102.6087 | O12: =(F12-O13-O14)/(1+O10) -> 103.47826 | P12: =(G12-P13-P14)/(1+P10) -> 114.65517
G13: Mythic +1 | L13: =if(ISBLANK(C13)=FALSE,$P$28,0) -> 0 | M13: =if(ISBLANK(D13)=FALSE,$P$28,0) -> 0 | N13: =if(ISBLANK(E13)=FALSE,$P$28,0) -> 0 | O13: =if(ISBLANK(F13)=FALSE,$P$28,0) -> 0 | P13: =if(ISBLANK(G13)=FALSE,$P$28,0) -> 7
L14: =if(C14="2 from Dual",2,0)+if(C14="1 from Dual",1,0) -> 0 | M14: =if(D14="2 from Dual",2,0)+if(D14="1 from Dual",1,0) -> 0 | N14: =if(E14="2 from Dual",2,0)+if(E14="1 from Dual",1,0) -> 0 | O14: =if(F14="2 from Dual",2,0)+if(F14="1 from Dual",1,0) -> 0 | P14: =if(G14="2 from Dual",2,0)+if(G14="1 from Dual",1,0) -> 0
K15: LB/MLB | L15: CB | M15: S | N15: DT | O15: DE | P15: COST
B16: DEFENSE | C16: RANK: | D16: 30 | K16: =vlookup($D$16,'Boost Data'!$J$1:$O$52,2,0) -> 12 | L16: =vlookup($D$16,'Boost Data'!$J$1:$O$52,2,0) -> 12 | M16: =vlookup($D$16,'Boost Data'!$J$1:$O$52,2,0) -> 12 | N16: =vlookup($D$16,'Boost Data'!$J$1:$O$52,2,0) -> 12 | O16: =vlookup($D$16,'Boost Data'!$J$1:$O$52,2,0) -> 12 | P16: =VLOOKUP(D16,'Boost Data'!$J$1:$P$52,7,0) -> 46750
K17: =hlookup(K18,$K$15:$O$16,2,0)/100 -> 0.12 | L17: =hlookup(L18,$K$15:$O$16,2,0)/100 -> 0.12 | M17: =hlookup(M18,$K$15:$O$16,2,0)/100 -> 0.12 | N17: =hlookup(N18,$K$15:$O$16,2,0)/100 -> 0.12 | O17: =hlookup(O18,$K$15:$O$16,2,0)/100 -> 0.12 | P17: =hlookup(P18,$K$15:$O$16,2,0)/100 -> 0.12 | Q17: =hlookup(Q18,$K$15:$O$16,2,0)/100 -> 0.12 | R17: =hlookup(R18,$K$15:$O$16,2,0)/100 -> 0.12
B18: CB1 | C18: SS | D18: LEFT LB | E18: MLB | F18: MLB | G18: RIGHT LB | H18: FS | I18: CB2 | K18: CB | L18: S | M18: LB/MLB | N18: LB/MLB | O18: LB/MLB | P18: LB/MLB | Q18: S | R18: CB
B19: 116 | C19: 138 | D19: 123 | E19: 116 | F19: 123 | G19: 103 | H19: 116 | I19: 116 | K19: =(B19-K20-K21)/(1+K17) -> 103.57143 | L19: =(C19-L20-L21)/(1+L17) -> 116.96429 | M19: =(D19-M20-M21)/(1+M17) -> 109.82143 | N19: =(E19-N20-N21)/(1+N17) -> 103.57143 | O19: =(F19-O20-O21)/(1+O17) -> 109.82143 | P19: =(G19-P20-P21)/(1+P17) -> 91.964286 | Q19: =(H19-Q20-Q21)/(1+Q17) -> 103.57143 | R19: =(I19-R20-R21)/(1+R17) -> 103.57143
C20: Mythic +1 | K20: =if(ISBLANK(B20)=FALSE,$P$28,0) -> 0 | L20: =if(ISBLANK(C20)=FALSE,$P$28,0) -> 7 | M20: =if(ISBLANK(D20)=FALSE,$P$28,0) -> 0 | N20: =if(ISBLANK(E20)=FALSE,$P$28,0) -> 0 | O20: =if(ISBLANK(F20)=FALSE,$P$28,0) -> 0 | P20: =if(ISBLANK(G20)=FALSE,$P$28,0) -> 0 | Q20: =if(ISBLANK(H20)=FALSE,$P$28,0) -> 0 | R20: =if(ISBLANK(I20)=FALSE,$P$28,0) -> 0
K21: =if(B21="2 from Dual",2,0)+if(B21="1 from Dual",1,0) -> 0 | L21: =if(C21="2 from Dual",2,0)+if(C21="1 from Dual",1,0) -> 0 | M21: =if(D21="2 from Dual",2,0)+if(D21="1 from Dual",1,0) -> 0 | N21: =if(E21="2 from Dual",2,0)+if(E21="1 from Dual",1,0) -> 0 | O21: =if(F21="2 from Dual",2,0)+if(F21="1 from Dual",1,0) -> 0 | P21: =if(G21="2 from Dual",2,0)+if(G21="1 from Dual",1,0) -> 0 | Q21: =if(H21="2 from Dual",2,0)+if(H21="1 from Dual",1,0) -> 0 | R21: =if(I21="2 from Dual",2,0)+if(I21="1 from Dual",1,0) -> 0
L22: =hlookup(L23,$K$15:$O$16,2,0)/100 -> 0.12 | M22: =hlookup(M23,$K$15:$O$16,2,0)/100 -> 0.12 | N22: =hlookup(N23,$K$15:$O$16,2,0)/100 -> 0.12 | O22: =hlookup(O23,$K$15:$O$16,2,0)/100 -> 0.12 | P22: =hlookup(P23,$K$15:$O$16,2,0)/100 -> 0.12 | Q22: =hlookup(Q23,$K$15:$O$16,2,0)/100 -> 0.12
C23: CB | D23: DE | E23: DT | F23: DT | G23: DE | H23: CB | L23: =C23 -> CB | M23: =D23 -> DE | N23: =E23 -> DT | O23: =F23 -> DT | P23: =G23 -> DE | Q23: =H23 -> CB
C24: 123 | D24: 115 | E24: 136 | F24: 115 | G24: 102 | H24: 102 | L24: =(C24-L25-L26)/(1+L22) -> 109.82143 | M24: =(D24-M25-M26)/(1+M22) -> 102.67857 | N24: =(E24-N25-N26)/(1+N22) -> 115.17857 | O24: =(F24-O25-O26)/(1+O22) -> 102.67857 | P24: =(G24-P25-P26)/(1+P22) -> 91.071429 | Q24: =(H24-Q25-Q26)/(1+Q22) -> 91.071429
E25: Mythic +1 | L25: =if(ISBLANK(C25)=FALSE,$P$28,0) -> 0 | M25: =if(ISBLANK(D25)=FALSE,$P$28,0) -> 0 | N25: =if(ISBLANK(E25)=FALSE,$P$28,0) -> 7 | O25: =if(ISBLANK(F25)=FALSE,$P$28,0) -> 0 | P25: =if(ISBLANK(G25)=FALSE,$P$28,0) -> 0 | Q25: =if(ISBLANK(H25)=FALSE,$P$28,0) -> 0
L26: =if(C26="2 from Dual",2,0)+if(C26="1 from Dual",1,0) -> 0 | M26: =if(D26="2 from Dual",2,0)+if(D26="1 from Dual",1,0) -> 0 | N26: =if(E26="2 from Dual",2,0)+if(E26="1 from Dual",1,0) -> 0 | O26: =if(F26="2 from Dual",2,0)+if(F26="1 from Dual",1,0) -> 0 | P26: =if(G26="2 from Dual",2,0)+if(G26="1 from Dual",1,0) -> 0 | Q26: =if(H26="2 from Dual",2,0)+if(H26="1 from Dual",1,0) -> 0
K27: K | L27: KR | M27: P | N27: PR | O27: COST | P27: Mythic Boosts | Q27: Dual Mythic | R27: Dual Iconic
B28: SPECIAL | C28: RANK: | D28: 30 | K28: =vlookup($D$28,'Boost Data'!$S$1:$W$52,2,0) -> 12 | L28: =vlookup($D$28,'Boost Data'!$S$1:$W$52,2,0) -> 12 | M28: =vlookup($D$28,'Boost Data'!$S$1:$W$52,2,0) -> 12 | N28: =vlookup($D$28,'Boost Data'!$S$1:$W$52,2,0) -> 12 | O28: =VLOOKUP(D28,'Boost Data'!$S$1:$X$52,6,0) -> 14380 | P28: =Countif($B$3:$I$33, "Mythic +1") -> 7
M29: =hlookup(M30,$K$27:$N$28,2,0)/100 -> 0.12 | N29: =hlookup(N30,$K$27:$N$28,2,0)/100 -> 0.12 | O29: =hlookup(O30,$K$27:$N$28,2,0)/100 -> 0.12 | P29: =hlookup(P30,$K$27:$N$28,2,0)/100 -> 0.12
D30: K | E30: KR | F30: P | G30: PR | M30: =D30 -> K | N30: =E30 -> KR | O30: =F30 -> P | P30: =G30 -> PR
D31: 102.4 | E31: 136 | F31: 102.2 | G31: 102 | M31: =(D31-M32-M33)/(1+M29) -> 91.428571 | N31: =(E31-N32-N33)/(1+N29) -> 115.17857 | O31: =(F31-O32-O33)/(1+O29) -> 91.25 | P31: =(G31-P32-P33)/(1+P29) -> 91.071429
E32: Mythic +1 | M32: =if(ISBLANK(D32)=FALSE,$P$28,0) -> 0 | N32: =if(ISBLANK(E32)=FALSE,$P$28,0) -> 7 | O32: =if(ISBLANK(F32)=FALSE,$P$28,0) -> 0 | P32: =if(ISBLANK(G32)=FALSE,$P$28,0) -> 0 | R32: Extra
M33: =if(D33="2 from Dual",2,0)+if(D33="1 from Dual",1,0) -> 0 | N33: =if(E33="2 from Dual",2,0)+if(E33="1 from Dual",1,0) -> 0 | O33: =if(F33="2 from Dual",2,0)+if(F33="1 from Dual",1,0) -> 0 | P33: =if(G33="2 from Dual",2,0)+if(G33="1 from Dual",1,0) -> 0 | R33: =I2*P28 -> 14
B35: RANK UP | K35: 2 | L35: 3 | M35: 4 | N35: 5 | O35: 6
B36: OFFENSE | H36: TARGET RANK | K36: QB | L36: HB/FB | M36: TE | N36: WR | O36: C/OG/OT | P36: COST
B37: QB | C37: HB/FB | D37: TE | E37: WR | F37: C/OG/OT | H37: 40 | K37: =vlookup($H$37,'Boost Data'!$A$1:$F$52,K$35,0) -> 16 | L37: =vlookup($H$37,'Boost Data'!$A$1:$F$52,L35,0) -> 16 | M37: =vlookup($H$37,'Boost Data'!$A$1:$F$52,M35,0) -> 16 | N37: =vlookup($H$37,'Boost Data'!$A$1:$F$52,N35,0) -> 16 | O37: =vlookup($H$37,'Boost Data'!$A$1:$F$52,O35,0) -> 16 | P37: =VLOOKUP(H37,'Boost Data'!$A$1:$G$52,7,0) -> 117960
B38: =K4&"% ⏩ "&K37&"%" -> 15% ⏩ 16% | C38: =L4&"% ⏩ "&L37&"%" -> 15% ⏩ 16% | D38: =M4&"% ⏩ "&M37&"%" -> 16% ⏩ 16% | E38: =N4&"% ⏩ "&N37&"%" -> 16% ⏩ 16% | F38: =O4&"% ⏩ "&O37&"%" -> 16% ⏩ 16% | K38: =hlookup(K39,$K36:$O37,2,0) -> 16 | L38: =hlookup(L39,$K$36:$O$37,2,0) -> 16 | M38: =hlookup(M39,$K36:$O37,2,0) -> 16 | N38: =hlookup(N39,$K36:$O37,2,0) -> 16 | O38: =hlookup(O39,$K36:$O37,2,0) -> 16 | P38: =hlookup(P39,$K36:$O37,2,0) -> 16 | Q38: =hlookup(Q39,$K36:$O37,2,0) -> 16
K39: =K6 -> WR | L39: =L6 -> C/OG/OT | M39: =M6 -> C/OG/OT | N39: =N6 -> C/OG/OT | O39: =O6 -> C/OG/OT | P39: =P6 -> C/OG/OT | Q39: =Q6 -> WR
B40: DEFENSE | H40: TARGET RANK | K40: =K7+(K7*(K38/100))+K41+K42 -> 141 | L40: =L7+(L7*(L38/100))+L41+L42 -> 120 | M40: =M7+(M7*(M38/100))+M41+M42 -> 106 | N40: =N7+(N7*(N38/100))+N41+N42 -> 106 | O40: =O7+(O7*(O38/100))+O41+O42 -> 140 | P40: =P7+(P7*(P38/100))+P41+P42 -> 140 | Q40: =Q7+(Q7*(Q38/100))+Q41+Q42 -> 121
B41: LB/MLB | C41: CB | D41: S | E41: DT | F41: DE | H41: 31 | K41: =if(isblank(B8),0,$P$61) -> 7 | L41: =if(isblank(C8),0,$P$61) -> 0 | M41: =if(isblank(D8),0,$P$61) -> 0 | N41: =if(isblank(E8),0,$P$61) -> 0 | O41: =if(isblank(F8),0,$P$61) -> 7 | P41: =if(isblank(G8),0,$P$61) -> 7 | Q41: =if(isblank(H8),0,$P$61) -> 0
B42: =K16&"% ⏩ "&K49&"%" -> 12% ⏩ 13% | C42: =L16&"% ⏩ "&L49&"%" -> 12% ⏩ 13% | D42: =M16&"% ⏩ "&M49&"%" -> 12% ⏩ 13% | E42: =N16&"% ⏩ "&N49&"%" -> 12% ⏩ 13% | F42: =O16&"% ⏩ "&O49&"%" -> 12% ⏩ 13% | K42: =K9 -> 0 | L42: =L9 -> 0 | M42: =M9 -> 0 | N42: =N9 -> 0 | O42: =O9 -> 0 | P42: =P9 -> 0 | Q42: =Q9 -> 0
L43: =hlookup(L44,$K$36:$O$37,2,0) -> 16 | M43: =hlookup(M44,$K$36:$O$37,2,0) -> 16 | N43: =hlookup(N44,$K$36:$O$37,2,0) -> 16 | O43: =hlookup(O44,$K$36:$O$37,2,0) -> 16 | P43: =hlookup(P44,$K$36:$O$37,2,0) -> 16
B44: SPECIAL | H44: TARGET RANK | L44: =L11 -> WR | M44: =M11 -> HB/FB | N44: =N11 -> QB | O44: =O11 -> HB/FB | P44: =P11 -> TE
B45: K | C45: KR | D45: P | E45: PR | H45: 30 | L45: =L12+(L12*(L43/100))+L46+L47 -> 120 | M45: =M12+(M12*(M43/100))+M46+M47 -> 120.03478 | N45: =N12+(N12*(N43/100))+N46+N47 -> 119.02609 | O45: =O12+(O12*(O43/100))+O46+O47 -> 120.03478 | P45: =P12+(P12*(P43/100))+P46+P47 -> 140
B46: =K28&"% ⏩ "&K61&"%" -> 12% ⏩ 12% | C46: =L28&"% ⏩ "&L61&"%" -> 12% ⏩ 12% | D46: =M28&"% ⏩ "&M61&"%" -> 12% ⏩ 12% | E46: =N28&"% ⏩ "&N61&"%" -> 12% ⏩ 12% | L46: =if(isblank(C13),0,$P$61) -> 0 | M46: =if(isblank(D13),0,$P$61) -> 0 | N46: =if(isblank(E13),0,$P$61) -> 0 | O46: =if(isblank(F13),0,$P$61) -> 0 | P46: =if(isblank(G13),0,$P$61) -> 7
L47: =L14 -> 0 | M47: =M14 -> 0 | N47: =N14 -> 0 | O47: =O14 -> 0 | P47: =P14 -> 0
K48: LB/MLB | L48: CB | M48: S | N48: DT | O48: DE | P48: COST
K49: =vlookup($H$41,'Boost Data'!$J$1:$O$52,K35,0) -> 13 | L49: =vlookup($H$41,'Boost Data'!$J$1:$O$52,L35,0) -> 13 | M49: =vlookup($H$41,'Boost Data'!$J$1:$O$52,M35,0) -> 13 | N49: =vlookup($H$41,'Boost Data'!$J$1:$O$52,N35,0) -> 13 | O49: =vlookup($H$41,'Boost Data'!$J$1:$O$52,O35,0) -> 13 | P49: =VLOOKUP(H41,'Boost Data'!$J$1:$P$52,7,0) -> 51580
K50: =hlookup(K51,$K48:$O49,2,0) -> 13 | L50: =hlookup(L51,$K$48:$O$49,2,0) -> 13 | M50: =hlookup(M51,$K48:$O49,2,0) -> 13 | N50: =hlookup(N51,$K48:$O49,2,0) -> 13 | O50: =hlookup(O51,$K48:$O49,2,0) -> 13 | P50: =hlookup(P51,$K48:$O49,2,0) -> 13 | Q50: =hlookup(Q51,$K48:$O49,2,0) -> 13 | R50: =hlookup(R51,$K48:$O49,2,0) -> 13
K51: =K18 -> CB | L51: =L18 -> S | M51: =M18 -> LB/MLB | N51: =N18 -> LB/MLB | O51: =O18 -> LB/MLB | P51: =P18 -> LB/MLB | Q51: =Q18 -> S | R51: =R18 -> CB
K52: =K19+(K19*(K50/100))+K53+K54 -> 117.03571 | L52: =L19+(L19*(L50/100))+L53+L54 -> 139.16964 | M52: =M19+(M19*(M50/100))+M53+M54 -> 124.09821 | N52: =N19+(N19*(N50/100))+N53+N54 -> 117.03571 | O52: =O19+(O19*(O50/100))+O53+O54 -> 124.09821 | P52: =P19+(P19*(P50/100))+P53+P54 -> 103.91964 | Q52: =Q19+(Q19*(Q50/100))+Q53+Q54 -> 117.03571 | R52: =R19+(R19*(R50/100))+R53+R54 -> 117.03571
K53: =if(isblank(B20),0,$P$61) -> 0 | L53: =if(isblank(C20),0,$P$61) -> 7 | M53: =if(isblank(D20),0,$P$61) -> 0 | N53: =if(isblank(E20),0,$P$61) -> 0 | O53: =if(isblank(F20),0,$P$61) -> 0 | P53: =if(isblank(G20),0,$P$61) -> 0 | Q53: =if(isblank(H20),0,$P$61) -> 0 | R53: =if(isblank(I20),0,$P$61) -> 0
K54: =K21 -> 0 | L54: =L21 -> 0 | M54: =M21 -> 0 | N54: =N21 -> 0 | O54: =O21 -> 0 | P54: =P21 -> 0 | Q54: =Q21 -> 0 | R54: =R21 -> 0
L55: =hlookup(L56,$K$48:$O$49,2,0) -> 13 | M55: =hlookup(M56,$K$48:$O$49,2,0) -> 13 | N55: =hlookup(N56,$K$48:$O$49,2,0) -> 13 | O55: =hlookup(O56,$K$48:$O$49,2,0) -> 13 | P55: =hlookup(P56,$K$48:$O$49,2,0) -> 13 | Q55: =hlookup(Q56,$K$48:$O$49,2,0) -> 13
L56: =L23 -> CB | M56: =M23 -> DE | N56: =N23 -> DT | O56: =O23 -> DT | P56: =P23 -> DE | Q56: =Q23 -> CB
L57: =L24+(L24*(L55/100))+L58+L59 -> 124.09821 | M57: =M24+(M24*(M55/100))+M58+M59 -> 116.02679 | N57: =N24+(N24*(N55/100))+N58+N59 -> 137.15179 | O57: =O24+(O24*(O55/100))+O58+O59 -> 116.02679 | P57: =P24+(P24*(P55/100))+P58+P59 -> 102.91071 | Q57: =Q24+(Q24*(Q55/100))+Q58+Q59 -> 102.91071
L58: =if(isblank(C25),0,$P$61) -> 0 | M58: =if(isblank(D25),0,$P$61) -> 0 | N58: =if(isblank(E25),0,$P$61) -> 7 | O58: =if(isblank(F25),0,$P$61) -> 0 | P58: =if(isblank(G25),0,$P$61) -> 0 | Q58: =if(isblank(H25),0,$P$61) -> 0
L59: =L26 -> 0 | M59: =M26 -> 0 | N59: =N26 -> 0 | O59: =O26 -> 0 | P59: =P26 -> 0 | Q59: =Q26 -> 0
K60: K | L60: KR | M60: P | N60: PR | O60: COST | P60: Mythic Boosts | Q60: Dual Mythic | R60: Dual Iconic
K61: =vlookup($H$45,'Boost Data'!$S$1:$W$52,K35,0) -> 12 | L61: =vlookup($H$45,'Boost Data'!$S$1:$W$52,L35,0) -> 12 | M61: =vlookup($H$45,'Boost Data'!$S$1:$W$52,M35,0) -> 12 | N61: =vlookup($H$45,'Boost Data'!$S$1:$W$52,N35,0) -> 12 | O61: =VLOOKUP(H45,'Boost Data'!$S$1:$X$52,6,0) -> 14380 | P61: =Countif($B$3:$I$33, "Mythic +1") -> 7 | Q61: =Countif($B$3:$I$33, "Dual +2")*2 -> 0 | R61: =Countif($B$3:$I$33, "Dual +1") -> 0
M62: =hlookup(M63,$K$60:$N$61,2,0) -> 12 | N62: =hlookup(N63,$K$60:$N$61,2,0) -> 12 | O62: =hlookup(O63,$K$60:$N$61,2,0) -> 12 | P62: =hlookup(P63,$K$60:$N$61,2,0) -> 12
M63: =M30 -> K | N63: =N30 -> KR | O63: =O30 -> P | P63: =P30 -> PR
M64: =M31+(M31*(M62/100))+M65+M66 -> 102.4 | N64: =N31+(N31*(N62/100))+N65+N66 -> 136 | O64: =O31+(O31*(O62/100))+O65+O66 -> 102.2 | P64: =P31+(P31*(P62/100))+P65+P66 -> 102
M65: =if(isblank(D32),0,$P$61) -> 0 | N65: =if(isblank(E32),0,$P$61) -> 7 | O65: =if(isblank(F32),0,$P$61) -> 0 | P65: =if(isblank(G32),0,$P$61) -> 0
M66: =M33 -> 0 | N66: =N33 -> 0 | O66: =O33 -> 0 | P66: =P33 -> 0

Sheet Projection 2
B1: BOOSTIMATOR 26 | E1: FINAL OVR: | F1: =sum(K40:Q40,L45:P45,K52:R52,L57:Q57,M64:P64,R33) -> 3623.6957 | G1: TTP NEEDED: | H1: =sum(O61,P49,P37)-sum(O28,P16,P4) -> 21300 | I1: by phredd & jawabomb
B2: MY GOAL | E2: TARGET OVR: | F2: 3600 | I2: 4
B3: MY CURRENT LINEUP | E3: CURRENT OVR: | F3: =SUM(B7:H7,C12:G12,B19:I19,C24:H24,D31:G31) -> 3584.6 | K3: QB | L3: HB/FB | M3: TE | N3: WR | O3: C/OG/OT | P3: COST
B4: OFFENSE | C4: RANK: | D4: 38 | K4: =vlookup($D$4,'Boost Data'!$A$1:$F$52,2,0) -> 15 | L4: =vlookup($D$4,'Boost Data'!$A$1:$F$52,3,0) -> 15 | M4: =vlookup($D$4,'Boost Data'!$A$1:$F$52,4,0) -> 16 | N4: =vlookup($D$4,'Boost Data'!$A$1:$F$52,5,0) -> 16 | O4: =vlookup($D$4,'Boost Data'!$A$1:$F$52,6,0) -> 16 | P4: =VLOOKUP(D4,'Boost Data'!$A$1:$G$52,7,0) -> 96660
K5: =hlookup(K6,$K3:$O4,2,0)/100 -> 0.16 | L5: =hlookup(L6,$K3:$O4,2,0)/100 -> 0.16 | M5: =hlookup(M6,$K3:$O4,2,0)/100 -> 0.16 | N5: =hlookup(N6,$K3:$O4,2,0)/100 -> 0.16 | O5: =hlookup(O6,$K3:$O4,2,0)/100 -> 0.16 | P5: =hlookup(P6,$K3:$O4,2,0)/100 -> 0.16 | Q5: =hlookup(Q6,$K3:$O4,2,0)/100 -> 0.16
B6: WR1 | C6: LEFT OT | D6: LEFT OG | E6: C | F6: RIGHT OG | G6: RIGHT OT | H6: WR2 | K6: WR | L6: C/OG/OT | M6: C/OG/OT | N6: C/OG/OT | O6: C/OG/OT | P6: C/OG/OT | Q6: WR
B7: 141 | C7: 120 | D7: 106 | E7: 106 | F7: 140 | G7: 140 | H7: 121 | K7: =(B7-K8-K9)/(1+K5) -> 113.7931 | L7: =(C7-L8-L9)/(1+L5) -> 103.44828 | M7: =(D7-M8-M9)/(1+M5) -> 91.37931 | N7: =(E7-N8-N9)/(1+N5) -> 91.37931 | O7: =(F7-O8-O9)/(1+O5) -> 112.93103 | P7: =(G7-P8-P9)/(1+P5) -> 112.93103 | Q7: =(H7-Q8-Q9)/(1+Q5) -> 104.31034
B8: Mythic +1 | F8: Mythic +1 | G8: Mythic +1 | K8: =if(ISBLANK(B8)=FALSE,$P$28,0) -> 9 | L8: =if(ISBLANK(C8)=FALSE,$P$28,0) -> 0 | M8: =if(ISBLANK(D8)=FALSE,$P$28,0) -> 0 | N8: =if(ISBLANK(E8)=FALSE,$P$28,0) -> 0 | O8: =if(ISBLANK(F8)=FALSE,$P$28,0) -> 9 | P8: =if(ISBLANK(G8)=FALSE,$P$28,0) -> 9 | Q8: =if(ISBLANK(H8)=FALSE,$P$28,0) -> 0
K9: =if(B9="2 from Dual",2,0)+if(B9="1 from Dual",1,0) -> 0 | L9: =if(C9="2 from Dual",2,0)+if(C9="1 from Dual",1,0) -> 0 | M9: =if(D9="2 from Dual",2,0)+if(D9="1 from Dual",1,0) -> 0 | N9: =if(E9="2 from Dual",2,0)+if(E9="1 from Dual",1,0) -> 0 | O9: =if(F9="2 from Dual",2,0)+if(F9="1 from Dual",1,0) -> 0 | P9: =if(G9="2 from Dual",2,0)+if(G9="1 from Dual",1,0) -> 0 | Q9: =if(H9="2 from Dual",2,0)+if(H9="1 from Dual",1,0) -> 0
L10: =hlookup(L11,$K$3:$O$4,2,0)/100 -> 0.16 | M10: =hlookup(M11,$K$3:$O$4,2,0)/100 -> 0.15 | N10: =hlookup(N11,$K$3:$O$4,2,0)/100 -> 0.15 | O10: =hlookup(O11,$K$3:$O$4,2,0)/100 -> 0.15 | P10: =hlookup(P11,$K$3:$O$4,2,0)/100 -> 0.16
C11: WR | D11: HB | E11: QB | F11: HB/FB | G11: TE | L11: =C11 -> WR | M11: HB/FB | N11: QB | O11: HB/FB | P11: TE
C12: 120 | D12: 119 | E12: 118 | F12: 119 | G12: 140 | L12: =(C12-L13-L14)/(1+L10) -> 103.44828 | M12: =(D12-M13-M14)/(1+M10) -> 103.47826 | N12: =(E12-N13-N14)/(1+N10) -> 102.6087 | O12: =(F12-O13-O14)/(1+O10) -> 103.47826 | P12: =(G12-P13-P14)/(1+P10) -> 112.93103
G13: Mythic +1 | L13: =if(ISBLANK(C13)=FALSE,$P$28,0) -> 0 | M13: =if(ISBLANK(D13)=FALSE,$P$28,0) -> 0 | N13: =if(ISBLANK(E13)=FALSE,$P$28,0) -> 0 | O13: =if(ISBLANK(F13)=FALSE,$P$28,0) -> 0 | P13: =if(ISBLANK(G13)=FALSE,$P$28,0) -> 9
L14: =if(C14="2 from Dual",2,0)+if(C14="1 from Dual",1,0) -> 0 | M14: =if(D14="2 from Dual",2,0)+if(D14="1 from Dual",1,0) -> 0 | N14: =if(E14="2 from Dual",2,0)+if(E14="1 from Dual",1,0) -> 0 | O14: =if(F14="2 from Dual",2,0)+if(F14="1 from Dual",1,0) -> 0 | P14: =if(G14="2 from Dual",2,0)+if(G14="1 from Dual",1,0) -> 0
K15: LB/MLB | L15: CB | M15: S | N15: DT | O15: DE | P15: COST
B16: DEFENSE | C16: RANK: | D16: 30 | K16: =vlookup($D$16,'Boost Data'!$J$1:$O$52,2,0) -> 12 | L16: =vlookup($D$16,'Boost Data'!$J$1:$O$52,2,0) -> 12 | M16: =vlookup($D$16,'Boost Data'!$J$1:$O$52,2,0) -> 12 | N16: =vlookup($D$16,'Boost Data'!$J$1:$O$52,2,0) -> 12 | O16: =vlookup($D$16,'Boost Data'!$J$1:$O$52,2,0) -> 12 | P16: =VLOOKUP(D16,'Boost Data'!$J$1:$P$52,7,0) -> 46750
K17: =hlookup(K18,$K$15:$O$16,2,0)/100 -> 0.12 | L17: =hlookup(L18,$K$15:$O$16,2,0)/100 -> 0.12 | M17: =hlookup(M18,$K$15:$O$16,2,0)/100 -> 0.12 | N17: =hlookup(N18,$K$15:$O$16,2,0)/100 -> 0.12 | O17: =hlookup(O18,$K$15:$O$16,2,0)/100 -> 0.12 | P17: =hlookup(P18,$K$15:$O$16,2,0)/100 -> 0.12 | Q17: =hlookup(Q18,$K$15:$O$16,2,0)/100 -> 0.12 | R17: =hlookup(R18,$K$15:$O$16,2,0)/100 -> 0.12
B18: CB1 | C18: SS | D18: LEFT LB | E18: MLB | F18: MLB | G18: RIGHT LB | H18: FS | I18: CB2 | K18: CB | L18: S | M18: LB/MLB | N18: LB/MLB | O18: LB/MLB | P18: LB/MLB | Q18: S | R18: CB
B19: 116 | C19: 138 | D19: 103 | E19: 116 | F19: 103 | G19: 103 | H19: 116 | I19: 116 | K19: =(B19-K20-K21)/(1+K17) -> 103.57143 | L19: =(C19-L20-L21)/(1+L17) -> 115.17857 | M19: =(D19-M20-M21)/(1+M17) -> 91.964286 | N19: =(E19-N20-N21)/(1+N17) -> 103.57143 | O19: =(F19-O20-O21)/(1+O17) -> 91.964286 | P19: =(G19-P20-P21)/(1+P17) -> 91.964286 | Q19: =(H19-Q20-Q21)/(1+Q17) -> 103.57143 | R19: =(I19-R20-R21)/(1+R17) -> 103.57143
C20: Mythic +1 | K20: =if(ISBLANK(B20)=FALSE,$P$28,0) -> 0 | L20: =if(ISBLANK(C20)=FALSE,$P$28,0) -> 9 | M20: =if(ISBLANK(D20)=FALSE,$P$28,0) -> 0 | N20: =if(ISBLANK(E20)=FALSE,$P$28,0) -> 0 | O20: =if(ISBLANK(F20)=FALSE,$P$28,0) -> 0 | P20: =if(ISBLANK(G20)=FALSE,$P$28,0) -> 0 | Q20: =if(ISBLANK(H20)=FALSE,$P$28,0) -> 0 | R20: =if(ISBLANK(I20)=FALSE,$P$28,0) -> 0
K21: =if(B21="2 from Dual",2,0)+if(B21="1 from Dual",1,0) -> 0 | L21: =if(C21="2 from Dual",2,0)+if(C21="1 from Dual",1,0) -> 0 | M21: =if(D21="2 from Dual",2,0)+if(D21="1 from Dual",1,0) -> 0 | N21: =if(E21="2 from Dual",2,0)+if(E21="1 from Dual",1,0) -> 0 | O21: =if(F21="2 from Dual",2,0)+if(F21="1 from Dual",1,0) -> 0 | P21: =if(G21="2 from Dual",2,0)+if(G21="1 from Dual",1,0) -> 0 | Q21: =if(H21="2 from Dual",2,0)+if(H21="1 from Dual",1,0) -> 0 | R21: =if(I21="2 from Dual",2,0)+if(I21="1 from Dual",1,0) -> 0
L22: =hlookup(L23,$K$15:$O$16,2,0)/100 -> 0.12 | M22: =hlookup(M23,$K$15:$O$16,2,0)/100 -> 0.12 | N22: =hlookup(N23,$K$15:$O$16,2,0)/100 -> 0.12 | O22: =hlookup(O23,$K$15:$O$16,2,0)/100 -> 0.12 | P22: =hlookup(P23,$K$15:$O$16,2,0)/100 -> 0.12 | Q22: =hlookup(Q23,$K$15:$O$16,2,0)/100 -> 0.12
C23: CB | D23: DE | E23: DT | F23: DT | G23: DE | H23: CB | L23: =C23 -> CB | M23: =D23 -> DE | N23: =E23 -> DT | O23: =F23 -> DT | P23: =G23 -> DE | Q23: =H23 -> CB
C24: 137 | D24: 115 | E24: 136 | F24: 115 | G24: 102 | H24: 102 | L24: =(C24-L25-L26)/(1+L22) -> 114.28571 | M24: =(D24-M25-M26)/(1+M22) -> 102.67857 | N24: =(E24-N25-N26)/(1+N22) -> 113.39286 | O24: =(F24-O25-O26)/(1+O22) -> 102.67857 | P24: =(G24-P25-P26)/(1+P22) -> 91.071429 | Q24: =(H24-Q25-Q26)/(1+Q22) -> 91.071429
C25: Mythic +1 | E25: Mythic +1 | L25: =if(ISBLANK(C25)=FALSE,$P$28,0) -> 9 | M25: =if(ISBLANK(D25)=FALSE,$P$28,0) -> 0 | N25: =if(ISBLANK(E25)=FALSE,$P$28,0) -> 9 | O25: =if(ISBLANK(F25)=FALSE,$P$28,0) -> 0 | P25: =if(ISBLANK(G25)=FALSE,$P$28,0) -> 0 | Q25: =if(ISBLANK(H25)=FALSE,$P$28,0) -> 0
L26: =if(C26="2 from Dual",2,0)+if(C26="1 from Dual",1,0) -> 0 | M26: =if(D26="2 from Dual",2,0)+if(D26="1 from Dual",1,0) -> 0 | N26: =if(E26="2 from Dual",2,0)+if(E26="1 from Dual",1,0) -> 0 | O26: =if(F26="2 from Dual",2,0)+if(F26="1 from Dual",1,0) -> 0 | P26: =if(G26="2 from Dual",2,0)+if(G26="1 from Dual",1,0) -> 0 | Q26: =if(H26="2 from Dual",2,0)+if(H26="1 from Dual",1,0) -> 0
K27: K | L27: KR | M27: P | N27: PR | O27: COST | P27: Mythic Boosts | Q27: Dual Mythic | R27: Dual Iconic
B28: SPECIAL | C28: RANK: | D28: 30 | K28: =vlookup($D$28,'Boost Data'!$S$1:$W$52,2,0) -> 12 | L28: =vlookup($D$28,'Boost Data'!$S$1:$W$52,2,0) -> 12 | M28: =vlookup($D$28,'Boost Data'!$S$1:$W$52,2,0) -> 12 | N28: =vlookup($D$28,'Boost Data'!$S$1:$W$52,2,0) -> 12 | O28: =VLOOKUP(D28,'Boost Data'!$S$1:$X$52,6,0) -> 14380 | P28: =Countif($B$3:$I$33, "Mythic +1") -> 9
M29: =hlookup(M30,$K$27:$N$28,2,0)/100 -> 0.12 | N29: =hlookup(N30,$K$27:$N$28,2,0)/100 -> 0.12 | O29: =hlookup(O30,$K$27:$N$28,2,0)/100 -> 0.12 | P29: =hlookup(P30,$K$27:$N$28,2,0)/100 -> 0.12
D30: K | E30: KR | F30: P | G30: PR | M30: =D30 -> K | N30: =E30 -> KR | O30: =F30 -> P | P30: =G30 -> PR
D31: 102.4 | E31: 136 | F31: 102.2 | G31: 136 | M31: =(D31-M32-M33)/(1+M29) -> 91.428571 | N31: =(E31-N32-N33)/(1+N29) -> 113.39286 | O31: =(F31-O32-O33)/(1+O29) -> 91.25 | P31: =(G31-P32-P33)/(1+P29) -> 113.39286
E32: Mythic +1 | G32: Mythic +1 | M32: =if(ISBLANK(D32)=FALSE,$P$28,0) -> 0 | N32: =if(ISBLANK(E32)=FALSE,$P$28,0) -> 9 | O32: =if(ISBLANK(F32)=FALSE,$P$28,0) -> 0 | P32: =if(ISBLANK(G32)=FALSE,$P$28,0) -> 9 | R32: Extra
M33: =if(D33="2 from Dual",2,0)+if(D33="1 from Dual",1,0) -> 0 | N33: =if(E33="2 from Dual",2,0)+if(E33="1 from Dual",1,0) -> 0 | O33: =if(F33="2 from Dual",2,0)+if(F33="1 from Dual",1,0) -> 0 | P33: =if(G33="2 from Dual",2,0)+if(G33="1 from Dual",1,0) -> 0 | R33: =I2*P28 -> 36
B35: RANK UP | K35: 2 | L35: 3 | M35: 4 | N35: 5 | O35: 6
B36: OFFENSE | H36: TARGET RANK | K36: QB | L36: HB/FB | M36: TE | N36: WR | O36: C/OG/OT | P36: COST
B37: QB | C37: HB/FB | D37: TE | E37: WR | F37: C/OG/OT | H37: 40 | K37: =vlookup($H$37,'Boost Data'!$A$1:$F$52,K$35,0) -> 16 | L37: =vlookup($H$37,'Boost Data'!$A$1:$F$52,L35,0) -> 16 | M37: =vlookup($H$37,'Boost Data'!$A$1:$F$52,M35,0) -> 16 | N37: =vlookup($H$37,'Boost Data'!$A$1:$F$52,N35,0) -> 16 | O37: =vlookup($H$37,'Boost Data'!$A$1:$F$52,O35,0) -> 16 | P37: =VLOOKUP(H37,'Boost Data'!$A$1:$G$52,7,0) -> 117960
B38: =K4&"% ⏩ "&K37&"%" -> 15% ⏩ 16% | C38: =L4&"% ⏩ "&L37&"%" -> 15% ⏩ 16% | D38: =M4&"% ⏩ "&M37&"%" -> 16% ⏩ 16% | E38: =N4&"% ⏩ "&N37&"%" -> 16% ⏩ 16% | F38: =O4&"% ⏩ "&O37&"%" -> 16% ⏩ 16% | K38: =hlookup(K39,$K36:$O37,2,0) -> 16 | L38: =hlookup(L39,$K$36:$O$37,2,0) -> 16 | M38: =hlookup(M39,$K36:$O37,2,0) -> 16 | N38: =hlookup(N39,$K36:$O37,2,0) -> 16 | O38: =hlookup(O39,$K36:$O37,2,0) -> 16 | P38: =hlookup(P39,$K36:$O37,2,0) -> 16 | Q38: =hlookup(Q39,$K36:$O37,2,0) -> 16
K39: =K6 -> WR | L39: =L6 -> C/OG/OT | M39: =M6 -> C/OG/OT | N39: =N6 -> C/OG/OT | O39: =O6 -> C/OG/OT | P39: =P6 -> C/OG/OT | Q39: =Q6 -> WR
B40: DEFENSE | H40: TARGET RANK | K40: =K7+(K7*(K38/100))+K41+K42 -> 141 | L40: =L7+(L7*(L38/100))+L41+L42 -> 120 | M40: =M7+(M7*(M38/100))+M41+M42 -> 106 | N40: =N7+(N7*(N38/100))+N41+N42 -> 106 | O40: =O7+(O7*(O38/100))+O41+O42 -> 140 | P40: =P7+(P7*(P38/100))+P41+P42 -> 140 | Q40: =Q7+(Q7*(Q38/100))+Q41+Q42 -> 121
B41: LB/MLB | C41: CB | D41: S | E41: DT | F41: DE | H41: 30 | K41: =if(isblank(B8),0,$P$61) -> 9 | L41: =if(isblank(C8),0,$P$61) -> 0 | M41: =if(isblank(D8),0,$P$61) -> 0 | N41: =if(isblank(E8),0,$P$61) -> 0 | O41: =if(isblank(F8),0,$P$61) -> 9 | P41: =if(isblank(G8),0,$P$61) -> 9 | Q41: =if(isblank(H8),0,$P$61) -> 0
B42: =K16&"% ⏩ "&K49&"%" -> 12% ⏩ 12% | C42: =L16&"% ⏩ "&L49&"%" -> 12% ⏩ 12% | D42: =M16&"% ⏩ "&M49&"%" -> 12% ⏩ 12% | E42: =N16&"% ⏩ "&N49&"%" -> 12% ⏩ 12% | F42: =O16&"% ⏩ "&O49&"%" -> 12% ⏩ 12% | K42: =K9 -> 0 | L42: =L9 -> 0 | M42: =M9 -> 0 | N42: =N9 -> 0 | O42: =O9 -> 0 | P42: =P9 -> 0 | Q42: =Q9 -> 0
L43: =hlookup(L44,$K$36:$O$37,2,0) -> 16 | M43: =hlookup(M44,$K$36:$O$37,2,0) -> 16 | N43: =hlookup(N44,$K$36:$O$37,2,0) -> 16 | O43: =hlookup(O44,$K$36:$O$37,2,0) -> 16 | P43: =hlookup(P44,$K$36:$O$37,2,0) -> 16
B44: SPECIAL | H44: TARGET RANK | L44: =L11 -> WR | M44: =M11 -> HB/FB | N44: =N11 -> QB | O44: =O11 -> HB/FB | P44: =P11 -> TE
B45: K | C45: KR | D45: P | E45: PR | H45: 30 | L45: =L12+(L12*(L43/100))+L46+L47 -> 120 | M45: =M12+(M12*(M43/100))+M46+M47 -> 120.03478 | N45: =N12+(N12*(N43/100))+N46+N47 -> 119.02609 | O45: =O12+(O12*(O43/100))+O46+O47 -> 120.03478 | P45: =P12+(P12*(P43/100))+P46+P47 -> 140
B46: =K28&"% ⏩ "&K61&"%" -> 12% ⏩ 12% | C46: =L28&"% ⏩ "&L61&"%" -> 12% ⏩ 12% | D46: =M28&"% ⏩ "&M61&"%" -> 12% ⏩ 12% | E46: =N28&"% ⏩ "&N61&"%" -> 12% ⏩ 12% | L46: =if(isblank(C13),0,$P$61) -> 0 | M46: =if(isblank(D13),0,$P$61) -> 0 | N46: =if(isblank(E13),0,$P$61) -> 0 | O46: =if(isblank(F13),0,$P$61) -> 0 | P46: =if(isblank(G13),0,$P$61) -> 9
L47: =L14 -> 0 | M47: =M14 -> 0 | N47: =N14 -> 0 | O47: =O14 -> 0 | P47: =P14 -> 0
K48: LB/MLB | L48: CB | M48: S | N48: DT | O48: DE | P48: COST
K49: =vlookup($H$41,'Boost Data'!$J$1:$O$52,K35,0) -> 12 | L49: =vlookup($H$41,'Boost Data'!$J$1:$O$52,L35,0) -> 12 | M49: =vlookup($H$41,'Boost Data'!$J$1:$O$52,M35,0) -> 12 | N49: =vlookup($H$41,'Boost Data'!$J$1:$O$52,N35,0) -> 12 | O49: =vlookup($H$41,'Boost Data'!$J$1:$O$52,O35,0) -> 12 | P49: =VLOOKUP(H41,'Boost Data'!$J$1:$P$52,7,0) -> 46750
K50: =hlookup(K51,$K48:$O49,2,0) -> 12 | L50: =hlookup(L51,$K$48:$O$49,2,0) -> 12 | M50: =hlookup(M51,$K48:$O49,2,0) -> 12 | N50: =hlookup(N51,$K48:$O49,2,0) -> 12 | O50: =hlookup(O51,$K48:$O49,2,0) -> 12 | P50: =hlookup(P51,$K48:$O49,2,0) -> 12 | Q50: =hlookup(Q51,$K48:$O49,2,0) -> 12 | R50: =hlookup(R51,$K48:$O49,2,0) -> 12
K51: =K18 -> CB | L51: =L18 -> S | M51: =M18 -> LB/MLB | N51: =N18 -> LB/MLB | O51: =O18 -> LB/MLB | P51: =P18 -> LB/MLB | Q51: =Q18 -> S | R51: =R18 -> CB
K52: =K19+(K19*(K50/100))+K53+K54 -> 116 | L52: =L19+(L19*(L50/100))+L53+L54 -> 138 | M52: =M19+(M19*(M50/100))+M53+M54 -> 103 | N52: =N19+(N19*(N50/100))+N53+N54 -> 116 | O52: =O19+(O19*(O50/100))+O53+O54 -> 103 | P52: =P19+(P19*(P50/100))+P53+P54 -> 103 | Q52: =Q19+(Q19*(Q50/100))+Q53+Q54 -> 116 | R52: =R19+(R19*(R50/100))+R53+R54 -> 116
K53: =if(isblank(B20),0,$P$61) -> 0 | L53: =if(isblank(C20),0,$P$61) -> 9 | M53: =if(isblank(D20),0,$P$61) -> 0 | N53: =if(isblank(E20),0,$P$61) -> 0 | O53: =if(isblank(F20),0,$P$61) -> 0 | P53: =if(isblank(G20),0,$P$61) -> 0 | Q53: =if(isblank(H20),0,$P$61) -> 0 | R53: =if(isblank(I20),0,$P$61) -> 0
K54: =K21 -> 0 | L54: =L21 -> 0 | M54: =M21 -> 0 | N54: =N21 -> 0 | O54: =O21 -> 0 | P54: =P21 -> 0 | Q54: =Q21 -> 0 | R54: =R21 -> 0
L55: =hlookup(L56,$K$48:$O$49,2,0) -> 12 | M55: =hlookup(M56,$K$48:$O$49,2,0) -> 12 | N55: =hlookup(N56,$K$48:$O$49,2,0) -> 12 | O55: =hlookup(O56,$K$48:$O$49,2,0) -> 12 | P55: =hlookup(P56,$K$48:$O$49,2,0) -> 12 | Q55: =hlookup(Q56,$K$48:$O$49,2,0) -> 12
L56: =L23 -> CB | M56: =M23 -> DE | N56: =N23 -> DT | O56: =O23 -> DT | P56: =P23 -> DE | Q56: =Q23 -> CB
L57: =L24+(L24*(L55/100))+L58+L59 -> 137 | M57: =M24+(M24*(M55/100))+M58+M59 -> 115 | N57: =N24+(N24*(N55/100))+N58+N59 -> 136 | O57: =O24+(O24*(O55/100))+O58+O59 -> 115 | P57: =P24+(P24*(P55/100))+P58+P59 -> 102 | Q57: =Q24+(Q24*(Q55/100))+Q58+Q59 -> 102
L58: =if(isblank(C25),0,$P$61) -> 9 | M58: =if(isblank(D25),0,$P$61) -> 0 | N58: =if(isblank(E25),0,$P$61) -> 9 | O58: =if(isblank(F25),0,$P$61) -> 0 | P58: =if(isblank(G25),0,$P$61) -> 0 | Q58: =if(isblank(H25),0,$P$61) -> 0
L59: =L26 -> 0 | M59: =M26 -> 0 | N59: =N26 -> 0 | O59: =O26 -> 0 | P59: =P26 -> 0 | Q59: =Q26 -> 0
K60: K | L60: KR | M60: P | N60: PR | O60: COST | P60: Mythic Boosts | Q60: Dual Mythic | R60: Dual Iconic
K61: =vlookup($H$45,'Boost Data'!$S$1:$W$52,K35,0) -> 12 | L61: =vlookup($H$45,'Boost Data'!$S$1:$W$52,L35,0) -> 12 | M61: =vlookup($H$45,'Boost Data'!$S$1:$W$52,M35,0) -> 12 | N61: =vlookup($H$45,'Boost Data'!$S$1:$W$52,N35,0) -> 12 | O61: =VLOOKUP(H45,'Boost Data'!$S$1:$X$52,6,0) -> 14380 | P61: =Countif($B$3:$I$33, "Mythic +1") -> 9 | Q61: =Countif($B$3:$I$33, "Dual +2")*2 -> 0 | R61: =Countif($B$3:$I$33, "Dual +1") -> 0
M62: =hlookup(M63,$K$60:$N$61,2,0) -> 12 | N62: =hlookup(N63,$K$60:$N$61,2,0) -> 12 | O62: =hlookup(O63,$K$60:$N$61,2,0) -> 12 | P62: =hlookup(P63,$K$60:$N$61,2,0) -> 12
M63: =M30 -> K | N63: =N30 -> KR | O63: =O30 -> P | P63: =P30 -> PR
M64: =M31+(M31*(M62/100))+M65+M66 -> 102.4 | N64: =N31+(N31*(N62/100))+N65+N66 -> 136 | O64: =O31+(O31*(O62/100))+O65+O66 -> 102.2 | P64: =P31+(P31*(P62/100))+P65+P66 -> 136
M65: =if(isblank(D32),0,$P$61) -> 0 | N65: =if(isblank(E32),0,$P$61) -> 9 | O65: =if(isblank(F32),0,$P$61) -> 0 | P65: =if(isblank(G32),0,$P$61) -> 9
M66: =M33 -> 0 | N66: =N33 -> 0 | O66: =O33 -> 0 | P66: =P33 -> 0

Sheet TTP Tracker 26
B1: TTP TRACKER 26 | F1: TTP: | G1: =sum(K9:K125)*N2+G4 -> -1153174.9 | H1: GOAL: | I1: ='Boostimator 26'!H1 -> 130500 | K1: TTP | L1: USD | M1: MC | N1: Pass Bonus | P1: # Mondays:
B2: REMAINING | D2: VIP PASS: | E2: Yes | F2: Total MC: | G2: =SUM(M:M) -> -13350 | H2: Total $: | I2: =SUM(L:L) -> 29.99 | L2: =if(E2="Yes",29.99,0) -> 29.99 | N2: =if(E2="Yes",1.3,1) -> 1.3 | P2: =Schedule!F2 -> 0
B3: FP Starts: | C3: 45876 | D3: Total Days: | E3: =IF(B2="MONTHLY TOTAL",(C4-C3),C4-TODAY()) -> -267 | F3: Current Day: | G3: =(NOW()-(C3+E4)+1) -> 300.37152
B4: FP Ends: | C4: 45908 | D4: Reset Time: | E4: 0.39583333 | F4: Starting TTP:
B6: My Goals from Boostimator | D6: Offense: | E6: ='Boostimator 26'!H37 -> 40 | F6: Defense: | G6: ='Boostimator 26'!H41 -> 30 | H6: Special: | I6: ='Boostimator 26'!H45 -> 31
B8: Core and Promos
B9: Madden Base | C9: TTP | D9: Tier: | E9: Diamond | F9: Daily Refills: | G9: Yes | J9: TTP: | K9: =IF(C9="TTP",SUM(E11:E14)*$E$3,0) -> -540087.6 | M9: =if(G9="Yes",(E3*50),0) -> -13350
B10: Event | C10: Reward | D10: Times | E10: Daily
B11: 20 Stamina | C11: =IF($C$9="TTP",N11,P11)*N2 -> 50.7 | D11: 1 | E11: =PRODUCT(C11:D11) -> 50.7 | N11: =(32+O11) -> 39 | O11: =if($E$9="Diamond", 7,5) -> 7 | P11: =1620+Q11 -> 1980 | Q11: =if($E$9="Diamond", 360,270) -> 360
B12: 60 Stamina | C12: =IF($C$9="TTP",N12,P12)*N2 -> 171.6 | D12: 1 | E12: =PRODUCT(C12:D12) -> 171.6 | N12: =(108+O12) -> 132 | O12: =if($E$9="Diamond", 24,18) -> 24 | P12: =5460+Q12 -> 6660 | Q12: =if($E$9="Diamond", 1200,900) -> 1200
B13: 100 Stamina | C13: =IF($C$9="TTP",N13,P13)*N2 -> 314.6 | D13: 1 | E13: =PRODUCT(C13:D13) -> 314.6 | N13: =(198+O13) -> 242 | O13: =if($E$9="Diamond", 44,33) -> 44 | P13: =9900+Q13 -> 13360 | Q13: =if($E$9="Diamond", 3460,2600) -> 3460
B14: VIP | C14: =IF($C$9="TTP",N14,P14)*N2 -> 495.3 | D14: 3 | E14: =PRODUCT(C14:D14) -> 1485.9 | N14: =(311+O14) -> 381 | O14: =if($E$9="Diamond", 70,52) -> 70 | P14: =15500+Q14 -> 17700 | Q14: =if($E$9="Diamond", 2200,1650) -> 2200
B16: Event 1 Pass | C16: Bought: | D16: No | E16: =if(C16="Yes",1,0) -> 0 | J16: TTP: | K16: =sum(C18:C20)+(N16*sum(D18:E20)) -> 600 | L16: =if(D16="Yes",29.99,0) -> 0 | N16: =if(D16="Yes",1,0) -> 0
C17: FREE | D17: PLUS | E17: PREMIUM
B18: Milestone | C18: 400 | D18: 140 | E18: 900
C19: 200 | D19: 1000
B22: Event 2 Pass | C22: Bought: | D22: No | E22: =if(C22="Yes",1,0) -> 0 | J22: TTP: | K22: =sum(C24:C26)+(N22*sum(D24:E26)) -> 600 | L22: =if(D22="Yes",29.99,0) -> 0 | N22: =if(D22="Yes",1,0) -> 0
C23: FREE | D23: PLUS | E23: PREMIUM
B24: Milestone | C24: 400 | D24: 140 | E24: 900
C25: 200 | D25: 1000
B28: Competitive
B29: Daily Arena | E29: TTP | J29: TTP: | K29: =N30*E3 -> 0 | N29: Average
B30: High Rank | E30: =iferror(vlookup(C30,Leaderboards!E46:F100,2,0),0) -> 0 | N30: =AVERAGE(E30:E31) -> 0
B31: Low Rank | E31: =iferror(vlookup(C31,Leaderboards!E46:F100,2,0),0) -> 0
B33: Unlimited | C33: ➡️85 pts | D33: ➡️160 pts | E33: ➡️275 pts | F33: ➡️500 pts | G33: ➡️1000 pts | J33: TTP: | K33: =sum(C34:G37)*Schedule!M2 -> 0
B34: Arena 1 | C34: 1600 | D34: 500 | E34: 500
B35: Arena 2 | C35: 1600 | D35: 500 | E35: 500
B36: Arena 3 | C36: 1600 | D36: 500 | E36: 500
B37: Arena 4 | C37: 1600 | D37: 500 | E37: 500
B39: Tournaments | C39: Clear | D39: Rank | E39: Rank TTP | F39: Milestone TTP | J39: TTP: | K39: =(Schedule!K2*sum(N40:N43))+Schedule!L2*sum(E40:E43) -> 0 | N39: TTP
B40: Arena 1 | C40: TRUE | D40: 2000 | E40: =IFERROR(VLOOKUP(D40,Leaderboards!A34:C45,2,0),0)*C40 -> 780 | F40: =N40 -> 3920 | N40: =IF(C40,3920,0) -> 3920
B41: Arena 2 | C41: TRUE | D41: 2000 | E41: =IFERROR(VLOOKUP($D$41,Leaderboards!A48:C58,2,0),0)*C41 -> 1040 | F41: =N41 -> 3920 | N41: =IF(C41,3920,0) -> 3920
B42: Arena 3 | C42: TRUE | D42: 250 | E42: =IFERROR(VLOOKUP(D42,Leaderboards!A61:C71,2,0),0)*C42 -> 4000 | F42: =N42 -> 3920 | N42: =IF(C42,3920,0) -> 3920
B43: Arena 4 | C43: TRUE | D43: 100 | E43: =IFERROR(VLOOKUP(D43,Leaderboards!A74:C84,2,0),0)*C43 -> 6000 | F43: =N43 -> 3920 | N43: =IF(C43,3920,0) -> 3920
B45: PA Rushing | C45: Clear | D45: TTP | F45: PA Passing | G45: Clear | H45: TTP | J45: TTP: | K45: =sum(D46:D49)*Schedule!G2+sum(H46:H49)*Schedule!I2 -> 0
B46: 1500 | C46: TRUE | D46: =N46*C46 -> 3500 | F46: 1500 | G46: TRUE | H46: =N46*G46 -> 3500 | N46: 3500
B47: 750 | C47: TRUE | D47: =N47*C47 -> 2500 | F47: 750 | G47: TRUE | H47: =N47*G47 -> 2500 | N47: 2500
B48: 500 | C48: TRUE | D48: =N48*C48 -> 2000 | F48: 500 | G48: TRUE | H48: =N48*G48 -> 2000 | N48: 2000
B49: 350 | C49: TRUE | D49: =N49*C49 -> 1500 | F49: 350 | G49: TRUE | H49: =N49*G49 -> 1500 | N49: 1500
B51: Draft | C51: Rank | D51: TTP | H51: Milestone Rewards
B52: Tournament 1 | D52: =iferror(vlookup($C$52,Leaderboards!$J$19:$L$29,2,0),0) -> 0 | H52: 3750 | I52: TTP | J52: TTP: | K52: =sum(Leaderboards!$K$3:$K$17,D52)*N52 -> 0 | N52: =if(ISBLANK(C52)=False,1,0) -> 0
B53: Tournament 2 | D53: =iferror(vlookup($C$53,Leaderboards!$J$19:$L$29,2,0),0) -> 0 | J53: TTP: | K53: =sum(Leaderboards!$K$3:$K$17,D53)*N53 -> 0 | N53: =if(ISBLANK(C53)=False,1,0) -> 0
B55: LvL W/L | C55: Avg. Rank | D55: HOF | 3 | F55: Est. Wins: | G55: 5 | J55: TTP: | K55: =(G55*C56)+((E3-G55)*C57)+(C58*P2) -> -81170
B56: Avg. Win | C56: =VLOOKUP(D55,Leaderboards!E3:H42,3,0) -> 630
B57: Avg. Loss | C57: =VLOOKUP(D55,Leaderboards!E3:H42,4,0) -> 310
B58: Avg. Reward | C58: =VLOOKUP(D55,Leaderboards!E3:H42,2,0) -> 25200
B60: VS | C60: TTP
B61: Daily | C61: 0 | J61: TTP: | K61: =C61*(E3-3) -> 0
B63: League Store | F63: Core Store
B64: Tokens | C64: TTP | D64: QTY | F64: Pack | G64: Price | H64: TTP | I64: Buy | J64: TTP: | K64: =sum(N65:N67) -> 0
B65: 2310 | C65: 7000 | F65: T.T. Special | G65: 2.99 | H65: 7800 | I65: FALSE | K65: =H65*I65 -> 0 | L65: =G65*I65 -> 0 | N65: =C65*D65 -> 0
B66: 1020 | C66: 3000 | I66: FALSE | K66: =H66*I66 -> 0 | L66: =G66*I66 -> 0 | N66: =C66*D66 -> 0
B67: 525 | C67: 1500 | I67: FALSE | K67: =H67*I67 -> 0 | L67: =G67*I67 -> 0 | N67: =C67*D67 -> 0
I68: FALSE | K68: =H68*I68 -> 0 | L68: =G68*I68 -> 0
B69: Madden Cash | C69: TTP | D69: QTY | I69: FALSE | K69: =H69*I69 -> 0 | L69: =G69*I69 -> 0
B70: 400 | C70: 2400 | I70: FALSE | K70: =H70*I70 -> 0 | L70: =G70*I70 -> 0 | M70: =D70*B70 -> 0 | N70: =C70*D70 -> 0
B71: 300 | C71: 1500 | I71: FALSE | K71: =H71*I71 -> 0 | L71: =G71*I71 -> 0 | M71: =D71*B71 -> 0 | N71: =C71*D71 -> 0
B72: 200 | C72: 900 | I72: FALSE | K72: =H72*I72 -> 0 | L72: =G72*I72 -> 0 | M72: =D72*B72 -> 0 | N72: =C72*D72 -> 0
B73: 100 | C73: 400 | I73: FALSE | K73: =H73*I73 -> 0 | L73: =G73*I73 -> 0 | M73: =D73*B73 -> 0 | N73: =C73*D73 -> 0
B74: 500 | C74: 1750 | I74: FALSE | K74: =H74*I74 -> 0 | L74: =G74*I74 -> 0 | M74: =D74*B74 -> 0 | N74: =C74*D74 -> 0
B75: 400 | C75: 1200 | I75: FALSE | K75: =H75*I75 -> 0 | L75: =G75*I75 -> 0 | M75: =D75*B75 -> 0 | N75: =C75*D75 -> 0
B76: 300 | C76: 750 | I76: FALSE | K76: =H76*I76 -> 0 | L76: =G76*I76 -> 0 | M76: =D76*B76 -> 0 | N76: =C76*D76 -> 0
B77: 200 | C77: 440 | I77: FALSE | K77: =H77*I77 -> 0 | L77: =G77*I77 -> 0 | M77: =D77*B77 -> 0 | N77: =C77*D77 -> 0
B78: 1000 | C78: 2000 | I78: FALSE | K78: =H78*I78 -> 0 | L78: =G78*I78 -> 0 | M78: =D78*B78 -> 0 | N78: =C78*D78 -> 0
B79: 100 | C79: 200 | I79: FALSE | K79: =H79*I79 -> 0 | L79: =G79*I79 -> 0 | M79: =D79*B79 -> 0 | N79: =C79*D79 -> 0
I80: FALSE | K80: =H80*I80 -> 0 | L80: =G80*I80 -> 0
I81: FALSE | K81: =H81*I81 -> 0 | L81: =G81*I81 -> 0
J82: TTP: | K82: =sum(N70:N79) -> 0
B83: Other
B84: Contributions: | J84: TTP: | K84: =C84
B86: Player Trades | C86: Avg. TTP | D86: QTY | J86: TTP: | K86: =sum(N87:N88) -> 0
B87: Iconic | C87: 5000 | N87: =C87*D87 -> 0 | O87: =E87*F87 -> 0
B88: Mythic | C88: 11500 | N88: =C88*D88 -> 0 | O88: =E88*F88 -> 0
B90: Promo Tokens | C90: TTP: | J90: TTP: | K90: =D90*2 -> 0
B92: Daily Goals | C92: ✅ | J92: TTP: | K92: =SUM(C93:C104)*$E$3 -> -133500
B93: Goals | C93: 125
C94: 20
C95: 20
C96: 20
C97: 25
C98: 20
C99: 20
B100: Ad Watch | C100: 15
C101: 20
C102: 15
B103: Training Ad | C103: 100
B104: Journey Ad | C104: 100
B106: League Goals | C106: ✅ | J106: TTP: | K106: =SUM(C107:C111)*$E$3+SUM(C112:C116)*P2 -> -133500
B107: Daily | C107: 100
C108: 100
C109: 100
C110: 100
C111: 100
B112: Weekly | C112: 2000
C113: 2000
C114: 2000
C115: 2000
C116: 2000
B118: FP Milestones | C118: ✅ | D118: Completed: | E118: 43000 | N118: =if(E2="Yes",1,0) -> 1 | O118: VIP
B119: Milestones | C119: TTP | D119: VIP
...

Sheet Schedule
D1: Date | E1: Day | F1: Weeks | G1: PA Rushing | I1: PA Passing | K1: Arena Tourney | L1: Leaderboard | M1: Unlimited | N1: Draft | O1: 2 Min Drill | P1: EZF
A2: Current FP | B2: Past | C2: Active | F2: =sum(F3:F1002) -> 0 | G2: =SUM(G4:G1002) -> 0 | I2: =SUM(I4:I1002) -> 0 | K2: =SUM(K4:K1002) -> 0 | L2: =SUM(L4:L1002) -> 0 | M2: =SUM(M4:M1002) -> 0 | N2: =SUM(N4:N1002) -> 0 | O2: =SUM(O4:O1002) -> 0 | P2: =SUM(P4:P1002) -> 0
A3: =IF(and(D3>='TTP Tracker 26'!$C$3,D3<'TTP Tracker 26'!$C$4),1,0) -> 1 | B3: =if(and(D3>TODAY(),D3<'TTP Tracker 26'!$C$4),1,0) -> 0 | C3: =if('TTP Tracker 26'!$B$2="MONTHLY TOTAL",$A3,$B3) -> 0 | D3: 45876 | E3: Thursday | F3: =if(E3="Monday",1,0)*if(A3=1,1,0) -> 0
A4: =IF(and(D4>='TTP Tracker 26'!$C$3,D4<'TTP Tracker 26'!$C$4),1,0) -> 1 | B4: =if(and(D4>TODAY(),D4<'TTP Tracker 26'!$C$4),1,0) -> 0 | C4: =if('TTP Tracker 26'!$B$2="MONTHLY TOTAL",$A4,$B4) -> 0 | D4: 45877 | E4: Friday | F4: =if(E4="Monday",1,0)*if(A4=1,1,0) -> 0 | G4: =if('TTP Tracker 26'!$B$2="MONTHLY TOTAL",$A4,$B4) -> 0
A5: =IF(and(D5>='TTP Tracker 26'!$C$3,D5<'TTP Tracker 26'!$C$4),1,0) -> 1 | B5: =if(and(D5>TODAY(),D5<'TTP Tracker 26'!$C$4),1,0) -> 0 | C5: =if('TTP Tracker 26'!$B$2="MONTHLY TOTAL",$A5,$B5) -> 0 | D5: 45878 | E5: Saturday | F5: =if(E5="Monday",1,0)*if(A5=1,1,0) -> 0 | K5: =if('TTP Tracker 26'!$B$2="MONTHLY TOTAL",$A5,$B5) -> 0
A6: =IF(and(D6>='TTP Tracker 26'!$C$3,D6<'TTP Tracker 26'!$C$4),1,0) -> 1 | B6: =if(and(D6>TODAY(),D6<'TTP Tracker 26'!$C$4),1,0) -> 0 | C6: =if('TTP Tracker 26'!$B$2="MONTHLY TOTAL",$A6,$B6) -> 0 | D6: 45879 | E6: Sunday | F6: =if(E6="Monday",1,0)*if(A6=1,1,0) -> 0
A7: =IF(and(D7>='TTP Tracker 26'!$C$3,D7<'TTP Tracker 26'!$C$4),1,0) -> 1 | B7: =if(and(D7>TODAY(),D7<'TTP Tracker 26'!$C$4),1,0) -> 0 | C7: =if('TTP Tracker 26'!$B$2="MONTHLY TOTAL",$A7,$B7) -> 0 | D7: 45880 | E7: Monday | F7: =if(E7="Monday",1,0)*if(C7=1,1,0) -> 0 | L7: =if('TTP Tracker 26'!$B$2="MONTHLY TOTAL",$A7,$B7) -> 0 | M7: =if('TTP Tracker 26'!$B$2="MONTHLY TOTAL",$A7,$B7) -> 0
A8: =IF(and(D8>='TTP Tracker 26'!$C$3,D8<'TTP Tracker 26'!$C$4),1,0) -> 1 | B8: =if(and(D8>TODAY(),D8<'TTP Tracker 26'!$C$4),1,0) -> 0 | C8: =if('TTP Tracker 26'!$B$2="MONTHLY TOTAL",$A8,$B8) -> 0 | D8: 45881 | E8: Tuesday | F8: =if(E8="Monday",1,0)*if(A8=1,1,0) -> 0
A9: =IF(and(D9>='TTP Tracker 26'!$C$3,D9<'TTP Tracker 26'!$C$4),1,0) -> 1 | B9: =if(and(D9>TODAY(),D9<'TTP Tracker 26'!$C$4),1,0) -> 0 | C9: =if('TTP Tracker 26'!$B$2="MONTHLY TOTAL",$A9,$B9) -> 0 | D9: 45882 | E9: Wednesday | F9: =if(E9="Monday",1,0)*if(A9=1,1,0) -> 0
A10: =IF(and(D10>='TTP Tracker 26'!$C$3,D10<'TTP Tracker 26'!$C$4),1,0) -> 1 | B10: =if(and(D10>TODAY(),D10<'TTP Tracker 26'!$C$4),1,0) -> 0 | C10: =if('TTP Tracker 26'!$B$2="MONTHLY TOTAL",$A10,$B10) -> 0 | D10: 45883 | E10: Thursday | F10: =if(E10="Monday",1,0)*if(A10=1,1,0) -> 0
A11: =IF(and(D11>='TTP Tracker 26'!$C$3,D11<'TTP Tracker 26'!$C$4),1,0) -> 1 | B11: =if(and(D11>TODAY(),D11<'TTP Tracker 26'!$C$4),1,0) -> 0 | C11: =if('TTP Tracker 26'!$B$2="MONTHLY TOTAL",$A11,$B11) -> 0 | D11: 45884 | E11: Friday | F11: =if(E11="Monday",1,0)*if(A11=1,1,0) -> 0 | I11: =if('TTP Tracker 26'!$B$2="MONTHLY TOTAL",$A11,$B11) -> 0
A12: =IF(and(D12>='TTP Tracker 26'!$C$3,D12<'TTP Tracker 26'!$C$4),1,0) -> 1 | B12: =if(and(D12>TODAY(),D12<'TTP Tracker 26'!$C$4),1,0) -> 0 | C12: =if('TTP Tracker 26'!$B$2="MONTHLY TOTAL",$A12,$B12) -> 0 | D12: 45885 | E12: Saturday | F12: =if(E12="Monday",1,0)*if(A12=1,1,0) -> 0
A13: =IF(and(D13>='TTP Tracker 26'!$C$3,D13<'TTP Tracker 26'!$C$4),1,0) -> 1 | B13: =if(and(D13>TODAY(),D13<'TTP Tracker 26'!$C$4),1,0) -> 0 | C13: =if('TTP Tracker 26'!$B$2="MONTHLY TOTAL",$A13,$B13) -> 0 | D13: 45886 | E13: Sunday | F13: =if(E13="Monday",1,0)*if(A13=1,1,0) -> 0
A14: =IF(and(D14>='TTP Tracker 26'!$C$3,D14<'TTP Tracker 26'!$C$4),1,0) -> 1 | B14: =if(and(D14>TODAY(),D14<'TTP Tracker 26'!$C$4),1,0) -> 0 | C14: =if('TTP Tracker 26'!$B$2="MONTHLY TOTAL",$A14,$B14) -> 0 | D14: 45887 | E14: Monday | F14: =if(E14="Monday",1,0)*if(C14=1,1,0) -> 0 | M14: =if('TTP Tracker 26'!$B$2="MONTHLY TOTAL",$A14,$B14) -> 0
A15: =IF(and(D15>='TTP Tracker 26'!$C$3,D15<'TTP Tracker 26'!$C$4),1,0) -> 1 | B15: =if(and(D15>TODAY(),D15<'TTP Tracker 26'!$C$4),1,0) -> 0 | C15: =if('TTP Tracker 26'!$B$2="MONTHLY TOTAL",$A15,$B15) -> 0 | D15: 45888 | E15: Tuesday | F15: =if(E15="Monday",1,0)*if(A15=1,1,0) -> 0
A16: =IF(and(D16>='TTP Tracker 26'!$C$3,D16<'TTP Tracker 26'!$C$4),1,0) -> 1 | B16: =if(and(D16>TODAY(),D16<'TTP Tracker 26'!$C$4),1,0) -> 0 | C16: =if('TTP Tracker 26'!$B$2="MONTHLY TOTAL",$A16,$B16) -> 0 | D16: 45889 | E16: Wednesday | F16: =if(E16="Monday",1,0)*if(A16=1,1,0) -> 0
A17: =IF(and(D17>='TTP Tracker 26'!$C$3,D17<'TTP Tracker 26'!$C$4),1,0) -> 1 | B17: =if(and(D17>TODAY(),D17<'TTP Tracker 26'!$C$4),1,0) -> 0 | C17: =if('TTP Tracker 26'!$B$2="MONTHLY TOTAL",$A17,$B17) -> 0 | D17: 45890 | E17: Thursday | F17: =if(E17="Monday",1,0)*if(A17=1,1,0) -> 0
A18: =IF(and(D18>='TTP Tracker 26'!$C$3,D18<'TTP Tracker 26'!$C$4),1,0) -> 1 | B18: =if(and(D18>TODAY(),D18<'TTP Tracker 26'!$C$4),1,0) -> 0 | C18: =if('TTP Tracker 26'!$B$2="MONTHLY TOTAL",$A18,$B18) -> 0 | D18: 45891 | E18: Friday | F18: =if(E18="Monday",1,0)*if(A18=1,1,0) -> 0 | G18: =if('TTP Tracker 26'!$B$2="MONTHLY TOTAL",$A18,$B18) -> 0
A19: =IF(and(D19>='TTP Tracker 26'!$C$3,D19<'TTP Tracker 26'!$C$4),1,0) -> 1 | B19: =if(and(D19>TODAY(),D19<'TTP Tracker 26'!$C$4),1,0) -> 0 | C19: =if('TTP Tracker 26'!$B$2="MONTHLY TOTAL",$A19,$B19) -> 0 | D19: 45892 | E19: Saturday | F19: =if(E19="Monday",1,0)*if(A19=1,1,0) -> 0 | K19: =if('TTP Tracker 26'!$B$2="MONTHLY TOTAL",$A19,$B19) -> 0
A20: =IF(and(D20>='TTP Tracker 26'!$C$3,D20<'TTP Tracker 26'!$C$4),1,0) -> 1 | B20: =if(and(D20>TODAY(),D20<'TTP Tracker 26'!$C$4),1,0) -> 0 | C20: =if('TTP Tracker 26'!$B$2="MONTHLY TOTAL",$A20,$B20) -> 0 | D20: 45893 | E20: Sunday | F20: =if(E20="Monday",1,0)*if(A20=1,1,0) -> 0
A21: =IF(and(D21>='TTP Tracker 26'!$C$3,D21<'TTP Tracker 26'!$C$4),1,0) -> 1 | B21: =if(and(D21>TODAY(),D21<'TTP Tracker 26'!$C$4),1,0) -> 0 | C21: =if('TTP Tracker 26'!$B$2="MONTHLY TOTAL",$A21,$B21) -> 0 | D21: 45894 | E21: Monday | F21: =if(E21="Monday",1,0)*if(C21=1,1,0) -> 0 | L21: =if('TTP Tracker 26'!$B$2="MONTHLY TOTAL",$A21,$B21) -> 0 | M21: =if('TTP Tracker 26'!$B$2="MONTHLY TOTAL",$A21,$B21) -> 0
A22: =IF(and(D22>='TTP Tracker 26'!$C$3,D22<'TTP Tracker 26'!$C$4),1,0) -> 1 | B22: =if(and(D22>TODAY(),D22<'TTP Tracker 26'!$C$4),1,0) -> 0 | C22: =if('TTP Tracker 26'!$B$2="MONTHLY TOTAL",$A22,$B22) -> 0 | D22: 45895 | E22: Tuesday | F22: =if(E22="Monday",1,0)*if(A22=1,1,0) -> 0
A23: =IF(and(D23>='TTP Tracker 26'!$C$3,D23<'TTP Tracker 26'!$C$4),1,0) -> 1 | B23: =if(and(D23>TODAY(),D23<'TTP Tracker 26'!$C$4),1,0) -> 0 | C23: =if('TTP Tracker 26'!$B$2="MONTHLY TOTAL",$A23,$B23) -> 0 | D23: 45896 | E23: Wednesday | F23: =if(E23="Monday",1,0)*if(A23=1,1,0) -> 0
A24: =IF(and(D24>='TTP Tracker 26'!$C$3,D24<'TTP Tracker 26'!$C$4),1,0) -> 1 | B24: =if(and(D24>TODAY(),D24<'TTP Tracker 26'!$C$4),1,0) -> 0 | C24: =if('TTP Tracker 26'!$B$2="MONTHLY TOTAL",$A24,$B24) -> 0 | D24: 45897 | E24: Thursday | F24: =if(E24="Monday",1,0)*if(A24=1,1,0) -> 0
A25: =IF(and(D25>='TTP Tracker 26'!$C$3,D25<'TTP Tracker 26'!$C$4),1,0) -> 1 | B25: =if(and(D25>TODAY(),D25<'TTP Tracker 26'!$C$4),1,0) -> 0 | C25: =if('TTP Tracker 26'!$B$2="MONTHLY TOTAL",$A25,$B25) -> 0 | D25: 45898 | E25: Friday | F25: =if(E25="Monday",1,0)*if(A25=1,1,0) -> 0 | I25: =if('TTP Tracker 26'!$B$2="MONTHLY TOTAL",$A25,$B25) -> 0
A26: =IF(and(D26>='TTP Tracker 26'!$C$3,D26<'TTP Tracker 26'!$C$4),1,0) -> 1 | B26: =if(and(D26>TODAY(),D26<'TTP Tracker 26'!$C$4),1,0) -> 0 | C26: =if('TTP Tracker 26'!$B$2="MONTHLY TOTAL",$A26,$B26) -> 0 | D26: 45899 | E26: Saturday | F26: =if(E26="Monday",1,0)*if(A26=1,1,0) -> 0
A27: =IF(and(D27>='TTP Tracker 26'!$C$3,D27<'TTP Tracker 26'!$C$4),1,0) -> 1 | B27: =if(and(D27>TODAY(),D27<'TTP Tracker 26'!$C$4),1,0) -> 0 | C27: =if('TTP Tracker 26'!$B$2="MONTHLY TOTAL",$A27,$B27) -> 0 | D27: 45900 | E27: Sunday | F27: =if(E27="Monday",1,0)*if(A27=1,1,0) -> 0
A28: =IF(and(D28>='TTP Tracker 26'!$C$3,D28<'TTP Tracker 26'!$C$4),1,0) -> 1 | B28: =if(and(D28>TODAY(),D28<'TTP Tracker 26'!$C$4),1,0) -> 0 | C28: =if('TTP Tracker 26'!$B$2="MONTHLY TOTAL",$A28,$B28) -> 0 | D28: 45901 | E28: Monday | F28: =if(E28="Monday",1,0)*if(C28=1,1,0) -> 0 | M28: =if('TTP Tracker 26'!$B$2="MONTHLY TOTAL",$A28,$B28) -> 0
A29: =IF(and(D29>='TTP Tracker 26'!$C$3,D29<'TTP Tracker 26'!$C$4),1,0) -> 1 | B29: =if(and(D29>TODAY(),D29<'TTP Tracker 26'!$C$4),1,0) -> 0 | C29: =if('TTP Tracker 26'!$B$2="MONTHLY TOTAL",$A29,$B29) -> 0 | D29: 45902 | E29: Tuesday | F29: =if(E29="Monday",1,0)*if(A29=1,1,0) -> 0
A30: =IF(and(D30>='TTP Tracker 26'!$C$3,D30<'TTP Tracker 26'!$C$4),1,0) -> 1 | B30: =if(and(D30>TODAY(),D30<'TTP Tracker 26'!$C$4),1,0) -> 0 | C30: =if('TTP Tracker 26'!$B$2="MONTHLY TOTAL",$A30,$B30) -> 0 | D30: 45903 | E30: Wednesday | F30: =if(E30="Monday",1,0)*if(A30=1,1,0) -> 0
A31: =IF(and(D31>='TTP Tracker 26'!$C$3,D31<'TTP Tracker 26'!$C$4),1,0) -> 1 | B31: =if(and(D31>TODAY(),D31<'TTP Tracker 26'!$C$4),1,0) -> 0 | C31: =if('TTP Tracker 26'!$B$2="MONTHLY TOTAL",$A31,$B31) -> 0 | D31: 45904 | E31: Thursday | F31: =if(E31="Monday",1,0)*if(A31=1,1,0) -> 0
A32: =IF(and(D32>='TTP Tracker 26'!$C$3,D32<'TTP Tracker 26'!$C$4),1,0) -> 1 | B32: =if(and(D32>TODAY(),D32<'TTP Tracker 26'!$C$4),1,0) -> 0 | C32: =if('TTP Tracker 26'!$B$2="MONTHLY TOTAL",$A32,$B32) -> 0 | D32: 45905 | E32: Friday | F32: =if(E32="Monday",1,0)*if(A32=1,1,0) -> 0 | G32: =if('TTP Tracker 26'!$B$2="MONTHLY TOTAL",$A32,$B32) -> 0
A33: =IF(and(D33>='TTP Tracker 26'!$C$3,D33<'TTP Tracker 26'!$C$4),1,0) -> 1 | B33: =if(and(D33>TODAY(),D33<'TTP Tracker 26'!$C$4),1,0) -> 0 | C33: =if('TTP Tracker 26'!$B$2="MONTHLY TOTAL",$A33,$B33) -> 0 | D33: 45906 | E33: Saturday | F33: =if(E33="Monday",1,0)*if(A33=1,1,0) -> 0 | K33: =if('TTP Tracker 26'!$B$2="MONTHLY TOTAL",$A33,$B33) -> 0
A34: =IF(and(D34>='TTP Tracker 26'!$C$3,D34<'TTP Tracker 26'!$C$4),1,0) -> 1 | B34: =if(and(D34>TODAY(),D34<'TTP Tracker 26'!$C$4),1,0) -> 0 | C34: =if('TTP Tracker 26'!$B$2="MONTHLY TOTAL",$A34,$B34) -> 0 | D34: 45907 | E34: Sunday | F34: =if(E34="Monday",1,0)*if(A34=1,1,0) -> 0
A35: =IF(and(D35>='TTP Tracker 26'!$C$3,D35<'TTP Tracker 26'!$C$4),1,0) -> 0 | B35: =if(and(D35>TODAY(),D35<'TTP Tracker 26'!$C$4),1,0) -> 0 | C35: =if('TTP Tracker 26'!$B$2="MONTHLY TOTAL",$A35,$B35) -> 0 | D35: 45908 | E35: Monday | F35: =if(E35="Monday",1,0)*if(C35=1,1,0) -> 0 | L35: =if('TTP Tracker 26'!$B$2="MONTHLY TOTAL",$A35,$B35) -> 0 | M35: =if('TTP Tracker 26'!$B$2="MONTHLY TOTAL",$A35,$B35) -> 0
A36: =IF(and(D36>='TTP Tracker 26'!$C$3,D36<'TTP Tracker 26'!$C$4),1,0) -> 0 | B36: =if(and(D36>TODAY(),D36<'TTP Tracker 26'!$C$4),1,0) -> 0 | C36: =if('TTP Tracker 26'!$B$2="MONTHLY TOTAL",$A36,$B36) -> 0 | D36: 45909 | E36: Tuesday | F36: =if(E36="Monday",1,0)*if(C36=1,1,0) -> 0
A37: =IF(and(D37>='TTP Tracker 26'!$C$3,D37<'TTP Tracker 26'!$C$4),1,0) -> 0 | B37: =if(and(D37>TODAY(),D37<'TTP Tracker 26'!$C$4),1,0) -> 0 | C37: =if('TTP Tracker 26'!$B$2="MONTHLY TOTAL",$A37,$B37) -> 0 | D37: 45910 | E37: Wednesday | F37: =if(E37="Monday",1,0)*if(C37=1,1,0) -> 0
A38: =IF(and(D38>='TTP Tracker 26'!$C$3,D38<'TTP Tracker 26'!$C$4),1,0) -> 0 | B38: =if(and(D38>TODAY(),D38<'TTP Tracker 26'!$C$4),1,0) -> 0 | C38: =if('TTP Tracker 26'!$B$2="MONTHLY TOTAL",$A38,$B38) -> 0 | D38: 45911 | E38: Thursday | F38: =if(E38="Monday",1,0)*if(C38=1,1,0) -> 0
A39: =IF(and(D39>='TTP Tracker 26'!$C$3,D39<'TTP Tracker 26'!$C$4),1,0) -> 0 | B39: =if(and(D39>TODAY(),D39<'TTP Tracker 26'!$C$4),1,0) -> 0 | C39: =if('TTP Tracker 26'!$B$2="MONTHLY TOTAL",$A39,$B39) -> 0 | D39: 45912 | E39: Friday | F39: =if(E39="Monday",1,0)*if(C39=1,1,0) -> 0 | I39: =if('TTP Tracker 26'!$B$2="MONTHLY TOTAL",$A39,$B39) -> 0
A40: =IF(and(D40>='TTP Tracker 26'!$C$3,D40<'TTP Tracker 26'!$C$4),1,0) -> 0 | B40: =if(and(D40>TODAY(),D40<'TTP Tracker 26'!$C$4),1,0) -> 0 | C40: =if('TTP Tracker 26'!$B$2="MONTHLY TOTAL",$A40,$B40) -> 0 | D40: 45913 | E40: Saturday | F40: =if(E40="Monday",1,0)*if(C40=1,1,0) -> 0
A41: =IF(and(D41>='TTP Tracker 26'!$C$3,D41<'TTP Tracker 26'!$C$4),1,0) -> 0 | B41: =if(and(D41>TODAY(),D41<'TTP Tracker 26'!$C$4),1,0) -> 0 | C41: =if('TTP Tracker 26'!$B$2="MONTHLY TOTAL",$A41,$B41) -> 0 | D41: 45914 | E41: Sunday | F41: =if(E41="Monday",1,0)*if(C41=1,1,0) -> 0
A42: =IF(and(D42>='TTP Tracker 26'!$C$3,D42<'TTP Tracker 26'!$C$4),1,0) -> 0 | B42: =if(and(D42>TODAY(),D42<'TTP Tracker 26'!$C$4),1,0) -> 0 | C42: =if('TTP Tracker 26'!$B$2="MONTHLY TOTAL",$A42,$B42) -> 0 | D42: 45915 | E42: Monday | F42: =if(E42="Monday",1,0)*if(C42=1,1,0) -> 0 | M42: =if('TTP Tracker 26'!$B$2="MONTHLY TOTAL",$A42,$B42) -> 0
A43: =IF(and(D43>='TTP Tracker 26'!$C$3,D43<'TTP Tracker 26'!$C$4),1,0) -> 0 | B43: =if(and(D43>TODAY(),D43<'TTP Tracker 26'!$C$4),1,0) -> 0 | C43: =if('TTP Tracker 26'!$B$2="MONTHLY TOTAL",$A43,$B43) -> 0 | D43: 45916 | E43: Tuesday | F43: =if(E43="Monday",1,0)*if(C43=1,1,0) -> 0
A44: =IF(and(D44>='TTP Tracker 26'!$C$3,D44<'TTP Tracker 26'!$C$4),1,0) -> 0 | B44: =if(and(D44>TODAY(),D44<'TTP Tracker 26'!$C$4),1,0) -> 0 | C44: =if('TTP Tracker 26'!$B$2="MONTHLY TOTAL",$A44,$B44) -> 0 | D44: 45917 | E44: Wednesday | F44: =if(E44="Monday",1,0)*if(C44=1,1,0) -> 0
A45: =IF(and(D45>='TTP Tracker 26'!$C$3,D45<'TTP Tracker 26'!$C$4),1,0) -> 0 | B45: =if(and(D45>TODAY(),D45<'TTP Tracker 26'!$C$4),1,0) -> 0 | C45: =if('TTP Tracker 26'!$B$2="MONTHLY TOTAL",$A45,$B45) -> 0 | D45: 45918 | E45: Thursday | F45: =if(E45="Monday",1,0)*if(C45=1,1,0) -> 0
A46: =IF(and(D46>='TTP Tracker 26'!$C$3,D46<'TTP Tracker 26'!$C$4),1,0) -> 0 | B46: =if(and(D46>TODAY(),D46<'TTP Tracker 26'!$C$4),1,0) -> 0 | C46: =if('TTP Tracker 26'!$B$2="MONTHLY TOTAL",$A46,$B46) -> 0 | D46: 45919 | E46: Friday | F46: =if(E46="Monday",1,0)*if(C46=1,1,0) -> 0 | G46: =if('TTP Tracker 26'!$B$2="MONTHLY TOTAL",$A46,$B46) -> 0
A47: =IF(and(D47>='TTP Tracker 26'!$C$3,D47<'TTP Tracker 26'!$C$4),1,0) -> 0 | B47: =if(and(D47>TODAY(),D47<'TTP Tracker 26'!$C$4),1,0) -> 0 | C47: =if('TTP Tracker 26'!$B$2="MONTHLY TOTAL",$A47,$B47) -> 0 | D47: 45920 | E47: Saturday | F47: =if(E47="Monday",1,0)*if(C47=1,1,0) -> 0 | K47: =if('TTP Tracker 26'!$B$2="MONTHLY TOTAL",$A47,$B47) -> 0
A48: =IF(and(D48>='TTP Tracker 26'!$C$3,D48<'TTP Tracker 26'!$C$4),1,0) -> 0 | B48: =if(and(D48>TODAY(),D48<'TTP Tracker 26'!$C$4),1,0) -> 0 | C48: =if('TTP Tracker 26'!$B$2="MONTHLY TOTAL",$A48,$B48) -> 0 | D48: 45921 | E48: Sunday | F48: =if(E48="Monday",1,0)*if(C48=1,1,0) -> 0
A49: =IF(and(D49>='TTP Tracker 26'!$C$3,D49<'TTP Tracker 26'!$C$4),1,0) -> 0 | B49: =if(and(D49>TODAY(),D49<'TTP Tracker 26'!$C$4),1,0) -> 0 | C49: =if('TTP Tracker 26'!$B$2="MONTHLY TOTAL",$A49,$B49) -> 0 | D49: 45922 | E49: Monday | F49: =if(E49="Monday",1,0)*if(C49=1,1,0) -> 0 | L49: =if('TTP Tracker 26'!$B$2="MONTHLY TOTAL",$A49,$B49) -> 0 | M49: =if('TTP Tracker 26'!$B$2="MONTHLY TOTAL",$A49,$B49) -> 0
A50: =IF(and(D50>='TTP Tracker 26'!$C$3,D50<'TTP Tracker 26'!$C$4),1,0) -> 0 | B50: =if(and(D50>TODAY(),D50<'TTP Tracker 26'!$C$4),1,0) -> 0 | C50: =if('TTP Tracker 26'!$B$2="MONTHLY TOTAL",$A50,$B50) -> 0 | D50: 45923 | E50: Tuesday | F50: =if(E50="Monday",1,0)*if(C50=1,1,0) -> 0
A51: =IF(and(D51>='TTP Tracker 26'!$C$3,D51<'TTP Tracker 26'!$C$4),1,0) -> 0 | B51: =if(and(D51>TODAY(),D51<'TTP Tracker 26'!$C$4),1,0) -> 0 | C51: =if('TTP Tracker 26'!$B$2="MONTHLY TOTAL",$A51,$B51) -> 0 | D51: 45924 | E51: Wednesday | F51: =if(E51="Monday",1,0)*if(C51=1,1,0) -> 0
A52: =IF(and(D52>='TTP Tracker 26'!$C$3,D52<'TTP Tracker 26'!$C$4),1,0) -> 0 | B52: =if(and(D52>TODAY(),D52<'TTP Tracker 26'!$C$4),1,0) -> 0 | C52: =if('TTP Tracker 26'!$B$2="MONTHLY TOTAL",$A52,$B52) -> 0 | D52: 45925 | E52: Thursday | F52: =if(E52="Monday",1,0)*if(C52=1,1,0) -> 0
A53: =IF(and(D53>='TTP Tracker 26'!$C$3,D53<'TTP Tracker 26'!$C$4),1,0) -> 0 | B53: =if(and(D53>TODAY(),D53<'TTP Tracker 26'!$C$4),1,0) -> 0 | C53: =if('TTP Tracker 26'!$B$2="MONTHLY TOTAL",$A53,$B53) -> 0 | D53: 45926 | E53: Friday | F53: =if(E53="Monday",1,0)*if(C53=1,1,0) -> 0 | I53: =if('TTP Tracker 26'!$B$2="MONTHLY TOTAL",$A53,$B53) -> 0
A54: =IF(and(D54>='TTP Tracker 26'!$C$3,D54<'TTP Tracker 26'!$C$4),1,0) -> 0 | B54: =if(and(D54>TODAY(),D54<'TTP Tracker 26'!$C$4),1,0) -> 0 | C54: =if('TTP Tracker 26'!$B$2="MONTHLY TOTAL",$A54,$B54) -> 0 | D54: 45927 | E54: Saturday | F54: =if(E54="Monday",1,0)*if(C54=1,1,0) -> 0
A55: =IF(and(D55>='TTP Tracker 26'!$C$3,D55<'TTP Tracker 26'!$C$4),1,0) -> 0 | B55: =if(and(D55>TODAY(),D55<'TTP Tracker 26'!$C$4),1,0) -> 0 | C55: =if('TTP Tracker 26'!$B$2="MONTHLY TOTAL",$A55,$B55) -> 0 | D55: 45928 | E55: Sunday | F55: =if(E55="Monday",1,0)*if(C55=1,1,0) -> 0
A56: =IF(and(D56>='TTP Tracker 26'!$C$3,D56<'TTP Tracker 26'!$C$4),1,0) -> 0 | B56: =if(and(D56>TODAY(),D56<'TTP Tracker 26'!$C$4),1,0) -> 0 | C56: =if('TTP Tracker 26'!$B$2="MONTHLY TOTAL",$A56,$B56) -> 0 | D56: 45929 | E56: Monday | F56: =if(E56="Monday",1,0)*if(C56=1,1,0) -> 0 | M56: =if('TTP Tracker 26'!$B$2="MONTHLY TOTAL",$A56,$B56) -> 0
A57: =IF(and(D57>='TTP Tracker 26'!$C$3,D57<'TTP Tracker 26'!$C$4),1,0) -> 0 | B57: =if(and(D57>TODAY(),D57<'TTP Tracker 26'!$C$4),1,0) -> 0 | C57: =if('TTP Tracker 26'!$B$2="MONTHLY TOTAL",$A57,$B57) -> 0 | D57: 45930 | E57: Tuesday | F57: =if(E57="Monday",1,0)*if(C57=1,1,0) -> 0
A58: =IF(and(D58>='TTP Tracker 26'!$C$3,D58<'TTP Tracker 26'!$C$4),1,0) -> 0 | B58: =if(and(D58>TODAY(),D58<'TTP Tracker 26'!$C$4),1,0) -> 0 | C58: =if('TTP Tracker 26'!$B$2="MONTHLY TOTAL",$A58,$B58) -> 0 | D58: 45931 | E58: Wednesday | F58: =if(E58="Monday",1,0)*if(C58=1,1,0) -> 0
A59: =IF(and(D59>='TTP Tracker 26'!$C$3,D59<'TTP Tracker 26'!$C$4),1,0) -> 0 | B59: =if(and(D59>TODAY(),D59<'TTP Tracker 26'!$C$4),1,0) -> 0 | C59: =if('TTP Tracker 26'!$B$2="MONTHLY TOTAL",$A59,$B59) -> 0 | D59: 45932 | E59: Thursday | F59: =if(E59="Monday",1,0)*if(C59=1,1,0) -> 0
A60: =IF(and(D60>='TTP Tracker 26'!$C$3,D60<'TTP Tracker 26'!$C$4),1,0) -> 0 | B60: =if(and(D60>TODAY(),D60<'TTP Tracker 26'!$C$4),1,0) -> 0 | C60: =if('TTP Tracker 26'!$B$2="MONTHLY TOTAL",$A60,$B60) -> 0 | D60: 45933 | E60: Friday | F60: =if(E60="Monday",1,0)*if(C60=1,1,0) -> 0 | G60: =if('TTP Tracker 26'!$B$2="MONTHLY TOTAL",$A60,$B60) -> 0
A61: =IF(and(D61>='TTP Tracker 26'!$C$3,D61<'TTP Tracker 26'!$C$4),1,0) -> 0 | B61: =if(and(D61>TODAY(),D61<'TTP Tracker 26'!$C$4),1,0) -> 0 | C61: =if('TTP Tracker 26'!$B$2="MONTHLY TOTAL",$A61,$B61) -> 0 | D61: 45934 | E61: Saturday | F61: =if(E61="Monday",1,0)*if(C61=1,1,0) -> 0 | K61: =if('TTP Tracker 26'!$B$2="MONTHLY TOTAL",$A61,$B61) -> 0
A62: =IF(and(D62>='TTP Tracker 26'!$C$3,D62<'TTP Tracker 26'!$C$4),1,0) -> 0 | B62: =if(and(D62>TODAY(),D62<'TTP Tracker 26'!$C$4),1,0) -> 0 | C62: =if('TTP Tracker 26'!$B$2="MONTHLY TOTAL",$A62,$B62) -> 0 | D62: 45935 | E62: Sunday | F62: =if(E62="Monday",1,0)*if(C62=1,1,0) -> 0
A63: =IF(and(D63>='TTP Tracker 26'!$C$3,D63<'TTP Tracker 26'!$C$4),1,0) -> 0 | B63: =if(and(D63>TODAY(),D63<'TTP Tracker 26'!$C$4),1,0) -> 0 | C63: =if('TTP Tracker 26'!$B$2="MONTHLY TOTAL",$A63,$B63) -> 0 | D63: 45936 | E63: Monday | F63: =if(E63="Monday",1,0)*if(C63=1,1,0) -> 0 | L63: =if('TTP Tracker 26'!$B$2="MONTHLY TOTAL",$A63,$B63) -> 0 | M63: =if('TTP Tracker 26'!$B$2="MONTHLY TOTAL",$A63,$B63) -> 0
A64: =IF(and(D64>='TTP Tracker 26'!$C$3,D64<'TTP Tracker 26'!$C$4),1,0) -> 0 | B64: =if(and(D64>TODAY(),D64<'TTP Tracker 26'!$C$4),1,0) -> 0 | C64: =if('TTP Tracker 26'!$B$2="MONTHLY TOTAL",$A64,$B64) -> 0 | D64: 45937 | E64: Tuesday | F64: =if(E64="Monday",1,0)*if(C64=1,1,0) -> 0
A65: =IF(and(D65>='TTP Tracker 26'!$C$3,D65<'TTP Tracker 26'!$C$4),1,0) -> 0 | B65: =if(and(D65>TODAY(),D65<'TTP Tracker 26'!$C$4),1,0) -> 0 | C65: =if('TTP Tracker 26'!$B$2="MONTHLY TOTAL",$A65,$B65) -> 0 | D65: 45938 | E65: Wednesday | F65: =if(E65="Monday",1,0)*if(C65=1,1,0) -> 0
A66: =IF(and(D66>='TTP Tracker 26'!$C$3,D66<'TTP Tracker 26'!$C$4),1,0) -> 0 | B66: =if(and(D66>TODAY(),D66<'TTP Tracker 26'!$C$4),1,0) -> 0 | C66: =if('TTP Tracker 26'!$B$2="MONTHLY TOTAL",$A66,$B66) -> 0 | D66: 45939 | E66: Thursday | F66: =if(E66="Monday",1,0)*if(C66=1,1,0) -> 0
A67: =IF(and(D67>='TTP Tracker 26'!$C$3,D67<'TTP Tracker 26'!$C$4),1,0) -> 0 | B67: =if(and(D67>TODAY(),D67<'TTP Tracker 26'!$C$4),1,0) -> 0 | C67: =if('TTP Tracker 26'!$B$2="MONTHLY TOTAL",$A67,$B67) -> 0 | D67: 45940 | E67: Friday | F67: =if(E67="Monday",1,0)*if(C67=1,1,0) -> 0 | I67: =if('TTP Tracker 26'!$B$2="MONTHLY TOTAL",$A67,$B67) -> 0
A68: =IF(and(D68>='TTP Tracker 26'!$C$3,D68<'TTP Tracker 26'!$C$4),1,0) -> 0 | B68: =if(and(D68>TODAY(),D68<'TTP Tracker 26'!$C$4),1,0) -> 0 | C68: =if('TTP Tracker 26'!$B$2="MONTHLY TOTAL",$A68,$B68) -> 0 | D68: 45941 | E68: Saturday | F68: =if(E68="Monday",1,0)*if(C68=1,1,0) -> 0
A69: =IF(and(D69>='TTP Tracker 26'!$C$3,D69<'TTP Tracker 26'!$C$4),1,0) -> 0 | B69: =if(and(D69>TODAY(),D69<'TTP Tracker 26'!$C$4),1,0) -> 0 | C69: =if('TTP Tracker 26'!$B$2="MONTHLY TOTAL",$A69,$B69) -> 0 | D69: 45942 | E69: Sunday | F69: =if(E69="Monday",1,0)*if(C69=1,1,0) -> 0
A70: =IF(and(D70>='TTP Tracker 26'!$C$3,D70<'TTP Tracker 26'!$C$4),1,0) -> 0 | B70: =if(and(D70>TODAY(),D70<'TTP Tracker 26'!$C$4),1,0) -> 0 | C70: =if('TTP Tracker 26'!$B$2="MONTHLY TOTAL",$A70,$B70) -> 0 | D70: 45943 | E70: Monday | F70: =if(E70="Monday",1,0)*if(C70=1,1,0) -> 0 | M70: =if('TTP Tracker 26'!$B$2="MONTHLY TOTAL",$A70,$B70) -> 0
A71: =IF(and(D71>='TTP Tracker 26'!$C$3,D71<'TTP Tracker 26'!$C$4),1,0) -> 0 | B71: =if(and(D71>TODAY(),D71<'TTP Tracker 26'!$C$4),1,0) -> 0 | C71: =if('TTP Tracker 26'!$B$2="MONTHLY TOTAL",$A71,$B71) -> 0 | D71: 45944 | E71: Tuesday | F71: =if(E71="Monday",1,0)*if(C71=1,1,0) -> 0
A72: =IF(and(D72>='TTP Tracker 26'!$C$3,D72<'TTP Tracker 26'!$C$4),1,0) -> 0 | B72: =if(and(D72>TODAY(),D72<'TTP Tracker 26'!$C$4),1,0) -> 0 | C72: =if('TTP Tracker 26'!$B$2="MONTHLY TOTAL",$A72,$B72) -> 0 | D72: 45945 | E72: Wednesday | F72: =if(E72="Monday",1,0)*if(C72=1,1,0) -> 0
A73: =IF(and(D73>='TTP Tracker 26'!$C$3,D73<'TTP Tracker 26'!$C$4),1,0) -> 0 | B73: =if(and(D73>TODAY(),D73<'TTP Tracker 26'!$C$4),1,0) -> 0 | C73: =if('TTP Tracker 26'!$B$2="MONTHLY TOTAL",$A73,$B73) -> 0 | D73: 45946 | E73: Thursday | F73: =if(E73="Monday",1,0)*if(C73=1,1,0) -> 0
A74: =IF(and(D74>='TTP Tracker 26'!$C$3,D74<'TTP Tracker 26'!$C$4),1,0) -> 0 | B74: =if(and(D74>TODAY(),D74<'TTP Tracker 26'!$C$4),1,0) -> 0 | C74: =if('TTP Tracker 26'!$B$2="MONTHLY TOTAL",$A74,$B74) -> 0 | D74: 45947 | E74: Friday | F74: =if(E74="Monday",1,0)*if(C74=1,1,0) -> 0 | G74: =if('TTP Tracker 26'!$B$2="MONTHLY TOTAL",$A74,$B74) -> 0
A75: =IF(and(D75>='TTP Tracker 26'!$C$3,D75<'TTP Tracker 26'!$C$4),1,0) -> 0 | B75: =if(and(D75>TODAY(),D75<'TTP Tracker 26'!$C$4),1,0) -> 0 | C75: =if('TTP Tracker 26'!$B$2="MONTHLY TOTAL",$A75,$B75) -> 0 | D75: 45948 | E75: Saturday | F75: =if(E75="Monday",1,0)*if(C75=1,1,0) -> 0 | K75: =if('TTP Tracker 26'!$B$2="MONTHLY TOTAL",$A75,$B75) -> 0
A76: =IF(and(D76>='TTP Tracker 26'!$C$3,D76<'TTP Tracker 26'!$C$4),1,0) -> 0 | B76: =if(and(D76>TODAY(),D76<'TTP Tracker 26'!$C$4),1,0) -> 0 | C76: =if('TTP Tracker 26'!$B$2="MONTHLY TOTAL",$A76,$B76) -> 0 | D76: 45949 | E76: Sunday | F76: =if(E76="Monday",1,0)*if(C76=1,1,0) -> 0
A77: =IF(and(D77>='TTP Tracker 26'!$C$3,D77<'TTP Tracker 26'!$C$4),1,0) -> 0 | B77: =if(and(D77>TODAY(),D77<'TTP Tracker 26'!$C$4),1,0) -> 0 | C77: =if('TTP Tracker 26'!$B$2="MONTHLY TOTAL",$A77,$B77) -> 0 | D77: 45950 | E77: Monday | F77: =if(E77="Monday",1,0)*if(C77=1,1,0) -> 0 | L77: =if('TTP Tracker 26'!$B$2="MONTHLY TOTAL",$A77,$B77) -> 0 | M77: =if('TTP Tracker 26'!$B$2="MONTHLY TOTAL",$A77,$B77) -> 0
A78: =IF(and(D78>='TTP Tracker 26'!$C$3,D78<'TTP Tracker 26'!$C$4),1,0) -> 0 | B78: =if(and(D78>TODAY(),D78<'TTP Tracker 26'!$C$4),1,0) -> 0 | C78: =if('TTP Tracker 26'!$B$2="MONTHLY TOTAL",$A78,$B78) -> 0 | D78: 45951 | E78: Tuesday | F78: =if(E78="Monday",1,0)*if(C78=1,1,0) -> 0
A79: =IF(and(D79>='TTP Tracker 26'!$C$3,D79<'TTP Tracker 26'!$C$4),1,0) -> 0 | B79: =if(and(D79>TODAY(),D79<'TTP Tracker 26'!$C$4),1,0) -> 0 | C79: =if('TTP Tracker 26'!$B$2="MONTHLY TOTAL",$A79,$B79) -> 0 | D79: 45952 | E79: Wednesday | F79: =if(E79="Monday",1,0)*if(C79=1,1,0) -> 0
A80: =IF(and(D80>='TTP Tracker 26'!$C$3,D80<'TTP Tracker 26'!$C$4),1,0) -> 0 | B80: =if(and(D80>TODAY(),D80<'TTP Tracker 26'!$C$4),1,0) -> 0 | C80: =if('TTP Tracker 26'!$B$2="MONTHLY TOTAL",$A80,$B80) -> 0 | D80: 45953 | E80: Thursday | F80: =if(E80="Monday",1,0)*if(C80=1,1,0) -> 0
A81: =IF(and(D81>='TTP Tracker 26'!$C$3,D81<'TTP Tracker 26'!$C$4),1,0) -> 0 | B81: =if(and(D81>TODAY(),D81<'TTP Tracker 26'!$C$4),1,0) -> 0 | C81: =if('TTP Tracker 26'!$B$2="MONTHLY TOTAL",$A81,$B81) -> 0 | D81: 45954 | E81: Friday | F81: =if(E81="Monday",1,0)*if(C81=1,1,0) -> 0 | I81: =if('TTP Tracker 26'!$B$2="MONTHLY TOTAL",$A81,$B81) -> 0
A82: =IF(and(D82>='TTP Tracker 26'!$C$3,D82<'TTP Tracker 26'!$C$4),1,0) -> 0 | B82: =if(and(D82>TODAY(),D82<'TTP Tracker 26'!$C$4),1,0) -> 0 | C82: =if('TTP Tracker 26'!$B$2="MONTHLY TOTAL",$A82,$B82) -> 0 | D82: 45955 | E82: Saturday | F82: =if(E82="Monday",1,0)*if(C82=1,1,0) -> 0
A83: =IF(and(D83>='TTP Tracker 26'!$C$3,D83<'TTP Tracker 26'!$C$4),1,0) -> 0 | B83: =if(and(D83>TODAY(),D83<'TTP Tracker 26'!$C$4),1,0) -> 0 | C83: =if('TTP Tracker 26'!$B$2="MONTHLY TOTAL",$A83,$B83) -> 0 | D83: 45956 | E83: Sunday | F83: =if(E83="Monday",1,0)*if(C83=1,1,0) -> 0
A84: =IF(and(D84>='TTP Tracker 26'!$C$3,D84<'TTP Tracker 26'!$C$4),1,0) -> 0 | B84: =if(and(D84>TODAY(),D84<'TTP Tracker 26'!$C$4),1,0) -> 0 | C84: =if('TTP Tracker 26'!$B$2="MONTHLY TOTAL",$A84,$B84) -> 0 | D84: 45957 | E84: Monday | F84: =if(E84="Monday",1,0)*if(C84=1,1,0) -> 0 | M84: =if('TTP Tracker 26'!$B$2="MONTHLY TOTAL",$A84,$B84) -> 0
A85: =IF(and(D85>='TTP Tracker 26'!$C$3,D85<'TTP Tracker 26'!$C$4),1,0) -> 0 | B85: =if(and(D85>TODAY(),D85<'TTP Tracker 26'!$C$4),1,0) -> 0 | C85: =if('TTP Tracker 26'!$B$2="MONTHLY TOTAL",$A85,$B85) -> 0 | D85: 45958 | E85: Tuesday | F85: =if(E85="Monday",1,0)*if(C85=1,1,0) -> 0
A86: =IF(and(D86>='TTP Tracker 26'!$C$3,D86<'TTP Tracker 26'!$C$4),1,0) -> 0 | B86: =if(and(D86>TODAY(),D86<'TTP Tracker 26'!$C$4),1,0) -> 0 | C86: =if('TTP Tracker 26'!$B$2="MONTHLY TOTAL",$A86,$B86) -> 0 | D86: 45959 | E86: Wednesday | F86: =if(E86="Monday",1,0)*if(C86=1,1,0) -> 0
A87: =IF(and(D87>='TTP Tracker 26'!$C$3,D87<'TTP Tracker 26'!$C$4),1,0) -> 0 | B87: =if(and(D87>TODAY(),D87<'TTP Tracker 26'!$C$4),1,0) -> 0 | C87: =if('TTP Tracker 26'!$B$2="MONTHLY TOTAL",$A87,$B87) -> 0 | D87: 45960 | E87: Thursday | F87: =if(E87="Monday",1,0)*if(C87=1,1,0) -> 0
A88: =IF(and(D88>='TTP Tracker 26'!$C$3,D88<'TTP Tracker 26'!$C$4),1,0) -> 0 | B88: =if(and(D88>TODAY(),D88<'TTP Tracker 26'!$C$4),1,0) -> 0 | C88: =if('TTP Tracker 26'!$B$2="MONTHLY TOTAL",$A88,$B88) -> 0 | D88: 45961 | E88: Friday | F88: =if(E88="Monday",1,0)*if(C88=1,1,0) -> 0 | G88: =if('TTP Tracker 26'!$B$2="MONTHLY TOTAL",$A88,$B88) -> 0
A89: =IF(and(D89>='TTP Tracker 26'!$C$3,D89<'TTP Tracker 26'!$C$4),1,0) -> 0 | B89: =if(and(D89>TODAY(),D89<'TTP Tracker 26'!$C$4),1,0) -> 0 | C89: =if('TTP Tracker 26'!$B$2="MONTHLY TOTAL",$A89,$B89) -> 0 | D89: 45962 | E89: Saturday | F89: =if(E89="Monday",1,0)*if(C89=1,1,0) -> 0 | K89: =if('TTP Tracker 26'!$B$2="MONTHLY TOTAL",$A89,$B89) -> 0
A90: =IF(and(D90>='TTP Tracker 26'!$C$3,D90<'TTP Tracker 26'!$C$4),1,0) -> 0 | B90: =if(and(D90>TODAY(),D90<'TTP Tracker 26'!$C$4),1,0) -> 0 | C90: =if('TTP Tracker 26'!$B$2="MONTHLY TOTAL",$A90,$B90) -> 0 | D90: 45963 | E90: Sunday | F90: =if(E90="Monday",1,0)*if(C90=1,1,0) -> 0
A91: =IF(and(D91>='TTP Tracker 26'!$C$3,D91<'TTP Tracker 26'!$C$4),1,0) -> 0 | B91: =if(and(D91>TODAY(),D91<'TTP Tracker 26'!$C$4),1,0) -> 0 | C91: =if('TTP Tracker 26'!$B$2="MONTHLY TOTAL",$A91,$B91) -> 0 | D91: 45964 | E91: Monday | F91: =if(E91="Monday",1,0)*if(C91=1,1,0) -> 0 | L91: =if('TTP Tracker 26'!$B$2="MONTHLY TOTAL",$A91,$B91) -> 0 | M91: =if('TTP Tracker 26'!$B$2="MONTHLY TOTAL",$A91,$B91) -> 0
A92: =IF(and(D92>='TTP Tracker 26'!$C$3,D92<'TTP Tracker 26'!$C$4),1,0) -> 0 | B92: =if(and(D92>TODAY(),D92<'TTP Tracker 26'!$C$4),1,0) -> 0 | C92: =if('TTP Tracker 26'!$B$2="MONTHLY TOTAL",$A92,$B92) -> 0 | D92: 45965 | E92: Tuesday | F92: =if(E92="Monday",1,0)*if(C92=1,1,0) -> 0
A93: =IF(and(D93>='TTP Tracker 26'!$C$3,D93<'TTP Tracker 26'!$C$4),1,0) -> 0 | B93: =if(and(D93>TODAY(),D93<'TTP Tracker 26'!$C$4),1,0) -> 0 | C93: =if('TTP Tracker 26'!$B$2="MONTHLY TOTAL",$A93,$B93) -> 0 | D93: 45966 | E93: Wednesday | F93: =if(E93="Monday",1,0)*if(C93=1,1,0) -> 0
A94: =IF(and(D94>='TTP Tracker 26'!$C$3,D94<'TTP Tracker 26'!$C$4),1,0) -> 0 | B94: =if(and(D94>TODAY(),D94<'TTP Tracker 26'!$C$4),1,0) -> 0 | C94: =if('TTP Tracker 26'!$B$2="MONTHLY TOTAL",$A94,$B94) -> 0 | D94: 45967 | E94: Thursday | F94: =if(E94="Monday",1,0)*if(C94=1,1,0) -> 0
A95: =IF(and(D95>='TTP Tracker 26'!$C$3,D95<'TTP Tracker 26'!$C$4),1,0) -> 0 | B95: =if(and(D95>TODAY(),D95<'TTP Tracker 26'!$C$4),1,0) -> 0 | C95: =if('TTP Tracker 26'!$B$2="MONTHLY TOTAL",$A95,$B95) -> 0 | D95: 45968 | E95: Friday | F95: =if(E95="Monday",1,0)*if(C95=1,1,0) -> 0 | I95: =if('TTP Tracker 26'!$B$2="MONTHLY TOTAL",$A95,$B95) -> 0
A96: =IF(and(D96>='TTP Tracker 26'!$C$3,D96<'TTP Tracker 26'!$C$4),1,0) -> 0 | B96: =if(and(D96>TODAY(),D96<'TTP Tracker 26'!$C$4),1,0) -> 0 | C96: =if('TTP Tracker 26'!$B$2="MONTHLY TOTAL",$A96,$B96) -> 0 | D96: 45969 | E96: Saturday | F96: =if(E96="Monday",1,0)*if(C96=1,1,0) -> 0
A97: =IF(and(D97>='TTP Tracker 26'!$C$3,D97<'TTP Tracker 26'!$C$4),1,0) -> 0 | B97: =if(and(D97>TODAY(),D97<'TTP Tracker 26'!$C$4),1,0) -> 0 | C97: =if('TTP Tracker 26'!$B$2="MONTHLY TOTAL",$A97,$B97) -> 0 | D97: 45970 | E97: Sunday | F97: =if(E97="Monday",1,0)*if(C97=1,1,0) -> 0
A98: =IF(and(D98>='TTP Tracker 26'!$C$3,D98<'TTP Tracker 26'!$C$4),1,0) -> 0 | B98: =if(and(D98>TODAY(),D98<'TTP Tracker 26'!$C$4),1,0) -> 0 | C98: =if('TTP Tracker 26'!$B$2="MONTHLY TOTAL",$A98,$B98) -> 0 | D98: 45971 | E98: Monday | F98: =if(E98="Monday",1,0)*if(C98=1,1,0) -> 0 | M98: =if('TTP Tracker 26'!$B$2="MONTHLY TOTAL",$A98,$B98) -> 0
A99: =IF(and(D99>='TTP Tracker 26'!$C$3,D99<'TTP Tracker 26'!$C$4),1,0) -> 0 | B99: =if(and(D99>TODAY(),D99<'TTP Tracker 26'!$C$4),1,0) -> 0 | C99: =if('TTP Tracker 26'!$B$2="MONTHLY TOTAL",$A99,$B99) -> 0 | D99: 45972 | E99: Tuesday | F99: =if(E99="Monday",1,0)*if(C99=1,1,0) -> 0
A100: =IF(and(D100>='TTP Tracker 26'!$C$3,D100<'TTP Tracker 26'!$C$4),1,0) -> 0 | B100: =if(and(D100>TODAY(),D100<'TTP Tracker 26'!$C$4),1,0) -> 0 | C100: =if('TTP Tracker 26'!$B$2="MONTHLY TOTAL",$A100,$B100) -> 0 | D100: 45973 | E100: Wednesday | F100: =if(E100="Monday",1,0)*if(C100=1,1,0) -> 0
...

Sheet January
B1: JANUARY | J1: JAN
B3: SUNDAY | C3: MONDAY | D3: TUESDAY | E3: WEDNESDAY | F3: THURSDAY | G3: FRIDAY | H3: SATURDAY
B4: =Year!B4 | C4: =Year!C4 | D4: =Year!D4 | E4: =Year!E4 | F4: =Year!F4 -> 1 | G4: =Year!G4 -> 2 | H4: =Year!H4 -> 3
B6: =Year!B5 -> 4 | C6: =Year!C5 -> 5 | D6: =Year!D5 -> 6 | E6: =Year!E5 -> 7 | F6: =Year!F5 -> 8 | G6: =Year!G5 -> 9 | H6: =Year!H5 -> 10
E7: FP Start | G7: PA Rushing | H7: Arena Tourney
B8: =Year!B6 -> 11 | C8: =Year!C6 -> 12 | D8: =Year!D6 -> 13 | E8: =Year!E6 -> 14 | F8: =Year!F6 -> 15 | G8: =Year!G6 -> 16 | H8: =Year!H6 -> 17
B9: Rush LB | C9: Tourney LB | D9: Unlimited | G9: PA Passing
B10: =Year!B7 -> 18 | C10: =Year!C7 -> 19 | D10: =Year!D7 -> 20 | E10: =Year!E7 -> 21 | F10: =Year!F7 -> 22 | G10: =Year!G7 -> 23 | H10: =Year!H7 -> 24
B11: Pass LB | C11: Unlimited | G11: PA Rushing | H11: Arena Tourney
B12: =Year!B8 -> 25 | C12: =Year!C8 -> 26 | D12: =Year!D8 -> 27 | E12: =Year!E8 -> 28 | F12: =Year!F8 -> 29 | G12: =Year!G8 -> 30 | H12: =Year!H8 -> 31
B13: Rush LB | C13: Tourney LB | D13: Unlimited | G13: PA Passing
B14: =Year!B9 | C14: =Year!C9 | D14: =Year!D9 | E14: =Year!E9 | F14: =Year!F9 | G14: =Year!G9 | H14: =Year!H9
B16: PA Rushing | C16: Leaderboard | D16: PA Passing | E16: Leaderboard | F16: Tournaments | G16: Leaderboard | H16: Unlimited
B17: 2 | C17: 2 | D17: 2 | E17: 2 | F17: 2 | G17: 2 | H17: 4

Sheet February
B1: FEBRUARY | J1: FEB
B3: SUNDAY | C3: MONDAY | D3: TUESDAY | E3: WEDNESDAY | F3: THURSDAY | G3: FRIDAY | H3: SATURDAY
B4: =Year!J4 -> 1 | C4: =Year!K4 -> 2 | D4: =Year!L4 -> 3 | E4: =Year!M4 -> 4 | F4: =Year!N4 -> 5 | G4: =Year!O4 -> 6 | H4: =Year!P4 -> 7
B6: =Year!J5 -> 8 | C6: =Year!K5 -> 9 | D6: =Year!L5 -> 10 | E6: =Year!M5 -> 11 | F6: =Year!N5 -> 12 | G6: =Year!O5 -> 13 | H6: =Year!P5 -> 14
B7: Pass LB | C7: Unlimited | G7: FP End
B8: =Year!J6 -> 15 | C8: =Year!K6 -> 16 | D8: =Year!L6 -> 17 | E8: =Year!M6 -> 18 | F8: =Year!N6 -> 19 | G8: =Year!O6 -> 20 | H8: =Year!P6 -> 21
B10: =Year!J7 -> 22 | C10: =Year!K7 -> 23 | D10: =Year!L7 -> 24 | E10: =Year!M7 -> 25 | F10: =Year!N7 -> 26 | G10: =Year!O7 -> 27 | H10: =Year!P7 -> 28
B12: =Year!J8 | C12: =Year!K8 | D12: =Year!L8 | E12: =Year!M8 | F12: =Year!N8 | G12: =Year!O8 | H12: =Year!P8
B14: =Year!J9 | C14: =Year!K9 | D14: =Year!L9 | E14: =Year!M9 | F14: =Year!N9 | G14: =Year!O9 | H14: =Year!P9
B17: NOTES

Sheet Leaderboards
E1: LvL Leaderboards | J1: Draft Leaderboards | N1: Packs | O1: Price | P1: TTP | Q1: Coins
E2: RANK | F2: REWARD | G2: W | H2: L | J2: Milestones | K2: TTP | L2: Coins | N2: 2nd Quarter I | O2: 1.99 | P2: 840
E3: HOF | 1 | F3: 35000 | G3: 630 | H3: 310 | K3: 150 | N3: 2nd Quarter II | O3: 9.99 | P3: 4500
E4: HOF | 2 | F4: 29700 | G4: 630 | H4: 310 | K4: 150 | N4: 2nd Quarter III | O4: 19.99 | P4: 7200
E5: HOF | 3 | F5: 25200 | G5: 630 | H5: 310 | K5: 150 | N5: 2nd Quarter IV | O5: 29.99 | P5: 11250
E6: HOF | 4 - 10 | F6: 21400 | G6: 630 | H6: 310 | K6: 150 | N6: 3rd Quarter I | O6: 0.99 | P6: 800
E7: HOF | 11 - 15 | F7: 18200 | G7: 630 | H7: 310 | K7: 150 | L7: 5000 | N7: 3rd Quarter II | O7: 4.99 | P7: 3300
E8: HOF | 16+ | F8: 14600 | G8: 630 | H8: 310 | K8: 250 | N8: 3rd Quarter III | O8: 14.99 | P8: 8400
E9: Elite I | 1 | F9: 21000 | G9: 570 | H9: 290 | K9: 250 | N9: 3rd Quarter IV | O9: 24.99 | P9: 12750
E10: Elite I | 2 | F10: 17800 | G10: 570 | H10: 290 | K10: 250 | N10: 4th Quarter I | O10: 1.99 | P10: 1400 | Q10: 70000
E11: Elite I | 3 | F11: 15100 | G11: 570 | H11: 290 | K11: 250 | N11: 4th Quarter II | O11: 9.99 | P11: 6500 | Q11: 175000
E12: Elite I | 4 - 10 | F12: 12900 | G12: 570 | H12: 290 | K12: 250 | L12: 10000 | N12: 4th Quarter III | O12: 19.99 | P12: 9600 | Q12: 120000
E13: Elite I | 11 - 25 | F13: 10900 | G13: 570 | H13: 290 | K13: 350 | N13: 4th Quarter IV | O13: 29.99 | P13: 15000 | Q13: 0
E14: Elite I | 26 - 50 | F14: 9320 | G14: 570 | H14: 290 | K14: 350 | N14: BITG I | O14: 19.99 | P14: 7800 | Q14: 210000
E15: Elite I | 51+ | F15: 7460 | G15: 570 | H15: 290 | K15: 350 | N15: BITG II | O15: 9.99 | P15: 5000 | Q15: 250000
E16: Elite II | 1 | F16: 14100 | G16: 520 | H16: 260 | K16: 350 | N16: BITG III | O16: 4.99 | P16: 2100 | Q16: 195000
A17: Arena Tournaments | E17: Elite II | 2 | F17: 12700 | G17: 520 | H17: 260 | K17: 350 | L17: 15000 | N17: BITG IV | O17: 0.99 | P17: 400 | Q17: 80000
A18: Milestones | B18: TTP | C18: Coins | E18: Elite II | 3 | F18: 11500 | G18: 520 | H18: 260 | J18: Rank | K18: TTP | L18: Coins
A19: B3 | B19: 200 | E19: Elite II | 4 - 10 | F19: 10300 | G19: 520 | H19: 260 | J19: 1 | K19: 15000 | L19: 400000
A20: B2 | B20: 200 | E20: Elite II | 11 - 25 | F20: 9310 | G20: 520 | H20: 260 | J20: 2 | K20: 12500 | L20: 300000
A21: B1 | B21: 200 | E21: Elite II | 26 - 50 | F21: 8380 | G21: 520 | H21: 260 | J21: 3 | K21: 10000 | L21: 240000
A22: S3 | B22: 200 | C22: 5000 | E22: Elite II | 51 - 100 | F22: 7540 | G22: 520 | H22: 260 | J22: 4 to 10 | K22: 8000 | L22: 200000
A23: S2 | B23: 240 | E23: Elite II | 101+ | F23: 6410 | G23: 520 | H23: 260 | J23: 11 to 25 | K23: 6500 | L23: 150000
A24: S1 | B24: 240 | E24: Elite III | 1 | F24: 11300 | G24: 470 | H24: 240 | J24: 26 to 50 | K24: 5000 | L24: 120000
A25: G3 | B25: 240 | C25: 6000 | E25: Elite III | 2 | F25: 10200 | G25: 470 | H25: 240 | J25: 51 to 100 | K25: 4000 | L25: 100000
A26: G2 | B26: 300 | E26: Elite III | 3 | F26: 9220 | G26: 470 | H26: 240 | J26: 101 to 250 | K26: 3000 | L26: 80000
A27: G1 | B27: 300 | E27: Elite III | 4 - 10 | F27: 8300 | G27: 470 | H27: 240 | J27: 251 to 500 | K27: 2000 | L27: 70000
A28: E3 | B28: 300 | C28: 7500 | E28: Elite III | 11 - 25 | F28: 7470 | G28: 470 | H28: 240 | J28: 501 to 1000 | K28: 1500 | L28: 60000
A29: E2 | B29: 400 | E29: Elite III | 26 - 50 | F29: 6720 | G29: 470 | H29: 240 | J29: 1001 to 2000 | K29: 1250 | L29: 50000
A30: E1 | B30: 500 | E30: Elite III | 51 - 100 | F30: 6050 | G30: 470 | H30: 240
A31: HOF | B31: 600 | C31: 15000 | E31: Elite III | 101 - 200 | F31: 5440 | G31: 470 | H31: 240
E32: Elite III | 201+ | F32: 4630 | G32: 470 | H32: 240
A33: A1 Rank | B33: TTP | C33: Coins | E33: Gold I | 1 | F33: 9130 | G33: 430 | H33: 210
A34: 1 | B34: 6000 | C34: 150000 | E34: Gold I | 2 | F34: 8210 | G34: 430 | H34: 210
A35: 2 | B35: 4500 | C35: 112500 | E35: Gold I | 3 | F35: 7390 | G35: 430 | H35: 210
A36: 3 | B36: 3600 | C36: 90000 | E36: Gold I | 4 - 10 | F36: 6650 | G36: 430 | H36: 210
A37: 10 | B37: 3000 | C37: 75000 | E37: Gold I | 11 - 25 | F37: 5990 | G37: 430 | H37: 210
A38: 25 | B38: 2400 | C38: 60000 | E38: Gold I | 26 - 50 | F38: 5390 | G38: 430 | H38: 210
A39: 50 | B39: 2100 | C39: 52500 | E39: Gold I | 51 - 100 | F39: 4850 | G39: 430 | H39: 210
A40: 100 | B40: 1800 | C40: 45000 | E40: Gold I | 101 - 250 | F40: 4370 | G40: 430 | H40: 210
A41: 250 | B41: 1500 | C41: 37500 | E41: Gold I | 251 - 500 | F41: 3930 | G41: 430 | H41: 210
A42: 500 | B42: 1200 | C42: 30000 | E42: Gold I | 501+ | F42: 3340 | G42: 430 | H42: 210
A43: 1000 | B43: 900 | C43: 22500
A44: 2000 | B44: 780 | C44: 19500 | E44: Daily Arena Leaderboards
A45: ="" | B45: 0 | C45: 0 | E45: Rank | F45: TTP
E46: HOF | 1 | F46: 8280
A47: A2 Rank | B47: TTP | C47: Coins | E47: HOF | 2 | F47: 5382
A48: 1 | B48: 8000 | C48: 200000 | E48: HOF | 3 | F48: 4140
A49: 2 | B49: 6000 | C49: 150000 | E49: HOF | 4-10 | F49: 3312
A50: 3 | B50: 4800 | C50: 120000 | E50: HOF | 11-25 | F50: 3144
A51: 10 | B51: 4000 | C51: 100000 | E51: HOF | 26-50 | F51: 2982
A52: 25 | B52: 3200 | C52: 80000 | E52: HOF | 51-75 | F52: 2814
A53: 50 | B53: 2800 | C53: 70000 | E53: HOF | 76-100 | F53: 2568
A54: 100 | B54: 2400 | C54: 60000 | E54: HOF | 101-250 | F54: 2400
A55: 250 | B55: 2000 | C55: 50000 | E55: HOF | 251-500 | F55: 2316
A56: 500 | B56: 1600 | C56: 40000 | E56: HOF | 501-1000 | F56: 2238
A57: 1000 | B57: 1200 | C57: 30000 | E57: Elite I | 1 | F57: 6360
A58: 2000 | B58: 1040 | C58: 26000 | E58: Elite I | 2 | F58: 4134
E59: Elite I | 3 | F59: 3180
A60: A3 Rank | B60: TTP | C60: Coins | E60: Elite I | 4-10 | F60: 2544
A61: 1 | B61: 15000 | C61: 375000 | E61: Elite I | 11-25 | F61: 2418
A62: 2 | B62: 12000 | C62: 300000 | E62: Elite I | 26-50 | F62: 2292
A63: 3 | B63: 10000 | C63: 250000 | E63: Elite I | 51-75 | F63: 2160
A64: 10 | B64: 8000 | C64: 187500 | E64: Elite I | 76-100 | F64: 1974
A65: 25 | B65: 7000 | C65: 150000 | E65: Elite I | 101-250 | F65: 1842
A66: 50 | B66: 6000 | C66: 125000 | E66: Elite I | 251-500 | F66: 1782
A67: 100 | B67: 5000 | C67: 100000 | E67: Elite I | 501-1000 | F67: 1716
A68: 250 | B68: 4000 | C68: 87500 | E68: Elite II | 1 | F68: 4890
A69: 500 | B69: 3000 | C69: 75000 | E69: Elite II | 2 | F69: 3180
A70: 1000 | B70: 2500 | C70: 62500 | E70: Elite II | 3 | F70: 2448
A71: 2000 | B71: 2000 | C71: 50000 | E71: Elite II | 4-10 | F71: 1956
E72: Elite II | 11-25 | F72: 1860
A73: A4 Rank | B73: TTP | C73: Coins | E73: Elite II | 26-50 | F73: 1758
A74: 1 | B74: 20000 | C74: 500000 | E74: Elite II | 51-75 | F74: 1662
A75: 2 | B75: 16000 | C75: 375000 | E75: Elite II | 76-100 | F75: 1518
A76: 3 | B76: 14000 | C76: 300000 | E76: Elite II | 101-250 | F76: 1416
A77: 10 | B77: 12000 | C77: 250000 | E77: Elite II | 251-500 | F77: 1368
A78: 25 | B78: 10000 | C78: 187500 | E78: Elite II | 501-1000 | F78: 1320
A79: 50 | B79: 8000 | C79: 150000 | E79: Elite III | 1 | F79: 3750
A80: 100 | B80: 6000 | C80: 125000 | E80: Elite III | 2 | F80: 2436
A81: 250 | B81: 5000 | C81: 100000 | E81: Elite III | 3 | F81: 1878
A82: 500 | B82: 4000 | C82: 87500 | E82: Elite III | 4-10 | F82: 1500
A83: 1000 | B83: 3000 | C83: 75000 | E83: Elite III | 11-25 | F83: 1428
A84: 2000 | B84: 2500 | C84: 62500 | E84: Elite III | 26-50 | F84: 1350
E85: Elite III | 51-75 | F85: 1278
E86: Elite III | 76-100 | F86: 1164
E87: Elite III | 101-250 | F87: 1086
E88: Elite III | 251-500 | F88: 1050
E89: Elite III | 501-1000 | F89: 1014
E90: Gold I | 1 | F90: 2880
E91: Gold I | 2 | F91: 1872
E92: Gold I | 3 | F92: 1440
E93: Gold I | 4-10 | F93: 1152
E94: Gold I | 11-25 | F94: 1092
E95: Gold I | 26-50 | F95: 1038
E96: Gold I | 51-75 | F96: 978
... E100: Gold I | 501-1000 | F100: 780

Sheet March
B1: MARCH | J1: MAR
B3: SUNDAY | C3: MONDAY | D3: TUESDAY | E3: WEDNESDAY | F3: THURSDAY | G3: FRIDAY | H3: SATURDAY
B4: =Year!R4 -> 1 | C4: =Year!S4 -> 2 | D4: =Year!T4 -> 3 | E4: =Year!U4 -> 4 | F4: =Year!V4 -> 5 | G4: =Year!W4 -> 6 | H4: =Year!X4 -> 7
B6: =Year!R5 -> 8 | C6: =Year!S5 -> 9 | D6: =Year!T5 -> 10 | E6: =Year!U5 -> 11 | F6: =Year!V5 -> 12 | G6: =Year!W5 -> 13 | H6: =Year!X5 -> 14
B8: =Year!R6 -> 15 | C8: =Year!S6 -> 16 | D8: =Year!T6 -> 17 | E8: =Year!U6 -> 18 | F8: =Year!V6 -> 19 | G8: =Year!W6 -> 20 | H8: =Year!X6 -> 21
B10: =Year!R7 -> 22 | C10: =Year!S7 -> 23 | D10: =Year!T7 -> 24 | E10: =Year!U7 -> 25 | F10: =Year!V7 -> 26 | G10: =Year!W7 -> 27 | H10: =Year!X7 -> 28
B12: =Year!R8 -> 29 | C12: =Year!S8 -> 30 | D12: =Year!T8 -> 31 | E12: =Year!U8 | F12: =Year!V8 | G12: =Year!W8 | H12: =Year!X8
B17: NOTES

Sheet April
B1: APRIL | J1: APR
B3: SUNDAY | C3: MONDAY | D3: TUESDAY | E3: WEDNESDAY | F3: THURSDAY | G3: FRIDAY | H3: SATURDAY
B4: =Year!B13 | C4: =Year!C13 | D4: =Year!D13 | E4: =Year!E13 -> 1 | F4: =Year!F13 -> 2 | G4: =Year!G13 -> 3 | H4: =Year!H13 -> 4
B6: =Year!B14 -> 5 | C6: =Year!C14 -> 6 | D6: =Year!D14 -> 7 | E6: =Year!E14 -> 8 | F6: =Year!F14 -> 9 | G6: =Year!G14 -> 10 | H6: =Year!H14 -> 11
B8: =Year!B15 -> 12 | C8: =Year!C15 -> 13 | D8: =Year!D15 -> 14 | E8: =Year!E15 -> 15 | F8: =Year!F15 -> 16 | G8: =Year!G15 -> 17 | H8: =Year!H15 -> 18
B10: =Year!B16 -> 19 | C10: =Year!C16 -> 20 | D10: =Year!D16 -> 21 | E10: =Year!E16 -> 22 | F10: =Year!F16 -> 23 | G10: =Year!G16 -> 24 | H10: =Year!H16 -> 25
B12: =Year!B17 -> 26 | C12: =Year!C17 -> 27 | D12: =Year!D17 -> 28 | E12: =Year!E17 -> 29 | F12: =Year!F17 -> 30 | G12: =Year!G17 | H12: =Year!H17
B14: =Year!B18 | C14: =Year!C18 | D14: =Year!D18 | E14: =Year!E18 | F14: =Year!F18 | G14: =Year!G18 | H14: =Year!H18
B17: NOTES

Sheet May
B1: MAY | J1: MAY
B3: SUNDAY | C3: MONDAY | D3: TUESDAY | E3: WEDNESDAY | F3: THURSDAY | G3: FRIDAY | H3: SATURDAY
B4: =Year!J13 | C4: =Year!K13 | D4: =Year!L13 | E4: =Year!M13 | F4: =Year!N13 | G4: =Year!O13 -> 1 | H4: =Year!P13 -> 2
B6: =Year!J14 -> 3 | C6: =Year!K14 -> 4 | D6: =Year!L14 -> 5 | E6: =Year!M14 -> 6 | F6: =Year!N14 -> 7 | G6: =Year!O14 -> 8 | H6: =Year!P14 -> 9
B8: =Year!J15 -> 10 | C8: =Year!K15 -> 11 | D8: =Year!L15 -> 12 | E8: =Year!M15 -> 13 | F8: =Year!N15 -> 14 | G8: =Year!O15 -> 15 | H8: =Year!P15 -> 16
B10: =Year!J16 -> 17 | C10: =Year!K16 -> 18 | D10: =Year!L16 -> 19 | E10: =Year!M16 -> 20 | F10: =Year!N16 -> 21 | G10: =Year!O16 -> 22 | H10: =Year!P16 -> 23
B12: =Year!J17 -> 24 | C12: =Year!K17 -> 25 | D12: =Year!L17 -> 26 | E12: =Year!M17 -> 27 | F12: =Year!N17 -> 28 | G12: =Year!O17 -> 29 | H12: =Year!P17 -> 30
B14: =Year!J18 -> 31 | C14: =Year!K18 | D14: =Year!L18 | E14: =Year!M18 | F14: =Year!N18 | G14: =Year!O18 | H14: =Year!P18
B17: NOTES

Sheet June
B1: JUNE | J1: JUN
B3: SUNDAY | C3: MONDAY | D3: TUESDAY | E3: WEDNESDAY | F3: THURSDAY | G3: FRIDAY | H3: SATURDAY
B4: =Year!R13 | C4: =Year!S13 -> 1 | D4: =Year!T13 -> 2 | E4: =Year!U13 -> 3 | F4: =Year!V13 -> 4 | G4: =Year!W13 -> 5 | H4: =Year!X13 -> 6
B6: =Year!R14 -> 7 | C6: =Year!S14 -> 8 | D6: =Year!T14 -> 9 | E6: =Year!U14 -> 10 | F6: =Year!V14 -> 11 | G6: =Year!W14 -> 12 | H6: =Year!X14 -> 13
B8: =Year!R15 -> 14 | C8: =Year!S15 -> 15 | D8: =Year!T15 -> 16 | E8: =Year!U15 -> 17 | F8: =Year!V15 -> 18 | G8: =Year!W15 -> 19 | H8: =Year!X15 -> 20
B10: =Year!R16 -> 21 | C10: =Year!S16 -> 22 | D10: =Year!T16 -> 23 | E10: =Year!U16 -> 24 | F10: =Year!V16 -> 25 | G10: =Year!W16 -> 26 | H10: =Year!X16 -> 27
B12: =Year!R17 -> 28 | C12: =Year!S17 -> 29 | D12: =Year!T17 -> 30 | E12: =Year!U17 | F12: =Year!V17 | G12: =Year!W17 | H12: =Year!X17
B14: =Year!R18 | C14: =Year!S18 | D14: =Year!T18 | E14: =Year!U18 | F14: =Year!V18 | G14: =Year!W18 | H14: =Year!X18
B17: NOTES

Sheet July
B1: JULY | J1: JUL
B3: SUNDAY | C3: MONDAY | D3: TUESDAY | E3: WEDNESDAY | F3: THURSDAY | G3: FRIDAY | H3: SATURDAY
B4: =Year!B22 | C4: =Year!C22 | D4: =Year!D22 | E4: =Year!E22 -> 1 | F4: =Year!F22 -> 2 | G4: =Year!G22 -> 3 | H4: =Year!H22 -> 4
B6: =Year!B23 -> 5 | C6: =Year!C23 -> 6 | D6: =Year!D23 -> 7 | E6: =Year!E23 -> 8 | F6: =Year!F23 -> 9 | G6: =Year!G23 -> 10 | H6: =Year!H23 -> 11
B8: =Year!B24 -> 12 | C8: =Year!C24 -> 13 | D8: =Year!D24 -> 14 | E8: =Year!E24 -> 15 | F8: =Year!F24 -> 16 | G8: =Year!G24 -> 17 | H8: =Year!H24 -> 18
B10: =Year!B25 -> 19 | C10: =Year!C25 -> 20 | D10: =Year!D25 -> 21 | E10: =Year!E25 -> 22 | F10: =Year!F25 -> 23 | G10: =Year!G25 -> 24 | H10: =Year!H25 -> 25
B12: =Year!B26 -> 26 | C12: =Year!C26 -> 27 | D12: =Year!D26 -> 28 | E12: =Year!E26 -> 29 | F12: =Year!F26 -> 30 | G12: =Year!G26 -> 31 | H12: =Year!H26
B14: =Year!B27 | C14: =Year!C27 | D14: =Year!D27 | E14: =Year!E27 | F14: =Year!F27 | G14: =Year!G27 | H14: =Year!H27
B17: NOTES

Sheet August
B1: AUGUST | J1: AUG
B3: SUNDAY | C3: MONDAY | D3: TUESDAY | E3: WEDNESDAY | F3: THURSDAY | G3: FRIDAY | H3: SATURDAY
B4: =Year!J22 | C4: =Year!K22 | D4: =Year!L22 | E4: =Year!M22 | F4: =Year!N22 | G4: =Year!O22 | H4: =Year!P22 -> 1
B6: =Year!J23 -> 2 | C6: =Year!K23 -> 3 | D6: =Year!L23 -> 4 | E6: =Year!M23 -> 5 | F6: =Year!N23 -> 6 | G6: =Year!O23 -> 7 | H6: =Year!P23 -> 8
B8: =Year!J24 -> 9 | C8: =Year!K24 -> 10 | D8: =Year!L24 -> 11 | E8: =Year!M24 -> 12 | F8: =Year!N24 -> 13 | G8: =Year!O24 -> 14 | H8: =Year!P24 -> 15
B10: =Year!J25 -> 16 | C10: =Year!K25 -> 17 | D10: =Year!L25 -> 18 | E10: =Year!M25 -> 19 | F10: =Year!N25 -> 20 | G10: =Year!O25 -> 21 | H10: =Year!P25 -> 22
B12: =Year!J26 -> 23 | C12: =Year!K26 -> 24 | D12: =Year!L26 -> 25 | E12: =Year!M26 -> 26 | F12: =Year!N26 -> 27 | G12: =Year!O26 -> 28 | H12: =Year!P26 -> 29
B14: =Year!J27 -> 30 | C14: =Year!K27 -> 31 | D14: =Year!L27 | E14: =Year!M27 | F14: =Year!N27 | G14: =Year!O27 | H14: =Year!P27
B17: NOTES

Sheet September
B1: SEPTEMBER | J1: SEP
B3: SUNDAY | C3: MONDAY | D3: TUESDAY | E3: WEDNESDAY | F3: THURSDAY | G3: FRIDAY | H3: SATURDAY
B4: =Year!R22 | C4: =Year!S22 | D4: =Year!T22 -> 1 | E4: =Year!U22 -> 2 | F4: =Year!V22 -> 3 | G4: =Year!W22 -> 4 | H4: =Year!X22 -> 5
B6: =Year!R23 -> 6 | C6: =Year!S23 -> 7 | D6: =Year!T23 -> 8 | E6: =Year!U23 -> 9 | F6: =Year!V23 -> 10 | G6: =Year!W23 -> 11 | H6: =Year!X23 -> 12
B8: =Year!R24 -> 13 | C8: =Year!S24 -> 14 | D8: =Year!T24 -> 15 | E8: =Year!U24 -> 16 | F8: =Year!V24 -> 17 | G8: =Year!W24 -> 18 | H8: =Year!X24 -> 19
B10: =Year!R25 -> 20 | C10: =Year!S25 -> 21 | D10: =Year!T25 -> 22 | E10: =Year!U25 -> 23 | F10: =Year!V25 -> 24 | G10: =Year!W25 -> 25 | H10: =Year!X25 -> 26
B12: =Year!R26 -> 27 | C12: =Year!S26 -> 28 | D12: =Year!T26 -> 29 | E12: =Year!U26 -> 30 | F12: =Year!V26 | G12: =Year!W26 | H12: =Year!X26
B14: =Year!R27 | C14: =Year!S27 | D14: =Year!T27 | E14: =Year!U27 | F14: =Year!V27 | G14: =Year!W27 | H14: =Year!X27
B17: NOTES

Sheet October
B1: OCTOBER | J1: OCT
B3: SUNDAY | C3: MONDAY | D3: TUESDAY | E3: WEDNESDAY | F3: THURSDAY | G3: FRIDAY | H3: SATURDAY
B4: =Year!B31 | C4: =Year!C31 | D4: =Year!D31 | E4: =Year!E31 | F4: =Year!F31 -> 1 | G4: =Year!G31 -> 2 | H4: =Year!H31 -> 3
B6: =Year!B32 -> 4 | C6: =Year!C32 -> 5 | D6: =Year!D32 -> 6 | E6: =Year!E32 -> 7 | F6: =Year!F32 -> 8 | G6: =Year!G32 -> 9 | H6: =Year!H32 -> 10
B8: =Year!B33 -> 11 | C8: =Year!C33 -> 12 | D8: =Year!D33 -> 13 | E8: =Year!E33 -> 14 | F8: =Year!F33 -> 15 | G8: =Year!G33 -> 16 | H8: =Year!H33 -> 17
B10: =Year!B34 -> 18 | C10: =Year!C34 -> 19 | D10: =Year!D34 -> 20 | E10: =Year!E34 -> 21 | F10: =Year!F34 -> 22 | G10: =Year!G34 -> 23 | H10: =Year!H34 -> 24
B12: =Year!B35 -> 25 | C12: =Year!C35 -> 26 | D12: =Year!D35 -> 27 | E12: =Year!E35 -> 28 | F12: =Year!F35 -> 29 | G12: =Year!G35 -> 30 | H12: =Year!H35 -> 31
B14: =Year!B36 | C14: =Year!C36 | D14: =Year!D36 | E14: =Year!E36 | F14: =Year!F36 | G14: =Year!G36 | H14: =Year!H36
B17: NOTES

Sheet November
B1: NOVEMBER | J1: NOV
B3: SUNDAY | C3: MONDAY | D3: TUESDAY | E3: WEDNESDAY | F3: THURSDAY | G3: FRIDAY | H3: SATURDAY
B4: =Year!J31 -> 1 | C4: =Year!K31 -> 2 | D4: =Year!L31 -> 3 | E4: =Year!M31 -> 4 | F4: =Year!N31 -> 5 | G4: =Year!O31 -> 6 | H4: =Year!P31 -> 7
B6: =Year!J32 -> 8 | C6: =Year!K32 -> 9 | D6: =Year!L32 -> 10 | E6: =Year!M32 -> 11 | F6: =Year!N32 -> 12 | G6: =Year!O32 -> 13 | H6: =Year!P32 -> 14
B8: =Year!J33 -> 15 | C8: =Year!K33 -> 16 | D8: =Year!L33 -> 17 | E8: =Year!M33 -> 18 | F8: =Year!N33 -> 19 | G8: =Year!O33 -> 20 | H8: =Year!P33 -> 21
B10: =Year!J34 -> 22 | C10: =Year!K34 -> 23 | D10: =Year!L34 -> 24 | E10: =Year!M34 -> 25 | F10: =Year!N34 -> 26 | G10: =Year!O34 -> 27 | H10: =Year!P34 -> 28
B12: =Year!J35 -> 29 | C12: =Year!K35 -> 30 | D12: =Year!L35 | E12: =Year!M35 | F12: =Year!N35 | G12: =Year!O35 | H12: =Year!P35
B14: =Year!J36 | C14: =Year!K36 | D14: =Year!L36 | E14: =Year!M36 | F14: =Year!N36 | G14: =Year!O36 | H14: =Year!P36
B17: NOTES

Sheet December
B1: DECEMBER | J1: DEC
B3: SUNDAY | C3: MONDAY | D3: TUESDAY | E3: WEDNESDAY | F3: THURSDAY | G3: FRIDAY | H3: SATURDAY
B4: =Year!R31 | C4: =Year!S31 | D4: =Year!T31 -> 1 | E4: =Year!U31 -> 2 | F4: =Year!V31 -> 3 | G4: =Year!W31 -> 4 | H4: =Year!X31 -> 5
B6: =Year!R32 -> 6 | C6: =Year!S32 -> 7 | D6: =Year!T32 -> 8 | E6: =Year!U32 -> 9 | F6: =Year!V32 -> 10 | G6: =Year!W32 -> 11 | H6: =Year!X32 -> 12
B8: =Year!R33 -> 13 | C8: =Year!S33 -> 14 | D8: =Year!T33 -> 15 | E8: =Year!U33 -> 16 | F8: =Year!V33 -> 17 | G8: =Year!W33 -> 18 | H8: =Year!X33 -> 19
B10: =Year!R34 -> 20 | C10: =Year!S34 -> 21 | D10: =Year!T34 -> 22 | E10: =Year!U34 -> 23 | F10: =Year!V34 -> 24 | G10: =Year!W34 -> 25 | H10: =Year!X34 -> 26
B12: =Year!R35 -> 27 | C12: =Year!S35 -> 28 | D12: =Year!T35 -> 29 | E12: =Year!U35 -> 30 | F12: =Year!V35 -> 31 | G12: =Year!W35 | H12: =Year!X35
B14: =Year!R36 | C14: =Year!S36 | D14: =Year!T36 | E14: =Year!U36 | F14: =Year!V36 | G14: =Year!W36 | H14: =Year!X36
B17: NOTES

Sheet Goals
B1: Code | C1: OFF | D1: DEF | E1: ST | F1: Total TTP | G1: Reward (STT Player)
B2: 50/50/50 | C2: 50 | D2: 50 | E2: 50 | F2: 775850 | G2: Marvel
B3: 40/40/30 | C3: 40 | D3: 40 | E3: 30 | F3: 263990 | G3: Mythic & Iconic
B4: 40/30/30 | C4: 40 | D4: 30 | E4: 30 | F4: 179090 | G4: Mythic
B5: 30/40/30 | C5: 30 | D5: 40 | E5: 30 | F5: 189390 | G5: Mythic
B6: 45/30/0 | C6: 45 | D6: 30 | E6: 0 | F6: 240510 | G6: Mythic
B7: 30/45/0 | C7: 30 | D7: 45 | E7: 0 | F7: 263510 | G7: Mythic
B8: 40/40/0 | C8: 40 | D8: 40 | E8: 0 | F8: 249610 | G8: 3x Iconics
B9: 40/20/0 | C9: 40 | D9: 20 | E9: 0 | F9: 133610 | G9: 2x Iconics
B10: 20/20/30 | C10: 20 | D10: 20 | E10: 30 | F10: 44890 | G10: Iconic
B11: 30/20/0 | C11: 30 | D11: 20 | E11: 0 | F11: 59010 | G11: Iconic
B12: 20/30/0 | C12: 20 | D12: 30 | E12: 0 | F12: 61610 | G12: Iconic

Sheet Boost Data
A1: Level | B1: QB | C1: HB/FB | D1: TE | E1: WR | F1: C/OG/OT | G1: Cost | H1: Delta | J1: Level | K1: LB/MLB | L1: CB | M1: S | N1: DT | O1: DE | P1: Cost | Q1: Delta | S1: Level | T1: K | U1: KR | V1: P | W1: PR | X1: Cost | Y1: Delta
A2: 0 | B2: 0 | C2: 0 | D2: 0 | E2: 0 | F2: 0 | G2: 0 | J2: 0 | K2: 0 | L2: 0 | M2: 0 | N2: 0 | O2: 0 | P2: 0 | S2: 0 | T2: 0 | U2: 0 | V2: 0 | W2: 0 | X2: 0
A3: 1 | B3: 1 | C3: 1 | D3: 1 | E3: 1 | F3: 1 | G3: 250 | J3: 1 | K3: 1 | L3: 1 | M3: 1 | N3: 1 | O3: 1 | P3: 250 | S3: 1 | T3: 1 | U3: 1 | V3: 1 | W3: 1 | X3: 100
A4: 2 | B4: 1 | C4: 1 | D4: 1 | E4: 1 | F4: 2 | G4: 530 | H4: 280 | J4: 2 | K4: =K3 -> 1 | L4: =L3 -> 1 | M4: =M3 -> 1 | N4: 2 | O4: 2 | P4: 530 | Q4: 280 | S4: 2 | T4: =T3 -> 1 | U4: =U3 -> 1 | V4: =V3 -> 1 | W4: 2 | X4: 210 | Y4: 110
A5: 3 | B5: 1 | C5: =C4 -> 1 | D5: 2 | E5: 2 | F5: =F4 -> 2 | G5: 830 | H5: 300 | J5: 3 | K5: =K4 -> 1 | L5: 2 | M5: =M4 -> 1 | N5: =N4 -> 2 | O5: =O4 -> 2 | P5: 840 | Q5: 310 | S5: 3 | T5: =T4 -> 1 | U5: =U4 -> 1 | V5: 2 | W5: =W4 -> 2 | X5: 210 | Y5: 0
A6: 4 | B6: 2 | C6: =C5 -> 1 | D6: =D5 -> 2 | E6: =E5 -> 2 | F6: =F5 -> 2 | G6: 1170 | H6: 340 | J6: 4 | K6: 2 | L6: =L5 -> 2 | M6: =M5 -> 1 | N6: =N5 -> 2 | O6: =O5 -> 2 | P6: 1180 | Q6: 340 | S6: 4 | T6: 2 | U6: =U5 -> 1 | V6: =V5 -> 2 | W6: =W5 -> 2 | X6: 460 | Y6: 250
A7: 5 | B7: 2 | C7: 2 | D7: =D6 -> 2 | E7: =E6 -> 2 | F7: =F6 -> 2 | G7: 1540 | H7: 370 | J7: 5 | K7: =K6 -> 2 | L7: =L6 -> 2 | M7: 2 | N7: =N6 -> 2 | O7: =O6 -> 2 | P7: 1560 | Q7: 380 | S7: 5 | T7: =T6 -> 2 | U7: 2 | V7: =V6 -> 2 | W7: =W6 -> 2 | X7: 600 | Y7: 140
A8: 6 | B8: 3 | C8: 3 | D8: 3 | E8: 3 | F8: 3 | G8: 1950 | H8: 410 | J8: 6 | K8: 3 | L8: 3 | M8: 3 | N8: 3 | O8: 3 | P8: 1980 | Q8: 420 | S8: 6 | T8: 3 | U8: 3 | V8: 3 | W8: 3 | X8: 760 | Y8: 160
A9: 7 | B9: 3 | C9: =C8 -> 3 | D9: =D8 -> 3 | E9: =E8 -> 3 | F9: 4 | G9: 2400 | H9: 450 | J9: 7 | K9: =K8 -> 3 | L9: =L8 -> 3 | M9: =M8 -> 3 | N9: 4 | O9: 4 | P9: 2440 | Q9: 460 | S9: 7 | T9: =T8 -> 3 | U9: =U8 -> 3 | V9: =V8 -> 3 | W9: 4 | X9: 930 | Y9: 170
A10: 8 | B10: 3 | C10: =C9 -> 3 | D10: 4 | E10: 4 | F10: =F9 -> 4 | G10: 2900 | H10: 500 | J10: 8 | K10: =K9 -> 3 | L10: 4 | M10: =M9 -> 3 | N10: =N9 -> 4 | O10: =O9 -> 4 | P10: 2950 | Q10: 510 | S10: 8 | T10: =T9 -> 3 | U10: =U9 -> 3 | V10: 4 | W10: =W9 -> 4 | X10: 1120 | Y10: 190
A11: 9 | B11: 4 | C11: =C10 -> 3 | D11: =D10 -> 4 | E11: =E10 -> 4 | F11: =F10 -> 4 | G11: 3450 | H11: 550 | J11: 9 | K11: 4 | L11: =L10 -> 4 | M11: =M10 -> 3 | N11: =N10 -> 4 | O11: =O10 -> 4 | P11: 3520 | Q11: 570 | S11: 9 | T11: 4 | U11: =U10 -> 3 | V11: =V10 -> 4 | W11: =W10 -> 4 | X11: 1320 | Y11: 200
A12: 10 | B12: 4 | C12: 4 | D12: =D11 -> 4 | E12: =E11 -> 4 | F12: =F11 -> 4 | G12: 4060 | H12: 610 | J12: 10 | K12: =K11 -> 4 | L12: =L11 -> 4 | M12: 4 | N12: =N11 -> 4 | O12: =O11 -> 4 | P12: 4150 | Q12: 630 | S12: 10 | T12: =T11 -> 4 | U12: 4 | V12: =V11 -> 4 | W12: =W11 -> 4 | X12: 1540 | Y12: 220
A13: 11 | B13: 5 | C13: 5 | D13: 5 | E13: 5 | F13: 5 | G13: 4740 | H13: 680 | J13: 11 | K13: 5 | L13: 5 | M13: 5 | N13: 5 | O13: 5 | P13: 4850 | Q13: 700 | S13: 11 | T13: 5 | U13: 5 | V13: 5 | W13: 5 | X13: 1780 | Y13: 240
A14: 12 | B14: 5 | C14: =C13 -> 5 | D14: =D13 -> 5 | E14: =E13 -> 5 | F14: 6 | G14: 5460 | H14: 720 | J14: 12 | K14: =K13 -> 5 | L14: =L13 -> 5 | M14: =M13 -> 5 | N14: 6 | O14: 6 | P14: 5650 | Q14: 800 | S14: 12 | T14: =T13 -> 5 | U14: =U13 -> 5 | V14: =V13 -> 5 | W14: 6 | X14: 2050 | Y14: 270
A15: 13 | B15: 5 | C15: =C14 -> 5 | D15: 6 | E15: 6 | F15: =F14 -> 6 | G15: 6260 | H15: 800 | J15: 13 | K15: =K14 -> 5 | L15: 6 | M15: =M14 -> 5 | N15: =N14 -> 6 | O15: =O14 -> 6 | P15: 6500 | Q15: 850 | S15: 13 | T15: =T14 -> 5 | U15: =U14 -> 5 | V15: 6 | W15: =W14 -> 6 | X15: 2340 | Y15: 290
A16: 14 | B16: 6 | C16: =C15 -> 5 | D16: =D15 -> 6 | E16: =E15 -> 6 | F16: =F15 -> 6 | G16: 7160 | H16: 900 | J16: 14 | K16: 6 | L16: =L15 -> 6 | M16: =M15 -> 5 | N16: =N15 -> 6 | O16: =O15 -> 6 | P16: 7450 | Q16: 950 | S16: 14 | T16: 6 | U16: =U15 -> 5 | V16: =V15 -> 6 | W16: =W15 -> 6 | X16: 2660 | Y16: 320
A17: 15 | B17: 6 | C17: 6 | D17: =D16 -> 6 | E17: =E16 -> 6 | F17: =F16 -> 6 | G17: 8160 | H17: 1000 | J17: 15 | K17: =K16 -> 6 | L17: =L16 -> 6 | M17: 6 | N17: =N16 -> 6 | O17: =O16 -> 6 | P17: 8450 | Q17: 1000 | S17: 15 | T17: =T16 -> 6 | U17: 6 | V17: =V16 -> 6 | W17: =W16 -> 6 | X17: 3010 | Y17: 350
A18: 16 | B18: 7 | C18: 7 | D18: 7 | E18: 7 | F18: 7 | G18: 9260 | H18: 1100 | J18: 16 | K18: 7 | L18: 7 | M18: 7 | N18: 7 | O18: 7 | P18: 9650 | Q18: 1200 | S18: 16 | T18: 7 | U18: 7 | V18: 7 | W18: 7 | X18: 3390 | Y18: 380
A19: 17 | B19: 7 | C19: =C18 -> 7 | D19: =D18 -> 7 | E19: =E18 -> 7 | F19: 8 | G19: 10460 | H19: 1200 | J19: 17 | K19: =K18 -> 7 | L19: =L18 -> 7 | M19: =M18 -> 7 | N19: 8 | O19: 8 | P19: 10950 | Q19: 1300 | S19: 17 | T19: =T18 -> 7 | U19: =U18 -> 7 | V19: =V18 -> 7 | W19: 8 | X19: 3800 | Y19: 410
A20: 18 | B20: 7 | C20: =C19 -> 7 | D20: 8 | E20: 8 | F20: =F19 -> 8 | G20: 11760 | H20: 1300 | J20: 18 | K20: =K19 -> 7 | L20: 8 | M20: =M19 -> 7 | N20: =N19 -> 8 | O20: =O19 -> 8 | P20: 12350 | Q20: 1400 | S20: 18 | T20: =T19 -> 7 | U20: =U19 -> 7 | V20: 8 | W20: =W19 -> 8 | X20: 4250 | Y20: 450
A21: 19 | B21: 8 | C21: =C20 -> 7 | D21: =D20 -> 8 | E21: =E20 -> 8 | F21: =F20 -> 8 | G21: 13260 | H21: 1500 | J21: 19 | K21: 8 | L21: =L20 -> 8 | M21: =M20 -> 7 | N21: =N20 -> 8 | O21: =O20 -> 8 | P21: 13950 | Q21: 1600 | S21: 19 | T21: 8 | U21: =U20 -> 7 | V21: =V20 -> 8 | W21: =W20 -> 8 | X21: 4740 | Y21: 490
A22: 20 | B22: 8 | C22: 8 | D22: =D21 -> 8 | E22: =E21 -> 8 | F22: =F21 -> 8 | G22: 14860 | H22: 1600 | J22: 20 | K22: =K21 -> 8 | L22: =L21 -> 8 | M22: 8 | N22: =N21 -> 8 | O22: =O21 -> 8 | P22: 15650 | Q22: 1700 | S22: 20 | T22: =T21 -> 8 | U22: 8 | V22: =V21 -> 8 | W22: =W21 -> 8 | X22: 5280 | Y22: 540
A23: 21 | B23: 9 | C23: 9 | D23: 9 | E23: 9 | F23: 9 | G23: 16660 | H23: 1800 | J23: 21 | K23: 9 | L23: 9 | M23: 9 | N23: 9 | O23: 9 | P23: 17550 | Q23: 1900 | S23: 21 | T23: 9 | U23: 9 | V23: 9 | W23: 9 | X23: 5870 | Y23: 590
A24: 22 | B24: 9 | C24: =C23 -> 9 | D24: =D23 -> 9 | E24: =E23 -> 9 | F24: 10 | G24: 18660 | H24: 2000 | J24: 22 | K24: =K23 -> 9 | L24: =L23 -> 9 | M24: =M23 -> 9 | N24: 10 | O24: 10 | P24: 19650 | Q24: 2100 | S24: 22 | T24: =T23 -> 9 | U24: =U23 -> 9 | V24: =V23 -> 9 | W24: 10 | X24: 6520 | Y24: 650
A25: 23 | B25: 9 | C25: =C24 -> 9 | D25: 10 | E25: 10 | F25: =F24 -> 10 | G25: 20860 | H25: 2200 | J25: 23 | K25: =K24 -> 9 | L25: 10 | M25: =M24 -> 9 | N25: =N24 -> 10 | O25: =O24 -> 10 | P25: 22050 | Q25: 2400 | S25: 23 | T25: =T24 -> 9 | U25: =U24 -> 9 | V25: 10 | W25: =W24 -> 10 | X25: 7230 | Y25: 710
A26: 24 | B26: 10 | C26: =C25 -> 9 | D26: =D25 -> 10 | E26: =E25 -> 10 | F26: =F25 -> 10 | G26: 23260 | H26: 2400 | J26: 24 | K26: 10 | L26: =L25 -> 10 | M26: =M25 -> 9 | N26: =N25 -> 10 | O26: =O25 -> 10 | P26: 24650 | Q26: 2600 | S26: 24 | T26: 10 | U26: =U25 -> 9 | V26: =V25 -> 10 | W26: =W25 -> 10 | X26: 8000 | Y26: 770
A27: 25 | B27: 10 | C27: 10 | D27: =D26 -> 10 | E27: =E26 -> 10 | F27: =F26 -> 10 | G27: 25960 | H27: 2700 | J27: 25 | K27: =K26 -> 10 | L27: =L26 -> 10 | M27: 10 | N27: =N26 -> 10 | O27: =O26 -> 10 | P27: 27550 | Q27: 2900 | S27: 25 | T27: =T26 -> 10 | U27: 10 | V27: =V26 -> 10 | W27: =W26 -> 10 | X27: 8840 | Y27: 840
A28: 26 | B28: 11 | C28: 11 | D28: 11 | E28: 11 | F28: 11 | G28: 28860 | H28: 2900 | J28: 26 | K28: 11 | L28: 11 | M28: 11 | N28: 11 | O28: 11 | P28: 30750 | Q28: 3200 | S28: 26 | T28: 11 | U28: 11 | V28: 11 | W28: 11 | X28: 9760 | Y28: 920
A29: 27 | B29: 11 | C29: =C28 -> 11 | D29: =D28 -> 11 | E29: =E28 -> 11 | F29: 12 | G29: 31960 | H29: 3100 | J29: 27 | K29: =K28 -> 11 | L29: =L28 -> 11 | M29: =M28 -> 11 | N29: 12 | O29: 12 | P29: 34150 | Q29: 3400 | S29: 27 | T29: =T28 -> 11 | U29: =U28 -> 11 | V29: =V28 -> 11 | W29: 12 | X29: 10770 | Y29: 1010
A30: 28 | B30: 11 | C30: =C29 -> 11 | D30: 12 | E30: 12 | F30: =F29 -> 12 | G30: 35360 | H30: 3400 | J30: 28 | K30: =K29 -> 11 | L30: 12 | M30: =M29 -> 11 | N30: =N29 -> 12 | O30: =O29 -> 12 | P30: 37950 | Q30: 3800 | S30: 28 | T30: =T29 -> 11 | U30: =U29 -> 11 | V30: 12 | W30: =W29 -> 12 | X30: 11870 | Y30: 1100
A31: 29 | B31: 12 | C31: =C30 -> 11 | D31: =D30 -> 12 | E31: =E30 -> 12 | F31: =F30 -> 12 | G31: 39160 | H31: 3800 | J31: 29 | K31: 12 | L31: =L30 -> 12 | M31: =M30 -> 11 | N31: =N30 -> 12 | O31: =O30 -> 12 | P31: 42150 | Q31: 4200 | S31: 29 | T31: 12 | U31: =U30 -> 11 | V31: =V30 -> 12 | W31: =W30 -> 12 | X31: 13070 | Y31: 1200
A32: 30 | B32: 12 | C32: 12 | D32: =D31 -> 12 | E32: =E31 -> 12 | F32: =F31 -> 12 | G32: 43360 | H32: 4200 | J32: 30 | K32: =K31 -> 12 | L32: =L31 -> 12 | M32: 12 | N32: =N31 -> 12 | O32: =O31 -> 12 | P32: 46750 | Q32: 4600 | S32: 30 | T32: =T31 -> 12 | U32: 12 | V32: =V31 -> 12 | W32: =W31 -> 12 | X32: 14380 | Y32: 1310
A33: 31 | B33: 13 | C33: 13 | D33: 13 | E33: 13 | F33: 13 | G33: 47960 | H33: 4600 | J33: 31 | K33: 13 | L33: 13 | M33: 13 | N33: 13 | O33: 13 | P33: 51580 | Q33: 4830 | S33: 31 | T33: 13 | U33: 13 | V33: 13 | W33: 13 | X33: 15820 | Y33: 1440
A34: 32 | B34: 13 | C34: =C33 -> 13 | D34: =D33 -> 13 | E34: =E33 -> 13 | F34: 14 | G34: 53060 | H34: 5100 | J34: 32 | K34: =K33 -> 13 | L34: =L33 -> 13 | M34: =M33 -> 13 | N34: 14 | O34: 14 | P34: 57550 | Q34: 5970 | S34: 32 | T34: =T33 -> 13 | U34: =U33 -> 13 | V34: =V33 -> 13 | W34: 14 | X34: 17390 | Y34: 1570
A35: 33 | B35: 13 | C35: =C34 -> 13 | D35: 14 | E35: 14 | F35: =F34 -> 14 | G35: 58660 | H35: 5600 | J35: 33 | K35: =K34 -> 13 | L35: 14 | M35: =M34 -> 13 | N35: =N34 -> 14 | O35: =O34 -> 14 | P35: 63850 | Q35: 6300 | S35: 33 | T35: =T34 -> 13 | U35: =U34 -> 13 | V35: 14 | W35: =W34 -> 14 | X35: 19110 | Y35: 1720
A36: 34 | B36: 14 | C36: =C35 -> 13 | D36: =D35 -> 14 | E36: =E35 -> 14 | F36: =F35 -> 14 | G36: 64860 | H36: 6200 | J36: 34 | K36: 14 | L36: =L35 -> 14 | M36: =M35 -> 13 | N36: =N35 -> 14 | O36: =O35 -> 14 | P36: 70850 | Q36: 7000 | S36: 34 | T36: 14 | U36: =U35 -> 13 | V36: =V35 -> 14 | W36: =W35 -> 14 | X36: 20990 | Y36: 1880
A37: 35 | B37: 14 | C37: 14 | D37: =D36 -> 14 | E37: =E36 -> 14 | F37: =F36 -> 14 | G37: 71660 | H37: 6800 | J37: 35 | K37: =K36 -> 14 | L37: =L36 -> 14 | M37: 14 | N37: =N36 -> 14 | O37: =O36 -> 14 | P37: 78850 | Q37: 8000 | S37: 35 | T37: =T36 -> 14 | U37: 14 | V37: =V36 -> 14 | W37: =W36 -> 14 | X37: 23040 | Y37: 2050
A38: 36 | B38: 15 | C38: 15 | D38: 15 | E38: 15 | F38: 15 | G38: 79160 | H38: 7500 | J38: 36 | K38: 15 | L38: 15 | M38: 15 | N38: 15 | O38: 15 | P38: 87150 | Q38: 8300 | S38: 36 | T38: 15 | U38: 15 | V38: 15 | W38: 15 | X38: 25280 | Y38: 2240
A39: 37 | B39: 15 | C39: =C38 -> 15 | D39: =D38 -> 15 | E39: =E38 -> 15 | F39: 16 | G39: 87460 | H39: 8300 | J39: 37 | K39: =K38 -> 15 | L39: =L38 -> 15 | M39: =M38 -> 15 | N39: 16 | O39: 16 | P39: 96650 | Q39: 9500 | S39: 37 | T39: =T38 -> 15 | U39: =U38 -> 15 | V39: =V38 -> 15 | W39: 16 | X39: 27730 | Y39: 2450
A40: 38 | B40: 15 | C40: =C39 -> 15 | D40: 16 | E40: 16 | F40: =F39 -> 16 | G40: 96660 | H40: 9200 | J40: 38 | K40: =K39 -> 15 | L40: 16 | M40: =M39 -> 15 | N40: =N39 -> 16 | O40: =O39 -> 16 | P40: 107150 | Q40: 10500 | S40: 38 | T40: =T39 -> 15 | U40: =U39 -> 15 | V40: 16 | W40: =W39 -> 16 | X40: 30410 | Y40: 2680
A41: 39 | B41: 16 | C41: =C40 -> 15 | D41: =D40 -> 16 | E41: =E40 -> 16 | F41: =F40 -> 16 | G41: 106760 | H41: 10100 | J41: 39 | K41: 16 | L41: =L40 -> 16 | M41: =M40 -> 15 | N41: =N40 -> 16 | O41: =O40 -> 16 | P41: 118750 | Q41: 11600 | S41: 39 | T41: 16 | U41: =U40 -> 15 | V41: =V40 -> 16 | W41: =W40 -> 16 | X41: 33330 | Y41: 2920
A42: 40 | B42: 16 | C42: 16 | D42: =D41 -> 16 | E42: =E41 -> 16 | F42: =F41 -> 16 | G42: 117960 | H42: 11200 | J42: 40 | K42: =K41 -> 16 | L42: =L41 -> 16 | M42: 16 | N42: =N41 -> 16 | O42: =O41 -> 16 | P42: 131650 | Q42: 12900 | S42: 40 | T42: =T41 -> 16 | U42: 16 | V42: =V41 -> 16 | W42: =W41 -> 16 | X42: 36530 | Y42: 3200
A43: 41 | B43: 17 | C43: 17 | D43: 17 | E43: 17 | F43: 17 | G43: 130260 | H43: 12300 | J43: 41 | K43: 17 | L43: 17 | M43: 17 | N43: 17 | O43: 17 | P43: 145950 | Q43: 14300 | S43: 41 | T43: 17 | U43: 17 | V43: 17 | W43: 17 | X43: 40020 | Y43: 3490
A44: 42 | B44: 17 | C44: =C43 -> 17 | D44: =D43 -> 17 | E44: =E43 -> 17 | F44: 18 | G44: 143860 | H44: 13600 | J44: 42 | K44: =K43 -> 17 | L44: =L43 -> 17 | M44: =M43 -> 17 | N44: 18 | O44: 18 | P44: 161750 | Q44: 15800 | S44: 42 | T44: =T43 -> 17 | U44: =U43 -> 17 | V44: =V43 -> 17 | W44: 18 | X44: 43840 | Y44: 3820
A45: 43 | B45: 17 | C45: =C44 -> 17 | D45: 18 | E45: 18 | F45: =F44 -> 18 | G45: 158860 | H45: 15000 | J45: 43 | K45: =K44 -> 17 | L45: 18 | M45: =M44 -> 17 | N45: =N44 -> 18 | O45: =O44 -> 18 | P45: 179250 | Q45: 17500 | S45: 43 | T45: =T44 -> 17 | U45: =U44 -> 17 | V45: 18 | W45: =W44 -> 18 | X45: 48010 | Y45: 4170
A46: 44 | B46: 18 | C46: =C45 -> 17 | D46: =D45 -> 18 | E46: =E45 -> 18 | F46: =F45 -> 18 | G46: 175460 | H46: 16600 | J46: 44 | K46: 18 | L46: =L45 -> 18 | M46: =M45 -> 17 | N46: =N45 -> 18 | O46: =O45 -> 18 | P46: 198650 | Q46: 19400 | S46: 44 | T46: 18 | U46: =U45 -> 17 | V46: =V45 -> 18 | W46: =W45 -> 18 | X46: 52570 | Y46: 4560
A47: 45 | B47: 18 | C47: 19 | D47: =D46 -> 18 | E47: =E46 -> 18 | F47: =F46 -> 18 | G47: 193760 | H47: 18300 | J47: 45 | K47: =K46 -> 18 | L47: =L46 -> 18 | M47: 18 | N47: =N46 -> 18 | O47: =O46 -> 18 | P47: 220150 | Q47: 21500 | S47: 45 | T47: =T46 -> 18 | U47: 18 | V47: =V46 -> 18 | W47: =W46 -> 18 | X47: 57550 | Y47: 4980
A48: 46 | B48: 19 | C48: 19 | D48: 19 | E48: 19 | F48: 19 | G48: 213960 | H48: 20200 | J48: 46 | K48: 19 | L48: 19 | M48: 19 | N48: 19 | O48: 19 | P48: 243950 | Q48: 23800 | S48: 46 | T48: 19 | U48: 19 | V48: 19 | W48: 19 | X48: 63000 | Y48: 5450
A49: 47 | B49: 19 | C49: =C48 -> 19 | D49: =D48 -> 19 | E49: =E48 -> 19 | F49: 20 | G49: 236190 | H49: 22230 | J49: 47 | K49: =K48 -> 19 | L49: =L48 -> 19 | M49: =M48 -> 19 | N49: 20 | O49: 20 | P49: 270350 | Q49: 26400 | S49: 47 | T49: =T48 -> 19 | U49: =U48 -> 19 | V49: =V48 -> 19 | W49: 20 | X49: 68950 | Y49: 5950
A50: 48 | B50: 20 | C50: =C49 -> 19 | D50: 20 | E50: 20 | F50: =F49 -> 20 | G50: 260660 | H50: 24470 | J50: 48 | K50: =K49 -> 19 | L50: 20 | M50: =M49 -> 19 | N50: =N49 -> 20 | O50: =O49 -> 20 | P50: 299550 | Q50: 29200 | S50: 48 | T50: =T49 -> 19 | U50: =U49 -> 19 | V50: 20 | W50: =W49 -> 20 | X50: 75460 | Y50: 6510
A51: 49 | B51: 20 | C51: =C50 -> 19 | D51: =D50 -> 20 | E51: =E50 -> 20 | F51: =F50 -> 20 | G51: 287760 | H51: 27100 | J51: 49 | K51: 20 | L51: =L50 -> 20 | M51: =M50 -> 19 | N51: =N50 -> 20 | O51: =O50 -> 20 | P51: 331950 | Q51: 32400 | S51: 49 | T51: 20 | U51: =U50 -> 19 | V51: =V50 -> 20 | W51: =W50 -> 20 | X51: 82570 | Y51: 7110
A52: 50 | B52: 20 | C52: 20 | D52: =D51 -> 20 | E52: =E51 -> 20 | F52: =F51 -> 20 | G52: 317660 | H52: 29900 | J52: 50 | K52: =K51 -> 20 | L52: =L51 -> 20 | M52: 20 | N52: =N51 -> 20 | O52: =O51 -> 20 | P52: 367850 | Q52: 35900 | S52: 50 | T52: =T51 -> 20 | U52: 20 | V52: =V51 -> 20 | W52: =W51 -> 20 | X52: 90340 | Y52: 7770
